Workbook

Sheet Tesoreria Overview
B1: #VALUE! | C1: SEGUIMIENTO DE TESORERIA
C2: ENERO | D2: FEBRERO | E2: MARZO | F2: ABRIL | G2: MAYO | H2: JUNIO | I2: JULIO | J2: AGOSTO | K2: SEPTIEMBRE | L2: OCTUBRE | M2: NOVIEMBRE | N2: DICIEMBRE
B3: Saldo inicial [Saldo en cuenta] | C3: 0 | D3: =C9 -> -12371.88 | E3: =D9 -> -32785.03 | F3: =E9 -> -51579.18 | G3: =F9 -> -50114.18 | H3: =G9 -> -73180.32 | I3: =H9 -> -63676.84 | J3: =I9 -> 22632.98 | K3: =J9 -> 25447.944 | ... N3: =M9 -> 126673.11
B4: Ingresos totales | C4: =C24 -> 22044 | D4: =D24 -> 16168 | E4: =E24 -> 53520 | F4: =F24 -> 32210 | G4: =G24 -> 12675 | H4: =H24 -> 43615 | I4: =I24 -> 132200 | J4: =J24 -> 85832.5 | ... N4: =N24 -> 0 | O4: =SUM(C4:N4) -> 568989.5
B5: Ingresos Estimados | C5: =Estimado!C22+C31 -> 0 | D5: =Estimado!D22+D31 -> 0 | E5: =Estimado!E22+E31 -> 0 | F5: =Estimado!F22+F31 -> 0 | G5: =Estimado!G22+G31 -> 0 | H5: =Estimado!H22+H31 -> 0 | I5: =Estimado!I22+I31 -> 0 | J5: =Estimado!J22+J31 -> 4000 | ... N5: =Estimado!N22+N31 -> 0 | O5: =SUM(C5:N5) -> 150610
B6: Egresos Totales | C6: =C95 -> 34415.88 | D6: =D95 -> 36581.15 | E6: =E95 -> 72314.15 | F6: =F95 -> 30745 | G6: =G95 -> 35741.14 | H6: =H95 -> 34111.52 | I6: =I95 -> 45890.18 | J6: =J95 -> 83017.536 | ... N6: =N95 -> 0 | O6: =SUM(C6:N6) -> 442316.39
B7: Egresos Estimados | C7: =Estimado!C74 -> 0 | D7: =Estimado!D74 -> 0 | E7: =Estimado!E74 -> 0 | F7: =Estimado!F74 -> 0 | G7: =Estimado!G74 -> 0 | H7: =Estimado!H74 -> 0 | I7: =Estimado!I74 -> 0 | J7: =Estimado!J74 -> 0 | ... N7: =Estimado!N74 -> 0 | O7: =SUM(C7:N7) -> 0
B8: INGRESOS NETOS | C8: =C4-C6 -> -12371.88 | D8: =D4-D6 -> -20413.15 | E8: =E4-E6 -> -18794.15 | F8: =F4-F6 -> 1465 | G8: =G4-G6 -> -23066.14 | H8: =H4-H6 -> 9503.48 | I8: =I4-I6 -> 86309.82 | J8: =J4-J6 -> 2814.9638 | ... N8: =N4-N6 -> 0 | O8: =SUM(C8:N8) -> 126673.11
B9: Saldo final proyectado | C9: =C4-C6+C3 -> -12371.88 | D9: =D4-D6+D3 -> -32785.03 | E9: =E4-E6+E3 -> -51579.18 | F9: =F4-F6+F3 -> -50114.18 | G9: =G4-G6+G3 -> -73180.32 | H9: =H4-H6+H3 -> -63676.84 | I9: =I4-I6+I3 -> 22632.98 | J9: =J4-J6+J3 -> 25447.944 | ... N9: =N4-N6+N3 -> 126673.11
B11: INGRESOS
B13: Venta de Alevines | C13: =SUMIF(Enero_2024[CATEGORÍA],$B13,Enero_2024[INGRESO]) -> 22044 | D13: =SUMIF(Febrero_2024[CATEGORÍA],$B13,Febrero_2024[INGRESO]) -> 15818 | E13: =SUMIF(Marzo_2024[CATEGORÍA],$B13,Marzo_2024[INGRESO]) -> 53120 | F13: =SUMIF(Abril_2024[CATEGORÍA],$B13,Abril_2024[INGRESO]) -> 32080 | G13: =SUMIF(Mayo_2024[CATEGORÍA],$B13,Mayo_2024[INGRESO]) -> 12675 | H13: =SUMIF(Junio_2024[CATEGORÍA],$B13,Junio_2024[INGRESO]) -> 43615 | I13: =SUMIF(Julio_2024[CATEGORÍA],$B13,Julio_2024[INGRESO]) -> 132200 | J13: =SUMIF(Agosto_2024[CATEGORÍA],$B13,Agosto_2024[INGRESO]) -> 84997.5 | K13: =SUMIF(Septiembre_2024[CATEGORÍA],$B13,Septiembre_2024[INGRESO]) -> 99340 | L13: =SUMIF(Octubre_2024[CATEGORÍA],$B13,Octubre_2024[INGRESO]) -> 66120 | M13: =SUMIF(Noviembre_2024[CATEGORÍA],$B13,Noviembre_2024[INGRESO]) -> 0 | N13: =SUMIF(Diciembre_2024[CATEGORÍA],$B13,Diciembre_2024[INGRESO]) -> 0 | O13: =SUM(D13:N13) -> 539965.5
B14: Venta de Mojarras (Kg) | C14: =SUMIF(Enero_2024[CATEGORÍA],$B14,Enero_2024[INGRESO]) -> 0 | D14: =SUMIF(Febrero_2024[CATEGORÍA],$B14,Febrero_2024[INGRESO]) -> 0 | E14: =SUMIF(Marzo_2024[CATEGORÍA],$B14,Marzo_2024[INGRESO]) -> 0 | F14: =SUMIF(Abril_2024[CATEGORÍA],$B14,Abril_2024[INGRESO]) -> 0 | G14: =SUMIF(Mayo_2024[CATEGORÍA],$B14,Mayo_2024[INGRESO]) -> 0 | H14: =SUMIF(Junio_2024[CATEGORÍA],$B14,Junio_2024[INGRESO]) -> 0 | I14: =SUMIF(Julio_2024[CATEGORÍA],$B14,Julio_2024[INGRESO]) -> 0 | J14: =SUMIF(Agosto_2024[CATEGORÍA],$B14,Agosto_2024[INGRESO]) -> 0 | K14: =SUMIF(Septiembre_2024[CATEGORÍA],$B14,Septiembre_2024[INGRESO]) -> 0 | L14: =SUMIF(Octubre_2024[CATEGORÍA],$B14,Octubre_2024[INGRESO]) -> 0 | M14: =SUMIF(Noviembre_2024[CATEGORÍA],$B14,Noviembre_2024[INGRESO]) -> 0 | N14: =SUMIF(Diciembre_2024[CATEGORÍA],$B14,Diciembre_2024[INGRESO]) -> 0 | O14: =SUM(D14:N14) -> 0
B15: Venta de Alimento | C15: =SUMIF(Enero_2024[CATEGORÍA],$B15,Enero_2024[INGRESO]) -> 0 | D15: =SUMIF(Febrero_2024[CATEGORÍA],$B15,Febrero_2024[INGRESO]) -> 350 | E15: =SUMIF(Marzo_2024[CATEGORÍA],$B15,Marzo_2024[INGRESO]) -> 400 | F15: =SUMIF(Abril_2024[CATEGORÍA],$B15,Abril_2024[INGRESO]) -> 130 | G15: =SUMIF(Mayo_2024[CATEGORÍA],$B15,Mayo_2024[INGRESO]) -> 0 | H15: =SUMIF(Junio_2024[CATEGORÍA],$B15,Junio_2024[INGRESO]) -> 0 | I15: =SUMIF(Julio_2024[CATEGORÍA],$B15,Julio_2024[INGRESO]) -> 0 | J15: =SUMIF(Agosto_2024[CATEGORÍA],$B15,Agosto_2024[INGRESO]) -> 835 | K15: =SUMIF(Septiembre_2024[CATEGORÍA],$B15,Septiembre_2024[INGRESO]) -> 5265 | L15: =SUMIF(Octubre_2024[CATEGORÍA],$B15,Octubre_2024[INGRESO]) -> 0 | M15: =SUMIF(Noviembre_2024[CATEGORÍA],$B15,Noviembre_2024[INGRESO]) -> 0 | N15: =SUMIF(Diciembre_2024[CATEGORÍA],$B15,Diciembre_2024[INGRESO]) -> 0 | O15: =SUM(D15:N15) -> 6980
B16: Venta Medicamentos/Vitaminas | C16: =SUMIF(Enero_2024[CATEGORÍA],$B16,Enero_2024[INGRESO]) -> 0 | D16: =SUMIF(Febrero_2024[CATEGORÍA],$B16,Febrero_2024[INGRESO]) -> 0 | E16: =SUMIF(Marzo_2024[CATEGORÍA],$B16,Marzo_2024[INGRESO]) -> 0 | F16: =SUMIF(Abril_2024[CATEGORÍA],$B16,Abril_2024[INGRESO]) -> 0 | G16: =SUMIF(Mayo_2024[CATEGORÍA],$B16,Mayo_2024[INGRESO]) -> 0 | H16: =SUMIF(Junio_2024[CATEGORÍA],$B16,Junio_2024[INGRESO]) -> 0 | I16: =SUMIF(Julio_2024[CATEGORÍA],$B16,Julio_2024[INGRESO]) -> 0 | J16: =SUMIF(Agosto_2024[CATEGORÍA],$B16,Agosto_2024[INGRESO]) -> 0 | K16: =SUMIF(Septiembre_2024[CATEGORÍA],$B16,Septiembre_2024[INGRESO]) -> 0 | L16: =SUMIF(Octubre_2024[CATEGORÍA],$B16,Octubre_2024[INGRESO]) -> 0 | M16: =SUMIF(Noviembre_2024[CATEGORÍA],$B16,Noviembre_2024[INGRESO]) -> 0 | N16: =SUMIF(Diciembre_2024[CATEGORÍA],$B16,Diciembre_2024[INGRESO]) -> 0 | O16: =SUM(D16:N16) -> 0
B17: Ingresos por intereses | C17: =SUMIF(Enero_2024[CATEGORÍA],$B17,Enero_2024[INGRESO]) -> 0 | D17: =SUMIF(Febrero_2024[CATEGORÍA],$B17,Febrero_2024[INGRESO]) -> 0 | E17: =SUMIF(Marzo_2024[CATEGORÍA],$B17,Marzo_2024[INGRESO]) -> 0 | F17: =SUMIF(Abril_2024[CATEGORÍA],$B17,Abril_2024[INGRESO]) -> 0 | G17: =SUMIF(Mayo_2024[CATEGORÍA],$B17,Mayo_2024[INGRESO]) -> 0 | H17: =SUMIF(Junio_2024[CATEGORÍA],$B17,Junio_2024[INGRESO]) -> 0 | I17: =SUMIF(Julio_2024[CATEGORÍA],$B17,Julio_2024[INGRESO]) -> 0 | J17: =SUMIF(Agosto_2024[CATEGORÍA],$B17,Agosto_2024[INGRESO]) -> 0 | K17: =SUMIF(Septiembre_2024[CATEGORÍA],$B17,Septiembre_2024[INGRESO]) -> 0 | L17: =SUMIF(Octubre_2024[CATEGORÍA],$B17,Octubre_2024[INGRESO]) -> 0 | M17: =SUMIF(Noviembre_2024[CATEGORÍA],$B17,Noviembre_2024[INGRESO]) -> 0 | N17: =SUMIF(Diciembre_2024[CATEGORÍA],$B17,Diciembre_2024[INGRESO]) -> 0 | O17: =SUM(D17:N17) -> 0
B18: Servicios de Gestion | C18: =SUMIF(Enero_2024[CATEGORÍA],$B18,Enero_2024[INGRESO]) -> 0 | D18: =SUMIF(Febrero_2024[CATEGORÍA],$B18,Febrero_2024[INGRESO]) -> 0 | E18: =SUMIF(Marzo_2024[CATEGORÍA],$B18,Marzo_2024[INGRESO]) -> 0 | F18: =SUMIF(Abril_2024[CATEGORÍA],$B18,Abril_2024[INGRESO]) -> 0 | G18: =SUMIF(Mayo_2024[CATEGORÍA],$B18,Mayo_2024[INGRESO]) -> 0 | H18: =SUMIF(Junio_2024[CATEGORÍA],$B18,Junio_2024[INGRESO]) -> 0 | I18: =SUMIF(Julio_2024[CATEGORÍA],$B18,Julio_2024[INGRESO]) -> 0 | J18: =SUMIF(Agosto_2024[CATEGORÍA],$B18,Agosto_2024[INGRESO]) -> 0 | K18: =SUMIF(Septiembre_2024[CATEGORÍA],$B18,Septiembre_2024[INGRESO]) -> 0 | L18: =SUMIF(Octubre_2024[CATEGORÍA],$B18,Octubre_2024[INGRESO]) -> 0 | M18: =SUMIF(Noviembre_2024[CATEGORÍA],$B18,Noviembre_2024[INGRESO]) -> 0 | N18: =SUMIF(Diciembre_2024[CATEGORÍA],$B18,Diciembre_2024[INGRESO]) -> 0 | O18: =SUM(D18:N18) -> 0
B19: Reembolsos | C19: =SUMIF(Enero_2024[CATEGORÍA],$B19,Enero_2024[INGRESO]) -> 0 | D19: =SUMIF(Febrero_2024[CATEGORÍA],$B19,Febrero_2024[INGRESO]) -> 0 | E19: =SUMIF(Marzo_2024[CATEGORÍA],$B19,Marzo_2024[INGRESO]) -> 0 | F19: =SUMIF(Abril_2024[CATEGORÍA],$B19,Abril_2024[INGRESO]) -> 0 | G19: =SUMIF(Mayo_2024[CATEGORÍA],$B19,Mayo_2024[INGRESO]) -> 0 | H19: =SUMIF(Junio_2024[CATEGORÍA],$B19,Junio_2024[INGRESO]) -> 0 | I19: =SUMIF(Julio_2024[CATEGORÍA],$B19,Julio_2024[INGRESO]) -> 0 | J19: =SUMIF(Agosto_2024[CATEGORÍA],$B19,Agosto_2024[INGRESO]) -> 0 | K19: =SUMIF(Septiembre_2024[CATEGORÍA],$B19,Septiembre_2024[INGRESO]) -> 0 | L19: =SUMIF(Octubre_2024[CATEGORÍA],$B19,Octubre_2024[INGRESO]) -> 0 | M19: =SUMIF(Noviembre_2024[CATEGORÍA],$B19,Noviembre_2024[INGRESO]) -> 0 | N19: =SUMIF(Diciembre_2024[CATEGORÍA],$B19,Diciembre_2024[INGRESO]) -> 0 | O19: =SUM(D19:N19) -> 0
B20: Comisiones | C20: =SUMIF(Enero_2024[CATEGORÍA],$B20,Enero_2024[INGRESO]) -> 0 | D20: =SUMIF(Febrero_2024[CATEGORÍA],$B20,Febrero_2024[INGRESO]) -> 0 | E20: =SUMIF(Marzo_2024[CATEGORÍA],$B20,Marzo_2024[INGRESO]) -> 0 | F20: =SUMIF(Abril_2024[CATEGORÍA],$B20,Abril_2024[INGRESO]) -> 0 | G20: =SUMIF(Mayo_2024[CATEGORÍA],$B20,Mayo_2024[INGRESO]) -> 0 | H20: =SUMIF(Junio_2024[CATEGORÍA],$B20,Junio_2024[INGRESO]) -> 0 | I20: =SUMIF(Julio_2024[CATEGORÍA],$B20,Julio_2024[INGRESO]) -> 0 | J20: =SUMIF(Agosto_2024[CATEGORÍA],$B20,Agosto_2024[INGRESO]) -> 0 | K20: =SUMIF(Septiembre_2024[CATEGORÍA],$B20,Septiembre_2024[INGRESO]) -> 0 | L20: =SUMIF(Octubre_2024[CATEGORÍA],$B20,Octubre_2024[INGRESO]) -> 0 | M20: =SUMIF(Noviembre_2024[CATEGORÍA],$B20,Noviembre_2024[INGRESO]) -> 0 | N20: =SUMIF(Diciembre_2024[CATEGORÍA],$B20,Diciembre_2024[INGRESO]) -> 0 | O20: =SUM(D20:N20) -> 0
B21: Fondeo Externo y Pasivos | C21: =SUMIF(Enero_2024[CATEGORÍA],$B21,Enero_2024[INGRESO]) -> 0 | D21: =SUMIF(Febrero_2024[CATEGORÍA],$B21,Febrero_2024[INGRESO]) -> 0 | E21: =SUMIF(Marzo_2024[CATEGORÍA],$B21,Marzo_2024[INGRESO]) -> 0 | F21: =SUMIF(Abril_2024[CATEGORÍA],$B21,Abril_2024[INGRESO]) -> 0 | G21: =SUMIF(Mayo_2024[CATEGORÍA],$B21,Mayo_2024[INGRESO]) -> 0 | H21: =SUMIF(Junio_2024[CATEGORÍA],$B21,Junio_2024[INGRESO]) -> 0 | I21: =SUMIF(Julio_2024[CATEGORÍA],$B21,Julio_2024[INGRESO]) -> 0 | J21: =SUMIF(Agosto_2024[CATEGORÍA],$B21,Agosto_2024[INGRESO]) -> 0 | K21: =SUMIF(Septiembre_2024[CATEGORÍA],$B21,Septiembre_2024[INGRESO]) -> 0 | L21: =SUMIF(Octubre_2024[CATEGORÍA],$B21,Octubre_2024[INGRESO]) -> 0 | M21: =SUMIF(Noviembre_2024[CATEGORÍA],$B21,Noviembre_2024[INGRESO]) -> 0 | N21: =SUMIF(Diciembre_2024[CATEGORÍA],$B21,Diciembre_2024[INGRESO]) -> 0 | O21: =SUM(D21:N21) -> 0
B22: Miscelaneo | C22: =SUMIF(Enero_2024[CATEGORÍA],$B22,Enero_2024[INGRESO]) -> 0 | D22: =SUMIF(Febrero_2024[CATEGORÍA],$B22,Febrero_2024[INGRESO]) -> 0 | E22: =SUMIF(Marzo_2024[CATEGORÍA],$B22,Marzo_2024[INGRESO]) -> 0 | F22: =SUMIF(Abril_2024[CATEGORÍA],$B22,Abril_2024[INGRESO]) -> 0 | G22: =SUMIF(Mayo_2024[CATEGORÍA],$B22,Mayo_2024[INGRESO]) -> 0 | H22: =SUMIF(Junio_2024[CATEGORÍA],$B22,Junio_2024[INGRESO]) -> 0 | I22: =SUMIF(Julio_2024[CATEGORÍA],$B22,Julio_2024[INGRESO]) -> 0 | J22: =SUMIF(Agosto_2024[CATEGORÍA],$B22,Agosto_2024[INGRESO]) -> 0 | K22: =SUMIF(Septiembre_2024[CATEGORÍA],$B22,Septiembre_2024[INGRESO]) -> 0 | L22: =SUMIF(Octubre_2024[CATEGORÍA],$B22,Octubre_2024[INGRESO]) -> 0 | M22: =SUMIF(Noviembre_2024[CATEGORÍA],$B22,Noviembre_2024[INGRESO]) -> 0 | N22: =SUMIF(Diciembre_2024[CATEGORÍA],$B22,Diciembre_2024[INGRESO]) -> 0 | O22: =SUM(D22:N22) -> 0
B24: TOTAL | C24: =SUM(C13:C22) -> 22044 | D24: =SUM(D13:D22) -> 16168 | E24: =SUM(E13:E22) -> 53520 | F24: =SUM(F13:F22) -> 32210 | G24: =SUM(G13:G22) -> 12675 | H24: =SUM(H13:H22) -> 43615 | I24: =SUM(I13:I22) -> 132200 | J24: =SUM(J13:J22) -> 85832.5 | ... O24: =SUM(O13:O22) -> 546945.5
B26: CAPITAL
B28: Fondo Liquido | C28: =SUMIF(Enero_2024[CATEGORÍA],$B28,Enero_2024[INGRESO]) -> 0 | D28: =SUMIF(Febrero_2024[CATEGORÍA],$B28,Febrero_2024[INGRESO]) -> 0 | E28: =SUMIF(Marzo_2024[CATEGORÍA],$B28,Marzo_2024[INGRESO]) -> 0 | F28: =SUMIF(Abril_2024[CATEGORÍA],$B28,Abril_2024[INGRESO]) -> 0 | G28: =SUMIF(Mayo_2024[CATEGORÍA],$B28,Mayo_2024[INGRESO]) -> 0 | H28: =SUMIF(Junio_2024[CATEGORÍA],$B28,Junio_2024[INGRESO]) -> 0 | I28: =SUMIF(Julio_2024[CATEGORÍA],$B28,Julio_2024[INGRESO]) -> 0 | J28: =SUMIF(Agosto_2024[CATEGORÍA],$B28,Agosto_2024[INGRESO]) -> 0 | K28: =SUMIF(Septiembre_2024[CATEGORÍA],$B28,Septiembre_2024[INGRESO]) -> 0 | L28: =SUMIF(Octubre_2024[CATEGORÍA],$B28,Octubre_2024[INGRESO]) -> 0 | M28: =SUMIF(Noviembre_2024[CATEGORÍA],$B28,Noviembre_2024[INGRESO]) -> 0 | N28: =SUMIF(Diciembre_2024[CATEGORÍA],$B28,Diciembre_2024[INGRESO]) -> 0 | O28: =SUM(D28:N28) -> 0
B29: Capital en Caja de Ahorro | C29: =C41 -> 2600 | D29: =C29+D41 -> 5800 | E29: =D29+E41 -> 10200 | F29: =E29+F41 -> 13400 | G29: =F29+G41 -> 16600 | H29: =G29+H41 -> 19600 | I29: =H29+I41 -> 22800 | J29: =I29+J41 -> 27600 | K29: =J29+K41 -> 30800 | ... N29: =M29+N41 -> 30800 | O29: =SUM(D29:N29) -> 239200
B30: Intereses Caja de Ahorro | C30: =SUMIF(Enero_2024[CATEGORÍA],$B30,Enero_2024[INGRESO]) -> 0 | D30: =SUMIF(Febrero_2024[CATEGORÍA],$B30,Febrero_2024[INGRESO])+C30 -> 0 | E30: =SUMIF(Febrero_2024[SUB CATEGORIA],$B30,Febrero_2024[EGRESO])+D30 -> 0 | F30: =SUMIF(Febrero_2024[EQUILIBRAR],$B30,Febrero_2024[BENEFICIARIO/PROVEEDOR])+E30 -> 0 | G30: =SUMIF(Febrero_2024[CUENTA],$B30,Febrero_2024[NO. FACTURA])+F30 -> 0 | H30: =SUMIF(Febrero_2024[FECHA],$B30,Febrero_2024[NO. PROYECTO])+G30 -> 0 | I30: =SUMIF(Febrero_2024[INGRESO],$B30,Febrero_2024[DESCRIPCION])+H30 -> 0 | J30: =SUMIF(Febrero_2024[EGRESO],$B30,Febrero_2024[CATEGORÍA])+I30 -> 0 | K30: =SUMIF(Febrero_2024[BENEFICIARIO/PROVEEDOR],$B30,Febrero_2024[SUB CATEGORIA])+J30 -> 0 | L30: =SUMIF(Febrero_2024[NO. FACTURA],$B30,Febrero_2024[EQUILIBRAR])+K30 -> 0 | M30: =SUMIF(Febrero_2024[NO. PROYECTO],$B30,Febrero_2024[CUENTA])+L30 -> 0 | N30: =SUMIF(Febrero_2024[DESCRIPCION],$B30,Febrero_2024[FECHA])+M30 -> 0
B31: Cuentas por Cobrar | C31: =SUMIF(Enero_2024[CATEGORÍA],$B31,Enero_2024[INGRESO]) -> 0 | D31: =SUMIF(Febrero_2024[CATEGORÍA],$B31,Febrero_2024[INGRESO]) -> 0 | E31: =SUMIF(Marzo_2024[CATEGORÍA],$B31,Marzo_2024[INGRESO]) -> 0 | F31: =SUMIF(Abril_2024[CATEGORÍA],$B31,Abril_2024[INGRESO]) -> 0 | G31: =SUMIF(Mayo_2024[CATEGORÍA],$B31,Mayo_2024[INGRESO]) -> 0 | H31: =SUMIF(Junio_2024[CATEGORÍA],$B31,Junio_2024[INGRESO]) -> 0 | I31: =SUMIF(Julio_2024[CATEGORÍA],$B31,Julio_2024[INGRESO]) -> 0 | J31: =SUMIF(Agosto_2024[CATEGORÍA],$B31,Agosto_2024[INGRESO]) -> 4000 | K31: =SUMIF(Septiembre_2024[CATEGORÍA],$B31,Septiembre_2024[INGRESO]) -> 0 | L31: =SUMIF(Octubre_2024[CATEGORÍA],$B31,Octubre_2024[INGRESO]) -> 0 | M31: =SUMIF(Noviembre_2024[CATEGORÍA],$B31,Noviembre_2024[INGRESO]) -> 146610 | N31: =SUMIF(Diciembre_2024[CATEGORÍA],$B31,Diciembre_2024[INGRESO]) -> 0 | O31: =SUM(D31:N31) -> 150610
B32: Otro | C32: =SUMIF(Enero_2024[CATEGORÍA],$B32,Enero_2024[INGRESO]) -> 0 | D32: =SUMIF(Febrero_2024[CATEGORÍA],$B32,Febrero_2024[INGRESO]) -> 0 | E32: =SUMIF(Marzo_2024[CATEGORÍA],$B32,Marzo_2024[INGRESO]) -> 0 | F32: =SUMIF(Abril_2024[CATEGORÍA],$B32,Abril_2024[INGRESO]) -> 0 | G32: =SUMIF(Mayo_2024[CATEGORÍA],$B32,Mayo_2024[INGRESO]) -> 0 | H32: =SUMIF(Junio_2024[CATEGORÍA],$B32,Junio_2024[INGRESO]) -> 0 | I32: =SUMIF(Julio_2024[CATEGORÍA],$B32,Julio_2024[INGRESO]) -> 0 | J32: =SUMIF(Agosto_2024[CATEGORÍA],$B32,Agosto_2024[INGRESO]) -> 0 | K32: =SUMIF(Septiembre_2024[CATEGORÍA],$B32,Septiembre_2024[INGRESO]) -> 0 | L32: =SUMIF(Octubre_2024[CATEGORÍA],$B32,Octubre_2024[INGRESO]) -> 0 | M32: =SUMIF(Noviembre_2024[CATEGORÍA],$B32,Noviembre_2024[INGRESO]) -> 0 | N32: =SUMIF(Diciembre_2024[CATEGORÍA],$B32,Diciembre_2024[INGRESO]) -> 0 | O32: =SUM(D32:N32) -> 0
B34: TOTAL | C34: =SUM(C28:C32) -> 2600 | D34: =SUM(D28:D32) -> 5800 | E34: =SUM(E28:E32) -> 10200 | F34: =SUM(F28:F32) -> 13400 | G34: =SUM(G28:G32) -> 16600 | H34: =SUM(H28:H32) -> 19600 | I34: =SUM(I28:I32) -> 22800 | J34: =SUM(J28:J32) -> 31600 | ... O34: =SUM(O28:O32) -> 389810
B36: GASTOS OPERATIVOS
B37: RECURSOS HUMANOS
B38: Sueldos y Salarios | C38: =SUMIF(Enero_2024[CATEGORÍA],$B38,Enero_2024[EGRESO]) -> 24465.713 | D38: =SUMIF(Febrero_2024[CATEGORÍA],$B38,Febrero_2024[EGRESO]) -> 23700 | E38: =SUMIF(Marzo_2024[CATEGORÍA],$B38,Marzo_2024[EGRESO]) -> 34950 | F38: =SUMIF(Abril_2024[CATEGORÍA],$B38,Abril_2024[EGRESO]) -> 22900 | G38: =SUMIF(Mayo_2024[CATEGORÍA],$B38,Mayo_2024[EGRESO]) -> 22100 | H38: =SUMIF(Junio_2024[CATEGORÍA],$B38,Junio_2024[EGRESO]) -> 22100 | I38: =SUMIF(Julio_2024[CATEGORÍA],$B38,Julio_2024[EGRESO]) -> 25100 | J38: =SUMIF(Agosto_2024[CATEGORÍA],$B38,Agosto_2024[EGRESO]) -> 38550 | K38: =SUMIF(Septiembre_2024[CATEGORÍA],$B38,Septiembre_2024[EGRESO]) -> 32100 | L38: =SUMIF(Octubre_2024[CATEGORÍA],$B38,Octubre_2024[EGRESO]) -> 0 | M38: =SUMIF(Noviembre_2024[CATEGORÍA],$B38,Noviembre_2024[EGRESO]) -> 0 | N38: =SUMIF(Diciembre_2024[CATEGORÍA],$B38,Diciembre_2024[EGRESO]) -> 0 | O38: =SUM(D38:N38) -> 221500
B39: Aguinaldo | C39: =SUMIF(Enero_2024[CATEGORÍA],$B39,Enero_2024[EGRESO]) -> 0 | D39: =SUMIF(Febrero_2024[CATEGORÍA],$B39,Febrero_2024[EGRESO]) -> 0 | E39: =SUMIF(Marzo_2024[CATEGORÍA],$B39,Marzo_2024[EGRESO]) -> 0 | F39: =SUMIF(Abril_2024[CATEGORÍA],$B39,Abril_2024[EGRESO]) -> 0 | G39: =SUMIF(Mayo_2024[CATEGORÍA],$B39,Mayo_2024[EGRESO]) -> 0 | H39: =SUMIF(Junio_2024[CATEGORÍA],$B39,Junio_2024[EGRESO]) -> 0 | I39: =SUMIF(Julio_2024[CATEGORÍA],$B39,Julio_2024[EGRESO]) -> 0 | J39: =SUMIF(Agosto_2024[CATEGORÍA],$B39,Agosto_2024[EGRESO]) -> 0 | K39: =SUMIF(Septiembre_2024[CATEGORÍA],$B39,Septiembre_2024[EGRESO]) -> 0 | L39: =SUMIF(Octubre_2024[CATEGORÍA],$B39,Octubre_2024[EGRESO]) -> 0 | M39: =SUMIF(Noviembre_2024[CATEGORÍA],$B39,Noviembre_2024[EGRESO]) -> 0 | N39: =SUMIF(Diciembre_2024[CATEGORÍA],$B39,Diciembre_2024[EGRESO]) -> 0 | O39: =SUM(D39:N39) -> 0
B40: Prestamos de Nomina | C40: =SUMIF(Enero_2024[CATEGORÍA],$B40,Enero_2024[EGRESO]) -> 0 | D40: =SUMIF(Febrero_2024[CATEGORÍA],$B40,Febrero_2024[EGRESO]) -> 0 | E40: =SUMIF(Marzo_2024[CATEGORÍA],$B40,Marzo_2024[EGRESO]) -> 0 | F40: =SUMIF(Abril_2024[CATEGORÍA],$B40,Abril_2024[EGRESO]) -> 0 | G40: =SUMIF(Mayo_2024[CATEGORÍA],$B40,Mayo_2024[EGRESO]) -> 0 | H40: =SUMIF(Junio_2024[CATEGORÍA],$B40,Junio_2024[EGRESO]) -> 0 | I40: =SUMIF(Julio_2024[CATEGORÍA],$B40,Julio_2024[EGRESO]) -> 0 | J40: =SUMIF(Agosto_2024[CATEGORÍA],$B40,Agosto_2024[EGRESO]) -> 0 | K40: =SUMIF(Septiembre_2024[CATEGORÍA],$B40,Septiembre_2024[EGRESO]) -> 0 | L40: =SUMIF(Octubre_2024[CATEGORÍA],$B40,Octubre_2024[EGRESO]) -> 0 | M40: =SUMIF(Noviembre_2024[CATEGORÍA],$B40,Noviembre_2024[EGRESO]) -> 0 | N40: =SUMIF(Diciembre_2024[CATEGORÍA],$B40,Diciembre_2024[EGRESO]) -> 0 | O40: =SUM(D40:N40) -> 0
B41: Caja de Ahorro | C41: =SUMIF(Enero_2024[CATEGORÍA],$B41,Enero_2024[EGRESO]) -> 2600 | D41: =SUMIF(Febrero_2024[CATEGORÍA],$B41,Febrero_2024[EGRESO]) -> 3200 | E41: =SUMIF(Marzo_2024[CATEGORÍA],$B41,Marzo_2024[EGRESO]) -> 4400 | F41: =SUMIF(Abril_2024[CATEGORÍA],$B41,Abril_2024[EGRESO]) -> 3200 | G41: =SUMIF(Mayo_2024[CATEGORÍA],$B41,Mayo_2024[EGRESO]) -> 3200 | H41: =SUMIF(Junio_2024[CATEGORÍA],$B41,Junio_2024[EGRESO]) -> 3000 | I41: =SUMIF(Julio_2024[CATEGORÍA],$B41,Julio_2024[EGRESO]) -> 3200 | J41: =SUMIF(Agosto_2024[CATEGORÍA],$B41,Agosto_2024[EGRESO]) -> 4800 | K41: =SUMIF(Septiembre_2024[CATEGORÍA],$B41,Septiembre_2024[EGRESO]) -> 3200 | L41: =SUMIF(Octubre_2024[CATEGORÍA],$B41,Octubre_2024[EGRESO]) -> 0 | M41: =SUMIF(Noviembre_2024[CATEGORÍA],$B41,Noviembre_2024[EGRESO]) -> 0 | N41: =SUMIF(Diciembre_2024[CATEGORÍA],$B41,Diciembre_2024[EGRESO]) -> 0 | O41: =SUM(D41:N41) -> 28200
B42: Seguro Social | C42: =SUMIF(Enero_2024[CATEGORÍA],$B42,Enero_2024[EGRESO]) -> 0 | D42: =SUMIF(Febrero_2024[CATEGORÍA],$B42,Febrero_2024[EGRESO]) -> 0 | E42: =SUMIF(Marzo_2024[CATEGORÍA],$B42,Marzo_2024[EGRESO]) -> 0 | F42: =SUMIF(Abril_2024[CATEGORÍA],$B42,Abril_2024[EGRESO]) -> 0 | G42: =SUMIF(Mayo_2024[CATEGORÍA],$B42,Mayo_2024[EGRESO]) -> 0 | H42: =SUMIF(Junio_2024[CATEGORÍA],$B42,Junio_2024[EGRESO]) -> 0 | I42: =SUMIF(Julio_2024[CATEGORÍA],$B42,Julio_2024[EGRESO]) -> 0 | J42: =SUMIF(Agosto_2024[CATEGORÍA],$B42,Agosto_2024[EGRESO]) -> 0 | K42: =SUMIF(Septiembre_2024[CATEGORÍA],$B42,Septiembre_2024[EGRESO]) -> 0 | L42: =SUMIF(Octubre_2024[CATEGORÍA],$B42,Octubre_2024[EGRESO]) -> 0 | M42: =SUMIF(Noviembre_2024[CATEGORÍA],$B42,Noviembre_2024[EGRESO]) -> 0 | N42: =SUMIF(Diciembre_2024[CATEGORÍA],$B42,Diciembre_2024[EGRESO]) -> 0 | O42: =SUM(D42:N42) -> 0
B43: Gastos Medicos | C43: =SUMIF(Enero_2024[CATEGORÍA],$B43,Enero_2024[EGRESO]) -> 0 | D43: =SUMIF(Febrero_2024[CATEGORÍA],$B43,Febrero_2024[EGRESO]) -> 0 | E43: =SUMIF(Marzo_2024[CATEGORÍA],$B43,Marzo_2024[EGRESO]) -> 0 | F43: =SUMIF(Abril_2024[CATEGORÍA],$B43,Abril_2024[EGRESO]) -> 0 | G43: =SUMIF(Mayo_2024[CATEGORÍA],$B43,Mayo_2024[EGRESO]) -> 0 | H43: =SUMIF(Junio_2024[CATEGORÍA],$B43,Junio_2024[EGRESO]) -> 0 | I43: =SUMIF(Julio_2024[CATEGORÍA],$B43,Julio_2024[EGRESO]) -> 0 | J43: =SUMIF(Agosto_2024[CATEGORÍA],$B43,Agosto_2024[EGRESO]) -> 0 | K43: =SUMIF(Septiembre_2024[CATEGORÍA],$B43,Septiembre_2024[EGRESO]) -> 0 | L43: =SUMIF(Octubre_2024[CATEGORÍA],$B43,Octubre_2024[EGRESO]) -> 68 | M43: =SUMIF(Noviembre_2024[CATEGORÍA],$B43,Noviembre_2024[EGRESO]) -> 0 | N43: =SUMIF(Diciembre_2024[CATEGORÍA],$B43,Diciembre_2024[EGRESO]) -> 0 | O43: =SUM(D43:N43) -> 68
B44: ISR | C44: =SUMIF(Enero_2024[CATEGORÍA],$B44,Enero_2024[EGRESO]) -> 0 | D44: =SUMIF(Febrero_2024[CATEGORÍA],$B44,Febrero_2024[EGRESO]) -> 0 | E44: =SUMIF(Marzo_2024[CATEGORÍA],$B44,Marzo_2024[EGRESO]) -> 0 | F44: =SUMIF(Abril_2024[CATEGORÍA],$B44,Abril_2024[EGRESO]) -> 0 | G44: =SUMIF(Mayo_2024[CATEGORÍA],$B44,Mayo_2024[EGRESO]) -> 0 | H44: =SUMIF(Junio_2024[CATEGORÍA],$B44,Junio_2024[EGRESO]) -> 0 | I44: =SUMIF(Julio_2024[CATEGORÍA],$B44,Julio_2024[EGRESO]) -> 0 | J44: =SUMIF(Agosto_2024[CATEGORÍA],$B44,Agosto_2024[EGRESO]) -> 0 | K44: =SUMIF(Septiembre_2024[CATEGORÍA],$B44,Septiembre_2024[EGRESO]) -> 0 | L44: =SUMIF(Octubre_2024[CATEGORÍA],$B44,Octubre_2024[EGRESO]) -> 0 | M44: =SUMIF(Noviembre_2024[CATEGORÍA],$B44,Noviembre_2024[EGRESO]) -> 0 | N44: =SUMIF(Diciembre_2024[CATEGORÍA],$B44,Diciembre_2024[EGRESO]) -> 0 | O44: =SUM(D44:N44) -> 0
B45: INFONAVIT | C45: =SUMIF(Enero_2024[CATEGORÍA],$B45,Enero_2024[EGRESO]) -> 0 | D45: =SUMIF(Febrero_2024[CATEGORÍA],$B45,Febrero_2024[EGRESO]) -> 0 | E45: =SUMIF(Marzo_2024[CATEGORÍA],$B45,Marzo_2024[EGRESO]) -> 0 | F45: =SUMIF(Abril_2024[CATEGORÍA],$B45,Abril_2024[EGRESO]) -> 0 | G45: =SUMIF(Mayo_2024[CATEGORÍA],$B45,Mayo_2024[EGRESO]) -> 0 | H45: =SUMIF(Junio_2024[CATEGORÍA],$B45,Junio_2024[EGRESO]) -> 0 | I45: =SUMIF(Julio_2024[CATEGORÍA],$B45,Julio_2024[EGRESO]) -> 0 | J45: =SUMIF(Agosto_2024[CATEGORÍA],$B45,Agosto_2024[EGRESO]) -> 0 | K45: =SUMIF(Septiembre_2024[CATEGORÍA],$B45,Septiembre_2024[EGRESO]) -> 0 | L45: =SUMIF(Octubre_2024[CATEGORÍA],$B45,Octubre_2024[EGRESO]) -> 0 | M45: =SUMIF(Noviembre_2024[CATEGORÍA],$B45,Noviembre_2024[EGRESO]) -> 0 | N45: =SUMIF(Diciembre_2024[CATEGORÍA],$B45,Diciembre_2024[EGRESO]) -> 0 | O45: =SUM(D45:N45) -> 0
B46: 2.5% Sobre Nomina | C46: =SUMIF(Enero_2024[CATEGORÍA],$B46,Enero_2024[EGRESO]) -> 0 | D46: =SUMIF(Febrero_2024[CATEGORÍA],$B46,Febrero_2024[EGRESO]) -> 0 | E46: =SUMIF(Marzo_2024[CATEGORÍA],$B46,Marzo_2024[EGRESO]) -> 0 | F46: =SUMIF(Abril_2024[CATEGORÍA],$B46,Abril_2024[EGRESO]) -> 0 | G46: =SUMIF(Mayo_2024[CATEGORÍA],$B46,Mayo_2024[EGRESO]) -> 0 | H46: =SUMIF(Junio_2024[CATEGORÍA],$B46,Junio_2024[EGRESO]) -> 0 | I46: =SUMIF(Julio_2024[CATEGORÍA],$B46,Julio_2024[EGRESO]) -> 0 | J46: =SUMIF(Agosto_2024[CATEGORÍA],$B46,Agosto_2024[EGRESO]) -> 0 | K46: =SUMIF(Septiembre_2024[CATEGORÍA],$B46,Septiembre_2024[EGRESO]) -> 0 | L46: =SUMIF(Octubre_2024[CATEGORÍA],$B46,Octubre_2024[EGRESO]) -> 0 | M46: =SUMIF(Noviembre_2024[CATEGORÍA],$B46,Noviembre_2024[EGRESO]) -> 0 | N46: =SUMIF(Diciembre_2024[CATEGORÍA],$B46,Diciembre_2024[EGRESO]) -> 0 | O46: =SUM(D46:N46) -> 0
B47: Vacaciones NO Disfrutadas | C47: =SUMIF(Enero_2024[CATEGORÍA],$B47,Enero_2024[EGRESO]) -> 0 | D47: =SUMIF(Febrero_2024[CATEGORÍA],$B47,Febrero_2024[EGRESO]) -> 0 | E47: =SUMIF(Marzo_2024[CATEGORÍA],$B47,Marzo_2024[EGRESO]) -> 0 | F47: =SUMIF(Abril_2024[CATEGORÍA],$B47,Abril_2024[EGRESO]) -> 0 | G47: =SUMIF(Mayo_2024[CATEGORÍA],$B47,Mayo_2024[EGRESO]) -> 0 | H47: =SUMIF(Junio_2024[CATEGORÍA],$B47,Junio_2024[EGRESO]) -> 0 | I47: =SUMIF(Julio_2024[CATEGORÍA],$B47,Julio_2024[EGRESO]) -> 0 | J47: =SUMIF(Agosto_2024[CATEGORÍA],$B47,Agosto_2024[EGRESO]) -> 0 | K47: =SUMIF(Septiembre_2024[CATEGORÍA],$B47,Septiembre_2024[EGRESO]) -> 0 | L47: =SUMIF(Octubre_2024[CATEGORÍA],$B47,Octubre_2024[EGRESO]) -> 0 | M47: =SUMIF(Noviembre_2024[CATEGORÍA],$B47,Noviembre_2024[EGRESO]) -> 0 | N47: =SUMIF(Diciembre_2024[CATEGORÍA],$B47,Diciembre_2024[EGRESO]) -> 0 | O47: =SUM(D47:N47) -> 0
B48: Prima Vacacional | C48: =SUMIF(Enero_2024[CATEGORÍA],$B48,Enero_2024[EGRESO]) -> 0 | D48: =SUMIF(Febrero_2024[CATEGORÍA],$B48,Febrero_2024[EGRESO]) -> 0 | E48: =SUMIF(Marzo_2024[CATEGORÍA],$B48,Marzo_2024[EGRESO]) -> 0 | F48: =SUMIF(Abril_2024[CATEGORÍA],$B48,Abril_2024[EGRESO]) -> 0 | G48: =SUMIF(Mayo_2024[CATEGORÍA],$B48,Mayo_2024[EGRESO]) -> 0 | H48: =SUMIF(Junio_2024[CATEGORÍA],$B48,Junio_2024[EGRESO]) -> 0 | I48: =SUMIF(Julio_2024[CATEGORÍA],$B48,Julio_2024[EGRESO]) -> 0 | J48: =SUMIF(Agosto_2024[CATEGORÍA],$B48,Agosto_2024[EGRESO]) -> 0 | K48: =SUMIF(Septiembre_2024[CATEGORÍA],$B48,Septiembre_2024[EGRESO]) -> 0 | L48: =SUMIF(Octubre_2024[CATEGORÍA],$B48,Octubre_2024[EGRESO]) -> 0 | M48: =SUMIF(Noviembre_2024[CATEGORÍA],$B48,Noviembre_2024[EGRESO]) -> 0 | N48: =SUMIF(Diciembre_2024[CATEGORÍA],$B48,Diciembre_2024[EGRESO]) -> 0 | O48: =SUM(D48:N48) -> 0
B49: Aguinaldo | C49: =SUMIF(Enero_2024[CATEGORÍA],$B49,Enero_2024[EGRESO]) -> 0 | D49: =SUMIF(Febrero_2024[CATEGORÍA],$B49,Febrero_2024[EGRESO]) -> 0 | E49: =SUMIF(Marzo_2024[CATEGORÍA],$B49,Marzo_2024[EGRESO]) -> 0 | F49: =SUMIF(Abril_2024[CATEGORÍA],$B49,Abril_2024[EGRESO]) -> 0 | G49: =SUMIF(Mayo_2024[CATEGORÍA],$B49,Mayo_2024[EGRESO]) -> 0 | H49: =SUMIF(Junio_2024[CATEGORÍA],$B49,Junio_2024[EGRESO]) -> 0 | I49: =SUMIF(Julio_2024[CATEGORÍA],$B49,Julio_2024[EGRESO]) -> 0 | J49: =SUMIF(Agosto_2024[CATEGORÍA],$B49,Agosto_2024[EGRESO]) -> 0 | K49: =SUMIF(Septiembre_2024[CATEGORÍA],$B49,Septiembre_2024[EGRESO]) -> 0 | L49: =SUMIF(Octubre_2024[CATEGORÍA],$B49,Octubre_2024[EGRESO]) -> 0 | M49: =SUMIF(Noviembre_2024[CATEGORÍA],$B49,Noviembre_2024[EGRESO]) -> 0 | N49: =SUMIF(Diciembre_2024[CATEGORÍA],$B49,Diciembre_2024[EGRESO]) -> 0 | O49: =SUM(D49:N49) -> 0
... B55: Otro RRHH | C55: =SUMIF(Enero_2024[CATEGORÍA],$B55,Enero_2024[EGRESO]) -> 356.66667 | D55: =SUMIF(Febrero_2024[CATEGORÍA],$B55,Febrero_2024[EGRESO]) -> 0 | E55: =SUMIF(Marzo_2024[CATEGORÍA],$B55,Marzo_2024[EGRESO]) -> 0 | F55: =SUMIF(Abril_2024[CATEGORÍA],$B55,Abril_2024[EGRESO]) -> 0 | G55: =SUMIF(Mayo_2024[CATEGORÍA],$B55,Mayo_2024[EGRESO]) -> 0 | H55: =SUMIF(Junio_2024[CATEGORÍA],$B55,Junio_2024[EGRESO]) -> 0 | I55: =SUMIF(Julio_2024[CATEGORÍA],$B55,Julio_2024[EGRESO]) -> 0 | J55: =SUMIF(Agosto_2024[CATEGORÍA],$B55,Agosto_2024[EGRESO]) -> 0 | K55: =SUMIF(Septiembre_2024[CATEGORÍA],$B55,Septiembre_2024[EGRESO]) -> 0 | L55: =SUMIF(Octubre_2024[CATEGORÍA],$B55,Octubre_2024[EGRESO]) -> 0 | M55: =SUMIF(Noviembre_2024[CATEGORÍA],$B55,Noviembre_2024[EGRESO]) -> 0 | N55: =SUMIF(Diciembre_2024[CATEGORÍA],$B55,Diciembre_2024[EGRESO]) -> 0 | O55: =SUM(D55:N55) -> 0
C56: =SUM(C38:C55) -> 27422.38 | D56: =SUM(D38:D55) -> 27818.5 | E56: =SUM(E38:E55) -> 40991 | F56: =SUM(F38:F55) -> 26300 | G56: =SUM(G38:G55) -> 25410 | H56: =SUM(H38:H55) -> 25709 | I56: =SUM(I38:I55) -> 30592.5 | J56: =SUM(J38:J55) -> 62840 | ... O56: =SUM(O38:O55) -> 275279
B57: LOGISTICA
B58: Pagos de automóviles | C58: =SUMIF(Enero_2024[CATEGORÍA],$B58,Enero_2024[EGRESO]) -> 0 | D58: =SUMIF(Febrero_2024[CATEGORÍA],$B58,Febrero_2024[EGRESO]) -> 0 | E58: =SUMIF(Marzo_2024[CATEGORÍA],$B58,Marzo_2024[EGRESO]) -> 0 | F58: =SUMIF(Abril_2024[CATEGORÍA],$B58,Abril_2024[EGRESO]) -> 0 | G58: =SUMIF(Mayo_2024[CATEGORÍA],$B58,Mayo_2024[EGRESO]) -> 0 | H58: =SUMIF(Junio_2024[CATEGORÍA],$B58,Junio_2024[EGRESO]) -> 0 | I58: =SUMIF(Julio_2024[CATEGORÍA],$B58,Julio_2024[EGRESO]) -> 0 | J58: =SUMIF(Agosto_2024[CATEGORÍA],$B58,Agosto_2024[EGRESO]) -> 0 | K58: =SUMIF(Septiembre_2024[CATEGORÍA],$B58,Septiembre_2024[EGRESO]) -> 0 | L58: =SUMIF(Octubre_2024[CATEGORÍA],$B58,Octubre_2024[EGRESO]) -> 0 | M58: =SUMIF(Noviembre_2024[CATEGORÍA],$B58,Noviembre_2024[EGRESO]) -> 0 | N58: =SUMIF(Diciembre_2024[CATEGORÍA],$B58,Diciembre_2024[EGRESO]) -> 0 | O58: =SUM(D58:N58) -> 0
B59: Seguro de Auto | C59: =SUMIF(Enero_2024[CATEGORÍA],$B59,Enero_2024[EGRESO]) -> 0 | D59: =SUMIF(Febrero_2024[CATEGORÍA],$B59,Febrero_2024[EGRESO]) -> 0 | E59: =SUMIF(Marzo_2024[CATEGORÍA],$B59,Marzo_2024[EGRESO]) -> 0 | F59: =SUMIF(Abril_2024[CATEGORÍA],$B59,Abril_2024[EGRESO]) -> 0 | G59: =SUMIF(Mayo_2024[CATEGORÍA],$B59,Mayo_2024[EGRESO]) -> 0 | H59: =SUMIF(Junio_2024[CATEGORÍA],$B59,Junio_2024[EGRESO]) -> 0 | I59: =SUMIF(Julio_2024[CATEGORÍA],$B59,Julio_2024[EGRESO]) -> 0 | J59: =SUMIF(Agosto_2024[CATEGORÍA],$B59,Agosto_2024[EGRESO]) -> 0 | K59: =SUMIF(Septiembre_2024[CATEGORÍA],$B59,Septiembre_2024[EGRESO]) -> 0 | L59: =SUMIF(Octubre_2024[CATEGORÍA],$B59,Octubre_2024[EGRESO]) -> 0 | M59: =SUMIF(Noviembre_2024[CATEGORÍA],$B59,Noviembre_2024[EGRESO]) -> 0 | N59: =SUMIF(Diciembre_2024[CATEGORÍA],$B59,Diciembre_2024[EGRESO]) -> 0 | O59: =SUM(D59:N59) -> 0
B60: Casetas/Peajes | C60: =SUMIF(Enero_2024[CATEGORÍA],$B60,Enero_2024[EGRESO]) -> 0 | D60: =SUMIF(Febrero_2024[CATEGORÍA],$B60,Febrero_2024[EGRESO]) -> 0 | E60: =SUMIF(Marzo_2024[CATEGORÍA],$B60,Marzo_2024[EGRESO]) -> 0 | F60: =SUMIF(Abril_2024[CATEGORÍA],$B60,Abril_2024[EGRESO]) -> 0 | G60: =SUMIF(Mayo_2024[CATEGORÍA],$B60,Mayo_2024[EGRESO]) -> 50 | H60: =SUMIF(Junio_2024[CATEGORÍA],$B60,Junio_2024[EGRESO]) -> 0 | I60: =SUMIF(Julio_2024[CATEGORÍA],$B60,Julio_2024[EGRESO]) -> 0 | J60: =SUMIF(Agosto_2024[CATEGORÍA],$B60,Agosto_2024[EGRESO]) -> 0 | K60: =SUMIF(Septiembre_2024[CATEGORÍA],$B60,Septiembre_2024[EGRESO]) -> 78 | L60: =SUMIF(Octubre_2024[CATEGORÍA],$B60,Octubre_2024[EGRESO]) -> 0 | M60: =SUMIF(Noviembre_2024[CATEGORÍA],$B60,Noviembre_2024[EGRESO]) -> 0 | N60: =SUMIF(Diciembre_2024[CATEGORÍA],$B60,Diciembre_2024[EGRESO]) -> 0 | O60: =SUM(D60:N60) -> 128
B61: Impuestos y Refrendos | C61: =SUMIF(Enero_2024[CATEGORÍA],$B61,Enero_2024[EGRESO]) -> 0 | D61: =SUMIF(Febrero_2024[CATEGORÍA],$B61,Febrero_2024[EGRESO]) -> 0 | E61: =SUMIF(Marzo_2024[CATEGORÍA],$B61,Marzo_2024[EGRESO]) -> 0 | F61: =SUMIF(Abril_2024[CATEGORÍA],$B61,Abril_2024[EGRESO]) -> 0 | G61: =SUMIF(Mayo_2024[CATEGORÍA],$B61,Mayo_2024[EGRESO]) -> 0 | H61: =SUMIF(Junio_2024[CATEGORÍA],$B61,Junio_2024[EGRESO]) -> 0 | I61: =SUMIF(Julio_2024[CATEGORÍA],$B61,Julio_2024[EGRESO]) -> 0 | J61: =SUMIF(Agosto_2024[CATEGORÍA],$B61,Agosto_2024[EGRESO]) -> 0 | K61: =SUMIF(Septiembre_2024[CATEGORÍA],$B61,Septiembre_2024[EGRESO]) -> 0 | L61: =SUMIF(Octubre_2024[CATEGORÍA],$B61,Octubre_2024[EGRESO]) -> 0 | M61: =SUMIF(Noviembre_2024[CATEGORÍA],$B61,Noviembre_2024[EGRESO]) -> 0 | N61: =SUMIF(Diciembre_2024[CATEGORÍA],$B61,Diciembre_2024[EGRESO]) -> 0 | O61: =SUM(D61:N61) -> 0
B62: Combustible | C62: =SUMIF(Enero_2024[CATEGORÍA],$B62,Enero_2024[EGRESO]) -> 0 | D62: =SUMIF(Febrero_2024[CATEGORÍA],$B62,Febrero_2024[EGRESO]) -> 0 | E62: =SUMIF(Marzo_2024[CATEGORÍA],$B62,Marzo_2024[EGRESO]) -> 0 | F62: =SUMIF(Abril_2024[CATEGORÍA],$B62,Abril_2024[EGRESO]) -> 0 | G62: =SUMIF(Mayo_2024[CATEGORÍA],$B62,Mayo_2024[EGRESO]) -> 0 | H62: =SUMIF(Junio_2024[CATEGORÍA],$B62,Junio_2024[EGRESO]) -> 500 | I62: =SUMIF(Julio_2024[CATEGORÍA],$B62,Julio_2024[EGRESO]) -> 1964.18 | J62: =SUMIF(Agosto_2024[CATEGORÍA],$B62,Agosto_2024[EGRESO]) -> 1600 | K62: =SUMIF(Septiembre_2024[CATEGORÍA],$B62,Septiembre_2024[EGRESO]) -> 4033.3333 | L62: =SUMIF(Octubre_2024[CATEGORÍA],$B62,Octubre_2024[EGRESO]) -> 0 | M62: =SUMIF(Noviembre_2024[CATEGORÍA],$B62,Noviembre_2024[EGRESO]) -> 0 | N62: =SUMIF(Diciembre_2024[CATEGORÍA],$B62,Diciembre_2024[EGRESO]) -> 0 | O62: =SUM(D62:N62) -> 8097.5133
B63: Transporte Público | C63: =SUMIF(Enero_2024[CATEGORÍA],$B63,Enero_2024[EGRESO]) -> 0 | D63: =SUMIF(Febrero_2024[CATEGORÍA],$B63,Febrero_2024[EGRESO]) -> 0 | E63: =SUMIF(Marzo_2024[CATEGORÍA],$B63,Marzo_2024[EGRESO]) -> 0 | F63: =SUMIF(Abril_2024[CATEGORÍA],$B63,Abril_2024[EGRESO]) -> 0 | G63: =SUMIF(Mayo_2024[CATEGORÍA],$B63,Mayo_2024[EGRESO]) -> 0 | H63: =SUMIF(Junio_2024[CATEGORÍA],$B63,Junio_2024[EGRESO]) -> 0 | I63: =SUMIF(Julio_2024[CATEGORÍA],$B63,Julio_2024[EGRESO]) -> 0 | J63: =SUMIF(Agosto_2024[CATEGORÍA],$B63,Agosto_2024[EGRESO]) -> 0 | K63: =SUMIF(Septiembre_2024[CATEGORÍA],$B63,Septiembre_2024[EGRESO]) -> 0 | L63: =SUMIF(Octubre_2024[CATEGORÍA],$B63,Octubre_2024[EGRESO]) -> 0 | M63: =SUMIF(Noviembre_2024[CATEGORÍA],$B63,Noviembre_2024[EGRESO]) -> 0 | N63: =SUMIF(Diciembre_2024[CATEGORÍA],$B63,Diciembre_2024[EGRESO]) -> 0 | O63: =SUM(D63:N63) -> 0
B64: Reparaciones y Mantenimientos | C64: =SUMIF(Enero_2024[CATEGORÍA],$B64,Enero_2024[EGRESO]) -> 0 | D64: =SUMIF(Febrero_2024[CATEGORÍA],$B64,Febrero_2024[EGRESO]) -> 0 | E64: =SUMIF(Marzo_2024[CATEGORÍA],$B64,Marzo_2024[EGRESO]) -> 0 | F64: =SUMIF(Abril_2024[CATEGORÍA],$B64,Abril_2024[EGRESO]) -> 0 | G64: =SUMIF(Mayo_2024[CATEGORÍA],$B64,Mayo_2024[EGRESO]) -> 0 | H64: =SUMIF(Junio_2024[CATEGORÍA],$B64,Junio_2024[EGRESO]) -> 0 | I64: =SUMIF(Julio_2024[CATEGORÍA],$B64,Julio_2024[EGRESO]) -> 115 | J64: =SUMIF(Agosto_2024[CATEGORÍA],$B64,Agosto_2024[EGRESO]) -> 0 | K64: =SUMIF(Septiembre_2024[CATEGORÍA],$B64,Septiembre_2024[EGRESO]) -> 0 | L64: =SUMIF(Octubre_2024[CATEGORÍA],$B64,Octubre_2024[EGRESO]) -> 0 | M64: =SUMIF(Noviembre_2024[CATEGORÍA],$B64,Noviembre_2024[EGRESO]) -> 0 | N64: =SUMIF(Diciembre_2024[CATEGORÍA],$B64,Diciembre_2024[EGRESO]) -> 0 | O64: =SUM(D64:N64) -> 115
B65: Registros y Licencias | C65: =SUMIF(Enero_2024[CATEGORÍA],$B65,Enero_2024[EGRESO]) -> 0 | D65: =SUMIF(Febrero_2024[CATEGORÍA],$B65,Febrero_2024[EGRESO]) -> 0 | E65: =SUMIF(Marzo_2024[CATEGORÍA],$B65,Marzo_2024[EGRESO]) -> 0 | F65: =SUMIF(Abril_2024[CATEGORÍA],$B65,Abril_2024[EGRESO]) -> 0 | G65: =SUMIF(Mayo_2024[CATEGORÍA],$B65,Mayo_2024[EGRESO]) -> 0 | H65: =SUMIF(Junio_2024[CATEGORÍA],$B65,Junio_2024[EGRESO]) -> 0 | I65: =SUMIF(Julio_2024[CATEGORÍA],$B65,Julio_2024[EGRESO]) -> 0 | J65: =SUMIF(Agosto_2024[CATEGORÍA],$B65,Agosto_2024[EGRESO]) -> 0 | K65: =SUMIF(Septiembre_2024[CATEGORÍA],$B65,Septiembre_2024[EGRESO]) -> 0 | L65: =SUMIF(Octubre_2024[CATEGORÍA],$B65,Octubre_2024[EGRESO]) -> 0 | M65: =SUMIF(Noviembre_2024[CATEGORÍA],$B65,Noviembre_2024[EGRESO]) -> 0 | N65: =SUMIF(Diciembre_2024[CATEGORÍA],$B65,Diciembre_2024[EGRESO]) -> 0 | O65: =SUM(D65:N65) -> 0
B66: Otro | C66: =SUMIF(Enero_2024[CATEGORÍA],$B66,Enero_2024[EGRESO]) -> 0 | D66: =SUMIF(Febrero_2024[CATEGORÍA],$B66,Febrero_2024[EGRESO]) -> 0 | E66: =SUMIF(Marzo_2024[CATEGORÍA],$B66,Marzo_2024[EGRESO]) -> 0 | F66: =SUMIF(Abril_2024[CATEGORÍA],$B66,Abril_2024[EGRESO]) -> 0 | G66: =SUMIF(Mayo_2024[CATEGORÍA],$B66,Mayo_2024[EGRESO]) -> 0 | H66: =SUMIF(Junio_2024[CATEGORÍA],$B66,Junio_2024[EGRESO]) -> 0 | I66: =SUMIF(Julio_2024[CATEGORÍA],$B66,Julio_2024[EGRESO]) -> 0 | J66: =SUMIF(Agosto_2024[CATEGORÍA],$B66,Agosto_2024[EGRESO]) -> 0 | K66: =SUMIF(Septiembre_2024[CATEGORÍA],$B66,Septiembre_2024[EGRESO]) -> 0 | L66: =SUMIF(Octubre_2024[CATEGORÍA],$B66,Octubre_2024[EGRESO]) -> 0 | M66: =SUMIF(Noviembre_2024[CATEGORÍA],$B66,Noviembre_2024[EGRESO]) -> 0 | N66: =SUMIF(Diciembre_2024[CATEGORÍA],$B66,Diciembre_2024[EGRESO]) -> 0 | O66: =SUM(D66:N66) -> 0
C67: =SUM(C58:C66) -> 0 | D67: =SUM(D58:D66) -> 0 | E67: =SUM(E58:E66) -> 0 | F67: =SUM(F58:F66) -> 0 | G67: =SUM(G58:G66) -> 50 | H67: =SUM(H58:H66) -> 500 | I67: =SUM(I58:I66) -> 2079.18 | J67: =SUM(J58:J66) -> 1600 | ... O67: =SUM(O58:O66) -> 8340.5133
B68: SERVICIOS
B69: Internet y Telefonico | C69: =SUMIF(Enero_2024[CATEGORÍA],$B69,Enero_2024[EGRESO]) -> 0 | D69: =SUMIF(Febrero_2024[CATEGORÍA],$B69,Febrero_2024[EGRESO]) -> 0 | E69: =SUMIF(Marzo_2024[CATEGORÍA],$B69,Marzo_2024[EGRESO]) -> 0 | F69: =SUMIF(Abril_2024[CATEGORÍA],$B69,Abril_2024[EGRESO]) -> 0 | G69: =SUMIF(Mayo_2024[CATEGORÍA],$B69,Mayo_2024[EGRESO]) -> 0 | H69: =SUMIF(Junio_2024[CATEGORÍA],$B69,Junio_2024[EGRESO]) -> 0 | I69: =SUMIF(Julio_2024[CATEGORÍA],$B69,Julio_2024[EGRESO]) -> 0 | J69: =SUMIF(Agosto_2024[CATEGORÍA],$B69,Agosto_2024[EGRESO]) -> 0 | K69: =SUMIF(Septiembre_2024[CATEGORÍA],$B69,Septiembre_2024[EGRESO]) -> 0 | L69: =SUMIF(Octubre_2024[CATEGORÍA],$B69,Octubre_2024[EGRESO]) -> 0 | M69: =SUMIF(Noviembre_2024[CATEGORÍA],$B69,Noviembre_2024[EGRESO]) -> 0 | N69: =SUMIF(Diciembre_2024[CATEGORÍA],$B69,Diciembre_2024[EGRESO]) -> 0 | O69: =SUM(D69:N69) -> 0
B70: Electricidad CFE | C70: =SUMIF(Enero_2024[CATEGORÍA],$B70,Enero_2024[EGRESO]) -> 0 | D70: =SUMIF(Febrero_2024[CATEGORÍA],$B70,Febrero_2024[EGRESO]) -> 0 | E70: =SUMIF(Marzo_2024[CATEGORÍA],$B70,Marzo_2024[EGRESO]) -> 0 | F70: =SUMIF(Abril_2024[CATEGORÍA],$B70,Abril_2024[EGRESO]) -> 0 | G70: =SUMIF(Mayo_2024[CATEGORÍA],$B70,Mayo_2024[EGRESO]) -> 0 | H70: =SUMIF(Junio_2024[CATEGORÍA],$B70,Junio_2024[EGRESO]) -> 0 | I70: =SUMIF(Julio_2024[CATEGORÍA],$B70,Julio_2024[EGRESO]) -> 0 | J70: =SUMIF(Agosto_2024[CATEGORÍA],$B70,Agosto_2024[EGRESO]) -> 0 | K70: =SUMIF(Septiembre_2024[CATEGORÍA],$B70,Septiembre_2024[EGRESO]) -> 179.66667 | L70: =SUMIF(Octubre_2024[CATEGORÍA],$B70,Octubre_2024[EGRESO]) -> 0 | M70: =SUMIF(Noviembre_2024[CATEGORÍA],$B70,Noviembre_2024[EGRESO]) -> 0 | N70: =SUMIF(Diciembre_2024[CATEGORÍA],$B70,Diciembre_2024[EGRESO]) -> 0 | O70: =SUM(D70:N70) -> 179.66667
B71: Limpieza | C71: =SUMIF(Enero_2024[CATEGORÍA],$B71,Enero_2024[EGRESO]) -> 0 | D71: =SUMIF(Febrero_2024[CATEGORÍA],$B71,Febrero_2024[EGRESO]) -> 0 | E71: =SUMIF(Marzo_2024[CATEGORÍA],$B71,Marzo_2024[EGRESO]) -> 0 | F71: =SUMIF(Abril_2024[CATEGORÍA],$B71,Abril_2024[EGRESO]) -> 0 | G71: =SUMIF(Mayo_2024[CATEGORÍA],$B71,Mayo_2024[EGRESO]) -> 0 | H71: =SUMIF(Junio_2024[CATEGORÍA],$B71,Junio_2024[EGRESO]) -> 0 | I71: =SUMIF(Julio_2024[CATEGORÍA],$B71,Julio_2024[EGRESO]) -> 0 | J71: =SUMIF(Agosto_2024[CATEGORÍA],$B71,Agosto_2024[EGRESO]) -> 0 | K71: =SUMIF(Septiembre_2024[CATEGORÍA],$B71,Septiembre_2024[EGRESO]) -> 0 | L71: =SUMIF(Octubre_2024[CATEGORÍA],$B71,Octubre_2024[EGRESO]) -> 0 | M71: =SUMIF(Noviembre_2024[CATEGORÍA],$B71,Noviembre_2024[EGRESO]) -> 0 | N71: =SUMIF(Diciembre_2024[CATEGORÍA],$B71,Diciembre_2024[EGRESO]) -> 0 | O71: =SUM(D71:N71) -> 0
B72: Comisiones Bancarias | C72: =SUMIF(Enero_2024[CATEGORÍA],$B72,Enero_2024[EGRESO]) -> 0 | D72: =SUMIF(Febrero_2024[CATEGORÍA],$B72,Febrero_2024[EGRESO]) -> 0 | E72: =SUMIF(Marzo_2024[CATEGORÍA],$B72,Marzo_2024[EGRESO]) -> 0 | F72: =SUMIF(Abril_2024[CATEGORÍA],$B72,Abril_2024[EGRESO]) -> 0 | G72: =SUMIF(Mayo_2024[CATEGORÍA],$B72,Mayo_2024[EGRESO]) -> 0 | H72: =SUMIF(Junio_2024[CATEGORÍA],$B72,Junio_2024[EGRESO]) -> 0 | I72: =SUMIF(Julio_2024[CATEGORÍA],$B72,Julio_2024[EGRESO]) -> 0 | J72: =SUMIF(Agosto_2024[CATEGORÍA],$B72,Agosto_2024[EGRESO]) -> 0 | K72: =SUMIF(Septiembre_2024[CATEGORÍA],$B72,Septiembre_2024[EGRESO]) -> 0 | L72: =SUMIF(Octubre_2024[CATEGORÍA],$B72,Octubre_2024[EGRESO]) -> 0 | M72: =SUMIF(Noviembre_2024[CATEGORÍA],$B72,Noviembre_2024[EGRESO]) -> 0 | N72: =SUMIF(Diciembre_2024[CATEGORÍA],$B72,Diciembre_2024[EGRESO]) -> 0 | O72: =SUM(D72:N72) -> 0
B73: Certificaciones | C73: =SUMIF(Enero_2024[CATEGORÍA],$B73,Enero_2024[EGRESO]) -> 0 | D73: =SUMIF(Febrero_2024[CATEGORÍA],$B73,Febrero_2024[EGRESO]) -> 4619.96 | E73: =SUMIF(Marzo_2024[CATEGORÍA],$B73,Marzo_2024[EGRESO]) -> 0 | F73: =SUMIF(Abril_2024[CATEGORÍA],$B73,Abril_2024[EGRESO]) -> 0 | G73: =SUMIF(Mayo_2024[CATEGORÍA],$B73,Mayo_2024[EGRESO]) -> 0 | H73: =SUMIF(Junio_2024[CATEGORÍA],$B73,Junio_2024[EGRESO]) -> 0 | I73: =SUMIF(Julio_2024[CATEGORÍA],$B73,Julio_2024[EGRESO]) -> 0 | J73: =SUMIF(Agosto_2024[CATEGORÍA],$B73,Agosto_2024[EGRESO]) -> 0 | K73: =SUMIF(Septiembre_2024[CATEGORÍA],$B73,Septiembre_2024[EGRESO]) -> 0 | L73: =SUMIF(Octubre_2024[CATEGORÍA],$B73,Octubre_2024[EGRESO]) -> 0 | M73: =SUMIF(Noviembre_2024[CATEGORÍA],$B73,Noviembre_2024[EGRESO]) -> 0 | N73: =SUMIF(Diciembre_2024[CATEGORÍA],$B73,Diciembre_2024[EGRESO]) -> 0 | O73: =SUM(D73:N73) -> 4619.96
B74: Marketing | C74: =SUMIF(Enero_2024[CATEGORÍA],$B74,Enero_2024[EGRESO]) -> 0 | D74: =SUMIF(Febrero_2024[CATEGORÍA],$B74,Febrero_2024[EGRESO]) -> 0 | E74: =SUMIF(Marzo_2024[CATEGORÍA],$B74,Marzo_2024[EGRESO]) -> 0 | F74: =SUMIF(Abril_2024[CATEGORÍA],$B74,Abril_2024[EGRESO]) -> 0 | G74: =SUMIF(Mayo_2024[CATEGORÍA],$B74,Mayo_2024[EGRESO]) -> 0 | H74: =SUMIF(Junio_2024[CATEGORÍA],$B74,Junio_2024[EGRESO]) -> 0 | I74: =SUMIF(Julio_2024[CATEGORÍA],$B74,Julio_2024[EGRESO]) -> 0 | J74: =SUMIF(Agosto_2024[CATEGORÍA],$B74,Agosto_2024[EGRESO]) -> 0 | K74: =SUMIF(Septiembre_2024[CATEGORÍA],$B74,Septiembre_2024[EGRESO]) -> 506 | L74: =SUMIF(Octubre_2024[CATEGORÍA],$B74,Octubre_2024[EGRESO]) -> 0 | M74: =SUMIF(Noviembre_2024[CATEGORÍA],$B74,Noviembre_2024[EGRESO]) -> 0 | N74: =SUMIF(Diciembre_2024[CATEGORÍA],$B74,Diciembre_2024[EGRESO]) -> 0 | O74: =SUM(D74:N74) -> 506
B75: Otros Servicios | C75: =SUMIF(Enero_2024[CATEGORÍA],$B75,Enero_2024[EGRESO]) -> 0 | D75: =SUMIF(Febrero_2024[CATEGORÍA],$B75,Febrero_2024[EGRESO]) -> 0 | E75: =SUMIF(Marzo_2024[CATEGORÍA],$B75,Marzo_2024[EGRESO]) -> 0 | F75: =SUMIF(Abril_2024[CATEGORÍA],$B75,Abril_2024[EGRESO]) -> 0 | G75: =SUMIF(Mayo_2024[CATEGORÍA],$B75,Mayo_2024[EGRESO]) -> 0 | H75: =SUMIF(Junio_2024[CATEGORÍA],$B75,Junio_2024[EGRESO]) -> 0 | I75: =SUMIF(Julio_2024[CATEGORÍA],$B75,Julio_2024[EGRESO]) -> 0 | J75: =SUMIF(Agosto_2024[CATEGORÍA],$B75,Agosto_2024[EGRESO]) -> 0 | K75: =SUMIF(Septiembre_2024[CATEGORÍA],$B75,Septiembre_2024[EGRESO]) -> 0 | L75: =SUMIF(Octubre_2024[CATEGORÍA],$B75,Octubre_2024[EGRESO]) -> 0 | M75: =SUMIF(Noviembre_2024[CATEGORÍA],$B75,Noviembre_2024[EGRESO]) -> 0 | N75: =SUMIF(Diciembre_2024[CATEGORÍA],$B75,Diciembre_2024[EGRESO]) -> 0 | O75: =SUM(D75:N75) -> 0
C76: =SUM(C69:C75) -> 0 | D76: =SUM(D69:D75) -> 4619.96 | E76: =SUM(E69:E75) -> 0 | F76: =SUM(F69:F75) -> 0 | G76: =SUM(G69:G75) -> 0 | H76: =SUM(H69:H75) -> 0 | I76: =SUM(I69:I75) -> 0 | J76: =SUM(J69:J75) -> 0 | ... O76: =SUM(O69:O75) -> 5305.6267
B77: RECURSOS MATERIALES
B78: Compra de Alevines | C78: =SUMIF(Enero_2024[CATEGORÍA],$B78,Enero_2024[EGRESO]) -> 0 | D78: =SUMIF(Febrero_2024[CATEGORÍA],$B78,Febrero_2024[EGRESO]) -> 0 | E78: =SUMIF(Marzo_2024[CATEGORÍA],$B78,Marzo_2024[EGRESO]) -> 0 | F78: =SUMIF(Abril_2024[CATEGORÍA],$B78,Abril_2024[EGRESO]) -> 0 | G78: =SUMIF(Mayo_2024[CATEGORÍA],$B78,Mayo_2024[EGRESO]) -> 0 | H78: =SUMIF(Junio_2024[CATEGORÍA],$B78,Junio_2024[EGRESO]) -> 0 | I78: =SUMIF(Julio_2024[CATEGORÍA],$B78,Julio_2024[EGRESO]) -> 0 | J78: =SUMIF(Agosto_2024[CATEGORÍA],$B78,Agosto_2024[EGRESO]) -> 0 | K78: =SUMIF(Septiembre_2024[CATEGORÍA],$B78,Septiembre_2024[EGRESO]) -> 0 | L78: =SUMIF(Octubre_2024[CATEGORÍA],$B78,Octubre_2024[EGRESO]) -> 0 | M78: =SUMIF(Noviembre_2024[CATEGORÍA],$B78,Noviembre_2024[EGRESO]) -> 0 | N78: =SUMIF(Diciembre_2024[CATEGORÍA],$B78,Diciembre_2024[EGRESO]) -> 0 | O78: =SUM(D78:N78) -> 0
B79: Compra de Alimento | C79: =SUMIF(Enero_2024[CATEGORÍA],$B79,Enero_2024[EGRESO]) -> 2639 | D79: =SUMIF(Febrero_2024[CATEGORÍA],$B79,Febrero_2024[EGRESO]) -> 3322.5 | E79: =SUMIF(Marzo_2024[CATEGORÍA],$B79,Marzo_2024[EGRESO]) -> 9536 | F79: =SUMIF(Abril_2024[CATEGORÍA],$B79,Abril_2024[EGRESO]) -> 4445 | G79: =SUMIF(Mayo_2024[CATEGORÍA],$B79,Mayo_2024[EGRESO]) -> 9927 | H79: =SUMIF(Junio_2024[CATEGORÍA],$B79,Junio_2024[EGRESO]) -> 7425 | I79: =SUMIF(Julio_2024[CATEGORÍA],$B79,Julio_2024[EGRESO]) -> 10952.5 | J79: =SUMIF(Agosto_2024[CATEGORÍA],$B79,Agosto_2024[EGRESO]) -> 15961 | K79: =SUMIF(Septiembre_2024[CATEGORÍA],$B79,Septiembre_2024[EGRESO]) -> 9110.5 | L79: =SUMIF(Octubre_2024[CATEGORÍA],$B79,Octubre_2024[EGRESO]) -> 13075 | M79: =SUMIF(Noviembre_2024[CATEGORÍA],$B79,Noviembre_2024[EGRESO]) -> 0 | N79: =SUMIF(Diciembre_2024[CATEGORÍA],$B79,Diciembre_2024[EGRESO]) -> 0 | O79: =SUM(D79:N79) -> 83754.5
B80: Compra de Medicamentos | C80: =SUMIF(Enero_2024[CATEGORÍA],$B80,Enero_2024[EGRESO]) -> 0 | D80: =SUMIF(Febrero_2024[CATEGORÍA],$B80,Febrero_2024[EGRESO]) -> 0 | E80: =SUMIF(Marzo_2024[CATEGORÍA],$B80,Marzo_2024[EGRESO]) -> 227.5 | F80: =SUMIF(Abril_2024[CATEGORÍA],$B80,Abril_2024[EGRESO]) -> 0 | G80: =SUMIF(Mayo_2024[CATEGORÍA],$B80,Mayo_2024[EGRESO]) -> 0 | H80: =SUMIF(Junio_2024[CATEGORÍA],$B80,Junio_2024[EGRESO]) -> 0 | I80: =SUMIF(Julio_2024[CATEGORÍA],$B80,Julio_2024[EGRESO]) -> 0 | J80: =SUMIF(Agosto_2024[CATEGORÍA],$B80,Agosto_2024[EGRESO]) -> 0 | K80: =SUMIF(Septiembre_2024[CATEGORÍA],$B80,Septiembre_2024[EGRESO]) -> 0 | L80: =SUMIF(Octubre_2024[CATEGORÍA],$B80,Octubre_2024[EGRESO]) -> 0 | M80: =SUMIF(Noviembre_2024[CATEGORÍA],$B80,Noviembre_2024[EGRESO]) -> 0 | N80: =SUMIF(Diciembre_2024[CATEGORÍA],$B80,Diciembre_2024[EGRESO]) -> 0 | O80: =SUM(D80:N80) -> 227.5
B81: Compra Reproductores | C81: =SUMIF(Enero_2024[CATEGORÍA],$B81,Enero_2024[EGRESO]) -> 0 | D81: =SUMIF(Febrero_2024[CATEGORÍA],$B81,Febrero_2024[EGRESO]) -> 0 | E81: =SUMIF(Marzo_2024[CATEGORÍA],$B81,Marzo_2024[EGRESO]) -> 15000 | F81: =SUMIF(Abril_2024[CATEGORÍA],$B81,Abril_2024[EGRESO]) -> 0 | G81: =SUMIF(Mayo_2024[CATEGORÍA],$B81,Mayo_2024[EGRESO]) -> 0 | H81: =SUMIF(Junio_2024[CATEGORÍA],$B81,Junio_2024[EGRESO]) -> 0 | I81: =SUMIF(Julio_2024[CATEGORÍA],$B81,Julio_2024[EGRESO]) -> 0 | J81: =SUMIF(Agosto_2024[CATEGORÍA],$B81,Agosto_2024[EGRESO]) -> 0 | K81: =SUMIF(Septiembre_2024[CATEGORÍA],$B81,Septiembre_2024[EGRESO]) -> 0 | L81: =SUMIF(Octubre_2024[CATEGORÍA],$B81,Octubre_2024[EGRESO]) -> 0 | M81: =SUMIF(Noviembre_2024[CATEGORÍA],$B81,Noviembre_2024[EGRESO]) -> 0 | N81: =SUMIF(Diciembre_2024[CATEGORÍA],$B81,Diciembre_2024[EGRESO]) -> 0 | O81: =SUM(D81:N81) -> 15000
B82: Compra Articulos Probioticos/Bacterias | C82: =SUMIF(Enero_2024[CATEGORÍA],$B82,Enero_2024[EGRESO]) -> 0 | D82: =SUMIF(Febrero_2024[CATEGORÍA],$B82,Febrero_2024[EGRESO]) -> 0 | E82: =SUMIF(Marzo_2024[CATEGORÍA],$B82,Marzo_2024[EGRESO]) -> 0 | F82: =SUMIF(Abril_2024[CATEGORÍA],$B82,Abril_2024[EGRESO]) -> 0 | G82: =SUMIF(Mayo_2024[CATEGORÍA],$B82,Mayo_2024[EGRESO]) -> 0 | H82: =SUMIF(Junio_2024[CATEGORÍA],$B82,Junio_2024[EGRESO]) -> 0 | I82: =SUMIF(Julio_2024[CATEGORÍA],$B82,Julio_2024[EGRESO]) -> 1566 | J82: =SUMIF(Agosto_2024[CATEGORÍA],$B82,Agosto_2024[EGRESO]) -> 1244 | K82: =SUMIF(Septiembre_2024[CATEGORÍA],$B82,Septiembre_2024[EGRESO]) -> 1265 | L82: =SUMIF(Octubre_2024[CATEGORÍA],$B82,Octubre_2024[EGRESO]) -> 0 | M82: =SUMIF(Noviembre_2024[CATEGORÍA],$B82,Noviembre_2024[EGRESO]) -> 0 | N82: =SUMIF(Diciembre_2024[CATEGORÍA],$B82,Diciembre_2024[EGRESO]) -> 0 | O82: =SUM(D82:N82) -> 4075
B83: Compra de Articulos Para Venta | C83: =SUMIF(Enero_2024[CATEGORÍA],$B83,Enero_2024[EGRESO]) -> 0 | D83: =SUMIF(Febrero_2024[CATEGORÍA],$B83,Febrero_2024[EGRESO]) -> 0 | E83: =SUMIF(Marzo_2024[CATEGORÍA],$B83,Marzo_2024[EGRESO]) -> 0 | F83: =SUMIF(Abril_2024[CATEGORÍA],$B83,Abril_2024[EGRESO]) -> 0 | G83: =SUMIF(Mayo_2024[CATEGORÍA],$B83,Mayo_2024[EGRESO]) -> 0 | H83: =SUMIF(Junio_2024[CATEGORÍA],$B83,Junio_2024[EGRESO]) -> 0 | I83: =SUMIF(Julio_2024[CATEGORÍA],$B83,Julio_2024[EGRESO]) -> 0 | J83: =SUMIF(Agosto_2024[CATEGORÍA],$B83,Agosto_2024[EGRESO]) -> 0 | K83: =SUMIF(Septiembre_2024[CATEGORÍA],$B83,Septiembre_2024[EGRESO]) -> 0 | L83: =SUMIF(Octubre_2024[CATEGORÍA],$B83,Octubre_2024[EGRESO]) -> 0 | M83: =SUMIF(Noviembre_2024[CATEGORÍA],$B83,Noviembre_2024[EGRESO]) -> 0 | N83: =SUMIF(Diciembre_2024[CATEGORÍA],$B83,Diciembre_2024[EGRESO]) -> 0 | O83: =SUM(D83:N83) -> 0
B84: Compra de Articulos Limpieza y Desinfeccion | C84: =SUMIF(Enero_2024[CATEGORÍA],$B84,Enero_2024[EGRESO]) -> 0 | D84: =SUMIF(Febrero_2024[CATEGORÍA],$B84,Febrero_2024[EGRESO]) -> 0 | E84: =SUMIF(Marzo_2024[CATEGORÍA],$B84,Marzo_2024[EGRESO]) -> 425 | F84: =SUMIF(Abril_2024[CATEGORÍA],$B84,Abril_2024[EGRESO]) -> 0 | G84: =SUMIF(Mayo_2024[CATEGORÍA],$B84,Mayo_2024[EGRESO]) -> 174.14 | H84: =SUMIF(Junio_2024[CATEGORÍA],$B84,Junio_2024[EGRESO]) -> 0 | I84: =SUMIF(Julio_2024[CATEGORÍA],$B84,Julio_2024[EGRESO]) -> 700 | J84: =SUMIF(Agosto_2024[CATEGORÍA],$B84,Agosto_2024[EGRESO]) -> 0 | K84: =SUMIF(Septiembre_2024[CATEGORÍA],$B84,Septiembre_2024[EGRESO]) -> 0 | L84: =SUMIF(Octubre_2024[CATEGORÍA],$B84,Octubre_2024[EGRESO]) -> 926 | M84: =SUMIF(Noviembre_2024[CATEGORÍA],$B84,Noviembre_2024[EGRESO]) -> 0 | N84: =SUMIF(Diciembre_2024[CATEGORÍA],$B84,Diciembre_2024[EGRESO]) -> 0 | O84: =SUM(D84:N84) -> 2225.14
B85: Devolucion de Alevines | C85: =SUMIF(Enero_2024[CATEGORÍA],$B85,Enero_2024[EGRESO]) -> 0 | D85: =SUMIF(Febrero_2024[CATEGORÍA],$B85,Febrero_2024[EGRESO]) -> 0 | E85: =SUMIF(Marzo_2024[CATEGORÍA],$B85,Marzo_2024[EGRESO]) -> 0 | F85: =SUMIF(Abril_2024[CATEGORÍA],$B85,Abril_2024[EGRESO]) -> 0 | G85: =SUMIF(Mayo_2024[CATEGORÍA],$B85,Mayo_2024[EGRESO]) -> 0 | H85: =SUMIF(Junio_2024[CATEGORÍA],$B85,Junio_2024[EGRESO]) -> 0 | I85: =SUMIF(Julio_2024[CATEGORÍA],$B85,Julio_2024[EGRESO]) -> 0 | J85: =SUMIF(Agosto_2024[CATEGORÍA],$B85,Agosto_2024[EGRESO]) -> 0 | K85: =SUMIF(Septiembre_2024[CATEGORÍA],$B85,Septiembre_2024[EGRESO]) -> 0 | L85: =SUMIF(Octubre_2024[CATEGORÍA],$B85,Octubre_2024[EGRESO]) -> 0 | M85: =SUMIF(Noviembre_2024[CATEGORÍA],$B85,Noviembre_2024[EGRESO]) -> 0 | N85: =SUMIF(Diciembre_2024[CATEGORÍA],$B85,Diciembre_2024[EGRESO]) -> 0 | O85: =SUM(D85:N85) -> 0
B86: Material de Construccion Interno | C86: =SUMIF(Enero_2024[CATEGORÍA],$B86,Enero_2024[EGRESO]) -> 462 | D86: =SUMIF(Febrero_2024[CATEGORÍA],$B86,Febrero_2024[EGRESO]) -> 0 | E86: =SUMIF(Marzo_2024[CATEGORÍA],$B86,Marzo_2024[EGRESO]) -> 0 | F86: =SUMIF(Abril_2024[CATEGORÍA],$B86,Abril_2024[EGRESO]) -> 0 | G86: =SUMIF(Mayo_2024[CATEGORÍA],$B86,Mayo_2024[EGRESO]) -> 0 | H86: =SUMIF(Junio_2024[CATEGORÍA],$B86,Junio_2024[EGRESO]) -> 0 | I86: =SUMIF(Julio_2024[CATEGORÍA],$B86,Julio_2024[EGRESO]) -> 0 | J86: =SUMIF(Agosto_2024[CATEGORÍA],$B86,Agosto_2024[EGRESO]) -> 0 | K86: =SUMIF(Septiembre_2024[CATEGORÍA],$B86,Septiembre_2024[EGRESO]) -> 0 | L86: =SUMIF(Octubre_2024[CATEGORÍA],$B86,Octubre_2024[EGRESO]) -> 0 | M86: =SUMIF(Noviembre_2024[CATEGORÍA],$B86,Noviembre_2024[EGRESO]) -> 0 | N86: =SUMIF(Diciembre_2024[CATEGORÍA],$B86,Diciembre_2024[EGRESO]) -> 0 | O86: =SUM(D86:N86) -> 0
B87: Articulos Infraestructura Interna | C87: =SUMIF(Enero_2024[CATEGORÍA],$B87,Enero_2024[EGRESO]) -> 3892.5 | D87: =SUMIF(Febrero_2024[CATEGORÍA],$B87,Febrero_2024[EGRESO]) -> 0 | E87: =SUMIF(Marzo_2024[CATEGORÍA],$B87,Marzo_2024[EGRESO]) -> 5764 | F87: =SUMIF(Abril_2024[CATEGORÍA],$B87,Abril_2024[EGRESO]) -> 0 | G87: =SUMIF(Mayo_2024[CATEGORÍA],$B87,Mayo_2024[EGRESO]) -> 0 | H87: =SUMIF(Junio_2024[CATEGORÍA],$B87,Junio_2024[EGRESO]) -> 0 | I87: =SUMIF(Julio_2024[CATEGORÍA],$B87,Julio_2024[EGRESO]) -> 0 | J87: =SUMIF(Agosto_2024[CATEGORÍA],$B87,Agosto_2024[EGRESO]) -> 0 | K87: =SUMIF(Septiembre_2024[CATEGORÍA],$B87,Septiembre_2024[EGRESO]) -> 1375 | L87: =SUMIF(Octubre_2024[CATEGORÍA],$B87,Octubre_2024[EGRESO]) -> 0 | M87: =SUMIF(Noviembre_2024[CATEGORÍA],$B87,Noviembre_2024[EGRESO]) -> 0 | N87: =SUMIF(Diciembre_2024[CATEGORÍA],$B87,Diciembre_2024[EGRESO]) -> 0 | O87: =SUM(D87:N87) -> 7139
B88: Articulos de Mantenimiento | C88: =SUMIF(Enero_2024[CATEGORÍA],$B88,Enero_2024[EGRESO]) -> 0 | D88: =SUMIF(Febrero_2024[CATEGORÍA],$B88,Febrero_2024[EGRESO]) -> 820.19 | E88: =SUMIF(Marzo_2024[CATEGORÍA],$B88,Marzo_2024[EGRESO]) -> 370.65 | F88: =SUMIF(Abril_2024[CATEGORÍA],$B88,Abril_2024[EGRESO]) -> 0 | G88: =SUMIF(Mayo_2024[CATEGORÍA],$B88,Mayo_2024[EGRESO]) -> 180 | H88: =SUMIF(Junio_2024[CATEGORÍA],$B88,Junio_2024[EGRESO]) -> 477.52 | I88: =SUMIF(Julio_2024[CATEGORÍA],$B88,Julio_2024[EGRESO]) -> 0 | J88: =SUMIF(Agosto_2024[CATEGORÍA],$B88,Agosto_2024[EGRESO]) -> 576.6512 | K88: =SUMIF(Septiembre_2024[CATEGORÍA],$B88,Septiembre_2024[EGRESO]) -> 0 | L88: =SUMIF(Octubre_2024[CATEGORÍA],$B88,Octubre_2024[EGRESO]) -> 0 | M88: =SUMIF(Noviembre_2024[CATEGORÍA],$B88,Noviembre_2024[EGRESO]) -> 0 | N88: =SUMIF(Diciembre_2024[CATEGORÍA],$B88,Diciembre_2024[EGRESO]) -> 0 | O88: =SUM(D88:N88) -> 2425.0112
B89: Pintura Barniz | C89: =SUMIF(Enero_2024[CATEGORÍA],$B89,Enero_2024[EGRESO]) -> 0 | D89: =SUMIF(Febrero_2024[CATEGORÍA],$B89,Febrero_2024[EGRESO]) -> 0 | E89: =SUMIF(Marzo_2024[CATEGORÍA],$B89,Marzo_2024[EGRESO]) -> 0 | F89: =SUMIF(Abril_2024[CATEGORÍA],$B89,Abril_2024[EGRESO]) -> 0 | G89: =SUMIF(Mayo_2024[CATEGORÍA],$B89,Mayo_2024[EGRESO]) -> 0 | H89: =SUMIF(Junio_2024[CATEGORÍA],$B89,Junio_2024[EGRESO]) -> 0 | I89: =SUMIF(Julio_2024[CATEGORÍA],$B89,Julio_2024[EGRESO]) -> 0 | J89: =SUMIF(Agosto_2024[CATEGORÍA],$B89,Agosto_2024[EGRESO]) -> 0 | K89: =SUMIF(Septiembre_2024[CATEGORÍA],$B89,Septiembre_2024[EGRESO]) -> 0 | L89: =SUMIF(Octubre_2024[CATEGORÍA],$B89,Octubre_2024[EGRESO]) -> 0 | M89: =SUMIF(Noviembre_2024[CATEGORÍA],$B89,Noviembre_2024[EGRESO]) -> 0 | N89: =SUMIF(Diciembre_2024[CATEGORÍA],$B89,Diciembre_2024[EGRESO]) -> 0 | O89: =SUM(D89:N89) -> 0
... B92: Mano de Obra | C92: =SUMIF(Enero_2024[CATEGORÍA],$B92,Enero_2024[EGRESO]) -> 0 | D92: =SUMIF(Febrero_2024[CATEGORÍA],$B92,Febrero_2024[EGRESO]) -> 0 | E92: =SUMIF(Marzo_2024[CATEGORÍA],$B92,Marzo_2024[EGRESO]) -> 0 | F92: =SUMIF(Abril_2024[CATEGORÍA],$B92,Abril_2024[EGRESO]) -> 0 | G92: =SUMIF(Mayo_2024[CATEGORÍA],$B92,Mayo_2024[EGRESO]) -> 0 | H92: =SUMIF(Junio_2024[CATEGORÍA],$B92,Junio_2024[EGRESO]) -> 0 | I92: =SUMIF(Julio_2024[CATEGORÍA],$B92,Julio_2024[EGRESO]) -> 0 | J92: =SUMIF(Agosto_2024[CATEGORÍA],$B92,Agosto_2024[EGRESO]) -> 0 | K92: =SUMIF(Septiembre_2024[CATEGORÍA],$B92,Septiembre_2024[EGRESO]) -> 0 | L92: =SUMIF(Octubre_2024[CATEGORÍA],$B92,Octubre_2024[EGRESO]) -> 0 | M92: =SUMIF(Noviembre_2024[CATEGORÍA],$B92,Noviembre_2024[EGRESO]) -> 0 | N92: =SUMIF(Diciembre_2024[CATEGORÍA],$B92,Diciembre_2024[EGRESO]) -> 0 | O92: =SUM(D92:N92) -> 0
C93: =SUM(C78:C92) -> 6993.5 | D93: =SUM(D78:D92) -> 4142.69 | E93: =SUM(E78:E92) -> 31323.15 | F93: =SUM(F78:F92) -> 4445 | G93: =SUM(G78:G92) -> 10281.14 | H93: =SUM(H78:H92) -> 7902.52 | I93: =SUM(I78:I92) -> 13218.5 | J93: =SUM(J78:J92) -> 18577.536 | ... O93: =SUM(O78:O92) -> 118975.37
B95: TOTAL | C95: =C93+C76+C67+C56 -> 34415.88 | D95: =D93+D76+D67+D56 -> 36581.15 | E95: =E93+E76+E67+E56 -> 72314.15 | F95: =F93+F76+F67+F56 -> 30745 | G95: =G93+G76+G67+G56 -> 35741.14 | H95: =H93+H76+H67+H56 -> 34111.52 | I95: =I93+I76+I67+I56 -> 45890.18 | J95: =J93+J76+J67+J56 -> 83017.536 | ... O95: =O93+O76+O67+O56 -> 407900.51

Sheet Cuentas
B2: CUENTAS CORRIENTES | F2: =SUM(F3:F4) -> 0
B3: Cheques BBVA | F3: 0
B4: Efectivo | F4: 0
B5: JC Jr.
B6: LINEAS DE CREDITO | F6: =SUM(F7:F8) -> 0
F7: 0
F8: 0
B10: OTROS ACTIVOS | F10: =SUM(F11:F12) -> 0
F11: 0
F12: 0
B14: OTROS PASIVOS | F14: =SUM(F15:F16) -> 0
F15: 0
F16: 0

Sheet Entradas y Salidas
A2: HISTORIAL DE TRANSACCIONES
B4: ENERO 2025
B5: CUENTA | C5: FECHA | D5: INGRESO | E5: EGRESO | F5: BENEFICIARIO/PROVEEDOR | G5: NO. FACTURA | H5: NO. PROYECTO | I5: DESCRIPCION | J5: CATEGORÍA | K5: SUB CATEGORIA | L5: EQUILIBRAR
B6: Cheques BBVA | C6: 45293 | E6: 1492.81 | F6: VAQUEIROS FERRETEROS | G6: PENDIENTE | H6: GASTOS INTERNOS | I6: Contectores de Mangueras | J6: Articulos Infraestructura Interna | L6: =IF(ISERROR(OFFSET(L6,-1,0,1,1)+D6-E6),D6-E6,OFFSET(L6,-1,0,1,1)+D6-E6) -> -1492.81
B7: Efectivo | C7: 45295 | E7: 356.66667 | F7: MANANTIAL DE VIDA | G7: NO APLICA | H7: GASTOS INTERNOS | I7: Pastel y Rosca | J7: Otro RRHH | L7: =IF(ISERROR(OFFSET(L7,-1,0,1,1)+D7-E7),D7-E7,OFFSET(L7,-1,0,1,1)+D7-E7) -> -1849.4767
B8: Efectivo | C8: 45661 | E8: 4137.1429 | F8: JOSE ACOSTA FARIAS | G8: NO APLICA | H8: NOMINA | J8: Sueldos y Salarios | L8: =IF(ISERROR(OFFSET(L8,-1,0,1,1)+'[1]Entradas y Salidas'!D9-'[1]Entradas y Salidas'!E9),'[1]Entradas y Salidas'!D9-'[1]Entradas y Salidas'!E9,OFFSET(L8,-1,0,1,1)+'[1]Entradas y Salidas'!D9-'[1]Entradas y Salidas'!E9) -> -2349.4767
B9: Efectivo | C9: 45661 | E9: 3420 | F9: DERIK ALEXIS CHABLE PASCUAL | G9: NO APLICA | H9: NOMINA | J9: Sueldos y Salarios | L9: =IF(ISERROR(OFFSET(L9,-1,0,1,1)+D9-E9),D9-E9,OFFSET(L9,-1,0,1,1)+D9-E9) -> -5769.4767
B10: Efectivo | C10: 45661 | E10: 200 | F10: DERIK ALEXIS CHABLE PASCUAL | G10: NO APLICA | H10: CAJA DE AHORRO | J10: Caja de Ahorro | L10: =IF(ISERROR(OFFSET(L10,-1,0,1,1)+D10-E10),D10-E10,OFFSET(L10,-1,0,1,1)+D10-E10) -> -5969.4767
B11: Efectivo | C11: 45661 | E11: 1968.57 | F11: YARA ODILIA RIVERA MARQUEZ | G11: NO APLICA | H11: NOMINA | J11: Sueldos y Salarios | L11: =IF(ISERROR(OFFSET(L11,-1,0,1,1)+D11-E11),D11-E11,OFFSET(L11,-1,0,1,1)+D11-E11) -> -7938.0467
B12: Efectivo | C12: 45661 | E12: 200 | F12: YARA ODILIA RIVERA MARQUEZ | G12: NO APLICA | H12: CAJA DE AHORRO | J12: Caja de Ahorro | L12: =IF(ISERROR(OFFSET(L12,-1,0,1,1)+D12-E12),D12-E12,OFFSET(L12,-1,0,1,1)+D12-E12) -> -8138.0467
B13: Efectivo | C13: 45661 | E13: 900 | F13: SELENE RIVERA ALCAZAR | G13: NO APLICA | H13: NOMINA | J13: Sueldos y Salarios | L13: =IF(ISERROR(OFFSET(L13,-1,0,1,1)+D13-E13),D13-E13,OFFSET(L13,-1,0,1,1)+D13-E13) -> -9038.0467
B14: Efectivo | C14: 45661 | E14: 200 | F14: SELENE RIVERA ALCAZAR | G14: NO APLICA | H14: CAJA DE AHORRO | J14: Caja de Ahorro | L14: =IF(ISERROR(OFFSET(L14,-1,0,1,1)+D14-E14),D14-E14,OFFSET(L14,-1,0,1,1)+D14-E14) -> -9238.0467
B15: Efectivo | C15: 45661 | E15: 2400 | F15: PATRICIO ACOSTA FARIAS | G15: NO APLICA | H15: NOMINA | J15: Sueldos y Salarios | L15: =IF(ISERROR(OFFSET(L15,-1,0,1,1)+D15-E15),D15-E15,OFFSET(L15,-1,0,1,1)+D15-E15) -> -11638.047
B16: Efectivo | C16: 45661 | E16: 400 | F16: PATRICIO ACOSTA FARIAS | G16: NO APLICA | H16: CAJA DE AHORRO | J16: Caja de Ahorro | L16: =IF(ISERROR(OFFSET(L16,-1,0,1,1)+D16-E16),D16-E16,OFFSET(L16,-1,0,1,1)+D16-E16) -> -12038.047
B17: Efectivo | C17: 45666 | E17: 2639 | F17: JYY AGROPECUARIA DE TABASCO | G17: BA 10871 | H17: GASTOS INTERNOS | I17: Alimento Hormonado y Dyno | J17: Compra de Alimento | L17: =IF(ISERROR(OFFSET(L17,-1,0,1,1)+D17-E17),D17-E17,OFFSET(L17,-1,0,1,1)+D17-E17) -> -14677.047
B18: Efectivo | C18: 45666 | E18: 600 | F18: FERRETERIA CHISPITA | G18: NO APLICA | H18: GASTOS INTERNOS | I18: Malla Mirinaque | J18: Articulos Infraestructura Interna | L18: =IF(ISERROR(OFFSET(L18,-1,0,1,1)+D18-E18),D18-E18,OFFSET(L18,-1,0,1,1)+D18-E18) -> -15277.047
B19: Efectivo | C19: 45667 | E19: 682.19 | F19: VAQUEIROS FERRETEROS | G19: C 601757 | H19: GASTOS INTERNOS | I19: Tensores, Conectores PVC Macho/Hembra | J19: Articulos Infraestructura Interna | L19: =IF(ISERROR(OFFSET(L19,-1,0,1,1)+D19-E19),D19-E19,OFFSET(L19,-1,0,1,1)+D19-E19) -> -15959.237
B20: Efectivo | C20: 45670 | D20: 1200 | F20: JORGE GAXIOLA | G20: NO APLICA | H20: GAM-0125001 | I20: Venta Alevines (1,000) | J20: Venta de Alevines | L20: =IF(ISERROR(OFFSET(L20,-1,0,1,1)+D20-E20),D20-E20,OFFSET(L20,-1,0,1,1)+D20-E20) -> -14759.237
B21: Cheques BBVA | C21: 45670 | D21: 8100 | F21: ELEAZER RIOS JIMENEZ / ACUICOLA TRES RIOS | G21: NO APLICA | H21: GAM-0125002 | I21: Venta Alevines (6,750) | J21: Venta de Alevines | L21: =IF(ISERROR(OFFSET(L21,-1,0,1,1)+D21-E21),D21-E21,OFFSET(L21,-1,0,1,1)+D21-E21) -> -6659.2367
B22: Efectivo | C22: 45671 | E22: 462 | F22: MATERIALES "SAN ROMAN" | G22: A4-7770 | H22: GASTOS INTERNOS | I22: Cemento Gris y Cal | J22: Material de Construccion Interno | L22: =IF(ISERROR(OFFSET(L22,-1,0,1,1)+D22-E22),D22-E22,OFFSET(L22,-1,0,1,1)+D22-E22) -> -7121.2367
B23: Efectivo | C23: 45675 | E23: 4480 | F23: JOSE ACOSTA FARIAS | G23: NO APLICA | H23: NOMINA | J23: Sueldos y Salarios | L23: =IF(ISERROR(OFFSET(L23,-1,0,1,1)+D23-E23),D23-E23,OFFSET(L23,-1,0,1,1)+D23-E23) -> -11601.237
B24: Efectivo | C24: 45675 | E24: 3520 | F24: DERIK ALEXIS CHABLE PASCUAL | G24: NO APLICA | H24: NOMINA | J24: Sueldos y Salarios | L24: =IF(ISERROR(OFFSET(L24,-1,0,1,1)+D24-E24),D24-E24,OFFSET(L24,-1,0,1,1)+D24-E24) -> -15121.237
B25: Efectivo | C25: 45675 | E25: 400 | F25: DERIK ALEXIS CHABLE PASCUAL | G25: NO APLICA | H25: CAJA DE AHORRO | J25: Caja de Ahorro | L25: =IF(ISERROR(OFFSET(L25,-1,0,1,1)+D25-E25),D25-E25,OFFSET(L25,-1,0,1,1)+D25-E25) -> -15521.237
B26: Efectivo | C26: 45675 | E26: 2040 | F26: YARA ODILIA RIVERA MARQUEZ | G26: NO APLICA | H26: NOMINA | J26: Sueldos y Salarios | L26: =IF(ISERROR(OFFSET(L26,-1,0,1,1)+D26-E26),D26-E26,OFFSET(L26,-1,0,1,1)+D26-E26) -> -17561.237
B27: Efectivo | C27: 45675 | E27: 400 | F27: YARA ODILIA RIVERA MARQUEZ | G27: NO APLICA | H27: CAJA DE AHORRO | J27: Caja de Ahorro | L27: =IF(ISERROR(OFFSET(L27,-1,0,1,1)+D27-E27),D27-E27,OFFSET(L27,-1,0,1,1)+D27-E27) -> -17961.237
B28: Efectivo | C28: 45675 | E28: 800 | F28: SELENE RIVERA ALCAZAR | G28: NO APLICA | H28: NOMINA | J28: Sueldos y Salarios | L28: =IF(ISERROR(OFFSET(L28,-1,0,1,1)+D28-E28),D28-E28,OFFSET(L28,-1,0,1,1)+D28-E28) -> -18761.237
B29: Efectivo | C29: 45675 | E29: 400 | F29: SELENE RIVERA ALCAZAR | G29: NO APLICA | H29: CAJA DE AHORRO | J29: Caja de Ahorro | L29: =IF(ISERROR(OFFSET(L29,-1,0,1,1)+D29-E29),D29-E29,OFFSET(L29,-1,0,1,1)+D29-E29) -> -19161.237
B30: Efectivo | C30: 45675 | E30: 800 | F30: PATRICIO ACOSTA FARIAS | G30: NO APLICA | H30: NOMINA | J30: Sueldos y Salarios | L30: =IF(ISERROR(OFFSET(L30,-1,0,1,1)+D30-E30),D30-E30,OFFSET(L30,-1,0,1,1)+D30-E30) -> -19961.237
B31: Efectivo | C31: 45675 | E31: 400 | F31: PATRICIO ACOSTA FARIAS | G31: NO APLICA | H31: CAJA DE AHORRO | J31: Caja de Ahorro | L31: =IF(ISERROR(OFFSET(L31,-1,0,1,1)+D31-E31),D31-E31,OFFSET(L31,-1,0,1,1)+D31-E31) -> -20361.237
B32: Efectivo | C32: 45675 | D32: 504 | F32: ALEJANDRO DOMINGUEZ | G32: NO APLICA | H32: GAM-0125003 | I32: Venta Alevines (420) | J32: Venta de Alevines | L32: =IF(ISERROR(OFFSET(L32,-1,0,1,1)+D32-E32),D32-E32,OFFSET(L32,-1,0,1,1)+D32-E32) -> -19857.237
B33: Cheques BBVA | C33: 45677 | E33: 937.5 | F33: POLIETILENOS DE TABASCO | G33: PENDIENTE | H33: GASTOS INTERNOS | I33: Bolsas 60 x 90 | J33: Articulos Infraestructura Interna | L33: =IF(ISERROR(OFFSET(L33,-1,0,1,1)+D33-E33),D33-E33,OFFSET(L33,-1,0,1,1)+D33-E33) -> -20794.737
B34: Efectivo | C34: 45677 | D34: 6840 | F34: ARTURO RABELO | G34: NO APLICA | H34: GAM-0125004 | I34: Venta Alevines (7,500) | J34: Venta de Alevines | L34: =IF(ISERROR(OFFSET(L34,-1,0,1,1)+D34-E34),D34-E34,OFFSET(L34,-1,0,1,1)+D34-E34) -> -13954.737
B35: Efectivo | C35: 45680 | D35: 2400 | F35: ALEJANDRO DOMINGUEZ | G35: NO APLICA | H35: GAM-0125005 | I35: Venta Alevines (2,000) | J35: Venta de Alevines | L35: =IF(ISERROR(OFFSET(L35,-1,0,1,1)+D35-E35),D35-E35,OFFSET(L35,-1,0,1,1)+D35-E35) -> -11554.737
B36: Efectivo | C36: 45682 | E36: 180 | F36: MATERIALES DE CONSTRUCCION ALAMILLA | G36: PENDIENTE | H36: GASTOS INTERNOS | I36: Conectores PVC | J36: Articulos Infraestructura Interna | L36: =IF(ISERROR(OFFSET(L36,-1,0,1,1)+D36-E36),D36-E36,OFFSET(L36,-1,0,1,1)+D36-E36) -> -11734.737
B37: Efectivo | C37: 45684 | D37: 3000 | F37: JAIME LASTRA | G37: NO APLICA | H37: GAM-0125006 | I37: Venta Alevines (2,500) | J37: Venta de Alevines | L37: =IF(ISERROR(OFFSET(L37,-1,0,1,1)+D37-E37),D37-E37,OFFSET(L37,-1,0,1,1)+D37-E37) -> -8734.7367
L38: =IF(ISERROR(OFFSET(L38,-1,0,1,1)+D38-E38),D38-E38,OFFSET(L38,-1,0,1,1)+D38-E38) -> -8734.7367
L39: =IF(ISERROR(OFFSET(L39,-1,0,1,1)+D39-E39),D39-E39,OFFSET(L39,-1,0,1,1)+D39-E39) -> -8734.7367
L40: =IF(ISERROR(OFFSET(L40,-1,0,1,1)+D40-E40),D40-E40,OFFSET(L40,-1,0,1,1)+D40-E40) -> -8734.7367
L41: =IF(ISERROR(OFFSET(L41,-1,0,1,1)+D41-E41),D41-E41,OFFSET(L41,-1,0,1,1)+D41-E41) -> -8734.7367
L42: =IF(ISERROR(OFFSET(L42,-1,0,1,1)+D42-E42),D42-E42,OFFSET(L42,-1,0,1,1)+D42-E42) -> -8734.7367
L43: =IF(ISERROR(OFFSET(L43,-1,0,1,1)+D43-E43),D43-E43,OFFSET(L43,-1,0,1,1)+D43-E43) -> -8734.7367
L44: =IF(ISERROR(OFFSET(L44,-1,0,1,1)+D44-E44),D44-E44,OFFSET(L44,-1,0,1,1)+D44-E44) -> -8734.7367
L45: =IF(ISERROR(OFFSET(L45,-1,0,1,1)+D45-E45),D45-E45,OFFSET(L45,-1,0,1,1)+D45-E45) -> -8734.7367
L46: =IF(ISERROR(OFFSET(L46,-1,0,1,1)+D46-E46),D46-E46,OFFSET(L46,-1,0,1,1)+D46-E46) -> -8734.7367
D47: =SUBTOTAL(109,Enero_2024[INGRESO]) -> 22044 | E47: =SUBTOTAL(109,Enero_2024[EGRESO]) -> 34415.88
B49: FEBRERO 2025
B50: CUENTA | C50: FECHA | D50: INGRESO | E50: EGRESO | F50: BENEFICIARIO/PROVEEDOR | G50: NO. FACTURA | H50: NO. PROYECTO | I50: DESCRIPCION | J50: CATEGORÍA | K50: SUB CATEGORIA | L50: EQUILIBRAR
B51: Efectivo | C51: 45689 | D51: 500 | F51: ALEJANDRO DOMINGUEZ | G51: NO APLICA | H51: GAM-0225001 | I51: Venta de Alevines (500) | J51: Venta de Alevines | L51: =IF(ISERROR(OFFSET(L51,-1,0,1,1)+D51-E51),D51-E51,OFFSET(L51,-1,0,1,1)+D51-E51) -> 500
B52: Efectivo | C52: 45689 | E52: 4500 | F52: JOSE ALFREDO ACOSTA FARIAS | G52: NO APLICA | H52: NOMINA | J52: Sueldos y Salarios | L52: =IF(ISERROR(OFFSET(L52,-1,0,1,1)+D52-E52),D52-E52,OFFSET(L52,-1,0,1,1)+D52-E52) -> -4000
B53: Efectivo | C53: 45689 | E53: 3500 | F53: DERKI ALEXIS CHABLE PASCUAL | G53: NO APLICA | H53: NOMINA | J53: Sueldos y Salarios | L53: =IF(ISERROR(OFFSET(L53,-1,0,1,1)+D53-E53),D53-E53,OFFSET(L53,-1,0,1,1)+D53-E53) -> -7500
B54: Efectivo | C54: 45689 | E54: 400 | F54: DERKI ALEXIS CHABLE PASCUAL | G54: NO APLICA | H54: CAJA DE AHORRO | J54: Caja de Ahorro | L54: =IF(ISERROR(OFFSET(L54,-1,0,1,1)+D54-E54),D54-E54,OFFSET(L54,-1,0,1,1)+D54-E54) -> -7900
B55: Efectivo | C55: 45689 | E55: 2050 | F55: YARA ODILIA RIVERA MARQUEZ | G55: NO APLICA | H55: NOMINA | J55: Sueldos y Salarios | L55: =IF(ISERROR(OFFSET(L55,-1,0,1,1)+D55-E55),D55-E55,OFFSET(L55,-1,0,1,1)+D55-E55) -> -9950
B56: Efectivo | C56: 45689 | E56: 400 | F56: YARA ODILIA RIVERA MARQUEZ | G56: NO APLICA | H56: CAJA DE AHORRO | J56: Caja de Ahorro | L56: =IF(ISERROR(OFFSET(L56,-1,0,1,1)+D56-E56),D56-E56,OFFSET(L56,-1,0,1,1)+D56-E56) -> -10350
B57: Efectivo | C57: 45689 | E57: 2000 | F57: PATRICIO ACOSTA | G57: NO APLICA | H57: NOMINA | J57: Sueldos y Salarios | L57: =IF(ISERROR(OFFSET(L57,-1,0,1,1)+D57-E57),D57-E57,OFFSET(L57,-1,0,1,1)+D57-E57) -> -12350
B58: Efectivo | C58: 45689 | E58: 400 | F58: PATRICIO ACOSTA | G58: NO APLICA | H58: CAJA DE AHORRO | J58: Caja de Ahorro | L58: =IF(ISERROR(OFFSET(L58,-1,0,1,1)+D58-E58),D58-E58,OFFSET(L58,-1,0,1,1)+D58-E58) -> -12750
B59: Efectivo | C59: 45689 | E59: 800 | F59: SELENE RIVERA ALCAZAR | G59: NO APLICA | H59: NOMINA | J59: Sueldos y Salarios | L59: =IF(ISERROR(OFFSET(L59,-1,0,1,1)+D59-E59),D59-E59,OFFSET(L59,-1,0,1,1)+D59-E59) -> -13550
B60: Efectivo | C60: 45689 | E60: 400 | F60: SELENE RIVERA ALCAZAR | G60: NO APLICA | H60: CAJA DE AHORRO | J60: Caja de Ahorro | L60: =IF(ISERROR(OFFSET(L60,-1,0,1,1)+D60-E60),D60-E60,OFFSET(L60,-1,0,1,1)+D60-E60) -> -13950
B61: Efectivo | C61: 45700 | D61: 450 | F61: PEDRO MORA | G61: NO APLICA | H61: GAM-0225002 | I61: Venta de Alevines (500) | J61: Venta de Alevines | L61: =IF(ISERROR(OFFSET(L61,-1,0,1,1)+D61-E61),D61-E61,OFFSET(L61,-1,0,1,1)+D61-E61) -> -13500
B62: Efectivo | C62: 45700 | D62: 720 | F62: PEDRO MORA | G62: NO APLICA | H62: GAM-0225003 | I62: Venta de Alevines (800) | J62: Venta de Alevines | L62: =IF(ISERROR(OFFSET(L62,-1,0,1,1)+D62-E62),D62-E62,OFFSET(L62,-1,0,1,1)+D62-E62) -> -12780
B63: Efectivo | C63: 45701 | D63: 6300 | F63: PEDRO MORA | G63: NO APLICA | H63: GAM-0225004 | I63: Venta de Alevines (7000) | J63: Venta de Alevines | L63: =IF(ISERROR(OFFSET(L63,-1,0,1,1)+D63-E63),D63-E63,OFFSET(L63,-1,0,1,1)+D63-E63) -> -6480
B64: Reposicion JC Jr. | C64: 45701 | E64: 393.96 | F64: MAIL BOXES ETC | G64: 2200021673 | H64: GASTOS INTERNOS | I64: Envio Documentos a Senasica Certificacion | J64: Certificaciones | L64: =IF(ISERROR(OFFSET(L64,-1,0,1,1)+D64-E64),D64-E64,OFFSET(L64,-1,0,1,1)+D64-E64) -> -6873.96
B65: Cheques BBVA | C65: 45701 | E65: 4226 | F65: SENASICA | G65: NO APLICA | H65: GASTOS INTERNOS | I65: Pago Derechos Certificacion | J65: Certificaciones | L65: =IF(ISERROR(OFFSET(L65,-1,0,1,1)+D65-E65),D65-E65,OFFSET(L65,-1,0,1,1)+D65-E65) -> -11099.96
B66: Efectivo | C66: 45703 | D66: 108 | F66: PEDRO MORA | G66: NO APLICA | H66: GAM-0225005 | I66: Venta de Alevines (120) | J66: Venta de Alevines | L66: =IF(ISERROR(OFFSET(L66,-1,0,1,1)+D66-E66),D66-E66,OFFSET(L66,-1,0,1,1)+D66-E66) -> -10991.96
B67: Efectivo | C67: 45703 | D67: 2400 | F67: MIGUEL PEREZ | G67: NO APLICA | H67: GAM-0225006 | I67: Venta de Alevines (2,000) | J67: Venta de Alevines | L67: =IF(ISERROR(OFFSET(L67,-1,0,1,1)+D67-E67),D67-E67,OFFSET(L67,-1,0,1,1)+D67-E67) -> -8591.96
B68: Efectivo | C68: 45703 | E68: 4500 | F68: JOSE ALFREDO ACOSTA FARIAS | G68: NO APLICA | H68: NOMINA | J68: Sueldos y Salarios | L68: =IF(ISERROR(OFFSET(L68,-1,0,1,1)+D68-E68),D68-E68,OFFSET(L68,-1,0,1,1)+D68-E68) -> -13091.96
B69: Efectivo | C69: 45703 | E69: 918.5 | F69: JOSE ALFREDO ACOSTA FARIAS | G69: NO APLICA | H69: NOMINA | J69: Incentivos/Bonos | L69: =IF(ISERROR(OFFSET(L69,-1,0,1,1)+D69-E69),D69-E69,OFFSET(L69,-1,0,1,1)+D69-E69) -> -14010.46
B70: Efectivo | C70: 45703 | E70: 3500 | F70: DERKI ALEXIS CHABLE PASCUAL | G70: NO APLICA | H70: NOMINA | J70: Sueldos y Salarios | L70: =IF(ISERROR(OFFSET(L70,-1,0,1,1)+D70-E70),D70-E70,OFFSET(L70,-1,0,1,1)+D70-E70) -> -17510.46
B71: Efectivo | C71: 45703 | E71: 400 | F71: DERKI ALEXIS CHABLE PASCUAL | G71: NO APLICA | H71: CAJA DE AHORRO | J71: Caja de Ahorro | L71: =IF(ISERROR(OFFSET(L71,-1,0,1,1)+D71-E71),D71-E71,OFFSET(L71,-1,0,1,1)+D71-E71) -> -17910.46
B72: Efectivo | C72: 45703 | E72: 2050 | F72: YARA ODILIA RIVERA MARQUEZ | G72: NO APLICA | H72: NOMINA | J72: Sueldos y Salarios | L72: =IF(ISERROR(OFFSET(L72,-1,0,1,1)+D72-E72),D72-E72,OFFSET(L72,-1,0,1,1)+D72-E72) -> -19960.46
B73: Efectivo | C73: 45703 | E73: 400 | F73: YARA ODILIA RIVERA MARQUEZ | G73: NO APLICA | H73: CAJA DE AHORRO | J73: Caja de Ahorro | L73: =IF(ISERROR(OFFSET(L73,-1,0,1,1)+D73-E73),D73-E73,OFFSET(L73,-1,0,1,1)+D73-E73) -> -20360.46
B74: Efectivo | C74: 45703 | E74: 400 | F74: PATRICIO ACOSTA | G74: NO APLICA | H74: NOMINA | J74: Caja de Ahorro | L74: =IF(ISERROR(OFFSET(L74,-1,0,1,1)+D74-E74),D74-E74,OFFSET(L74,-1,0,1,1)+D74-E74) -> -20760.46
B75: Efectivo | C75: 45703 | E75: 800 | F75: SELENE RIVERA ALCAZAR | G75: NO APLICA | H75: NOMINA | J75: Sueldos y Salarios | L75: =IF(ISERROR(OFFSET(L75,-1,0,1,1)+D75-E75),D75-E75,OFFSET(L75,-1,0,1,1)+D75-E75) -> -21560.46
B76: Efectivo | C76: 45703 | E76: 400 | F76: SELENE RIVERA ALCAZAR | G76: NO APLICA | H76: CAJA DE AHORRO | J76: Caja de Ahorro | L76: =IF(ISERROR(OFFSET(L76,-1,0,1,1)+D76-E76),D76-E76,OFFSET(L76,-1,0,1,1)+D76-E76) -> -21960.46
B77: Cheques BBVA | C77: 45707 | E77: 3322.5 | F77: RODOLFO SANCHEZ VIMIFOS | G77: NO APLICA | H77: GASTOS INTERNOS | I77: Alimento VIMIFOS | J77: Compra de Alimento | L77: =IF(ISERROR(OFFSET(L77,-1,0,1,1)+D77-E77),D77-E77,OFFSET(L77,-1,0,1,1)+D77-E77) -> -25282.96
B78: Efectivo | C78: 45708 | D78: 990 | F78: PEDRO MORA | G78: NO APLICA | H78: GAM-0225007 | I78: Venta de Alevines (1,100) | J78: Venta de Alevines | L78: =IF(ISERROR(OFFSET(L78,-1,0,1,1)+D78-E78),D78-E78,OFFSET(L78,-1,0,1,1)+D78-E78) -> -24292.96
B79: Efectivo | C79: 45708 | D79: 900 | F79: PEDRO MORA | G79: NO APLICA | H79: GAM-0225008 | I79: Venta de Alevines (1,000) | J79: Venta de Alevines | L79: =IF(ISERROR(OFFSET(L79,-1,0,1,1)+D79-E79),D79-E79,OFFSET(L79,-1,0,1,1)+D79-E79) -> -23392.96
B80: Efectivo | C80: 45710 | D80: 100 | F80: DAVID JIMENEZ | G80: NO APLICA | H80: GAMALI-0224001 | I80: 2 Kg | J80: Venta de Alimento | L80: =IF(ISERROR(OFFSET(L80,-1,0,1,1)+D80-E80),D80-E80,OFFSET(L80,-1,0,1,1)+D80-E80) -> -23292.96
B81: Efectivo | C81: 45711 | D81: 1200 | F81: DEYSI TORRES | G81: NO APLICA | H81: GAM-0225009 | I81: Venta de Alevines (1,000) | J81: Venta de Alevines | L81: =IF(ISERROR(OFFSET(L81,-1,0,1,1)+D81-E81),D81-E81,OFFSET(L81,-1,0,1,1)+D81-E81) -> -22092.96
B82: Efectivo | C82: 45711 | D82: 100 | F82: DEYSI TORRES | G82: NO APLICA | H82: GAMALI-0224002 | I82: 2 Kg | J82: Venta de Alimento | L82: =IF(ISERROR(OFFSET(L82,-1,0,1,1)+D82-E82),D82-E82,OFFSET(L82,-1,0,1,1)+D82-E82) -> -21992.96
B83: Efectivo | C83: 45711 | D83: 900 | F83: PEDRO MORA | G83: NO APLICA | H83: GAM-0225010 | I83: Venta de Alevines (1,000) | J83: Venta de Alevines | L83: =IF(ISERROR(OFFSET(L83,-1,0,1,1)+D83-E83),D83-E83,OFFSET(L83,-1,0,1,1)+D83-E83) -> -21092.96
B84: Efectivo | C84: 45712 | E84: 820.19 | F84: VAQUEIROS FERRETEROS | G84: H 501180 | H84: GASTOS INTERNOS | I84: Interruptores y Flotador Bomba | J84: Articulos de Mantenimiento | L84: =IF(ISERROR(OFFSET(L84,-1,0,1,1)+D84-E84),D84-E84,OFFSET(L84,-1,0,1,1)+D84-E84) -> -21913.15
B85: Efectivo | C85: 45713 | D85: 1350 | F85: PEDRO MORA | G85: NO APLICA | H85: GAM-0225011 | I85: Venta de Alevines (1,500) | J85: Venta de Alevines | L85: =IF(ISERROR(OFFSET(L85,-1,0,1,1)+D85-E85),D85-E85,OFFSET(L85,-1,0,1,1)+D85-E85) -> -20563.15
B86: Efectivo | C86: 45715 | D86: 150 | F86: PEDRO MORA | G86: NO APLICA | H86: GAMALI-0224003 | I86: 3 Kg | J86: Venta de Alimento | L86: =IF(ISERROR(OFFSET(L86,-1,0,1,1)+D86-E86),D86-E86,OFFSET(L86,-1,0,1,1)+D86-E86) -> -20413.15
L87: =IF(ISERROR(OFFSET(L87,-1,0,1,1)+D87-E87),D87-E87,OFFSET(L87,-1,0,1,1)+D87-E87) -> -20413.15
L88: =IF(ISERROR(OFFSET(L88,-1,0,1,1)+D88-E88),D88-E88,OFFSET(L88,-1,0,1,1)+D88-E88) -> -20413.15
L89: =IF(ISERROR(OFFSET(L89,-1,0,1,1)+D89-E89),D89-E89,OFFSET(L89,-1,0,1,1)+D89-E89) -> -20413.15
L90: =IF(ISERROR(OFFSET(L90,-1,0,1,1)+D90-E90),D90-E90,OFFSET(L90,-1,0,1,1)+D90-E90) -> -20413.15
L91: =IF(ISERROR(OFFSET(L91,-1,0,1,1)+D91-E91),D91-E91,OFFSET(L91,-1,0,1,1)+D91-E91) -> -20413.15
L92: =IF(ISERROR(OFFSET(L92,-1,0,1,1)+D92-E92),D92-E92,OFFSET(L92,-1,0,1,1)+D92-E92) -> -20413.15
L93: =IF(ISERROR(OFFSET(L93,-1,0,1,1)+D93-E93),D93-E93,OFFSET(L93,-1,0,1,1)+D93-E93) -> -20413.15
L94: =IF(ISERROR(OFFSET(L94,-1,0,1,1)+D94-E94),D94-E94,OFFSET(L94,-1,0,1,1)+D94-E94) -> -20413.15
L95: =IF(ISERROR(OFFSET(L95,-1,0,1,1)+D95-E95),D95-E95,OFFSET(L95,-1,0,1,1)+D95-E95) -> -20413.15
L96: =IF(ISERROR(OFFSET(L96,-1,0,1,1)+D96-E96),D96-E96,OFFSET(L96,-1,0,1,1)+D96-E96) -> -20413.15
L97: =IF(ISERROR(OFFSET(L97,-1,0,1,1)+D97-E97),D97-E97,OFFSET(L97,-1,0,1,1)+D97-E97) -> -20413.15
L98: =IF(ISERROR(OFFSET(L98,-1,0,1,1)+D98-E98),D98-E98,OFFSET(L98,-1,0,1,1)+D98-E98) -> -20413.15
... L109: =IF(ISERROR(OFFSET(L109,-1,0,1,1)+D109-E109),D109-E109,OFFSET(L109,-1,0,1,1)+D109-E109) -> -20413.15
D110: =SUBTOTAL(109,Febrero_2024[INGRESO]) -> 16168 | E110: =SUBTOTAL(109,Febrero_2024[EGRESO]) -> 36581.15
B112: MARZO 2025
B113: CUENTA | C113: FECHA | D113: INGRESO | E113: EGRESO | F113: BENEFICIARIO/PROVEEDOR | G113: NO. FACTURA | H113: NO. PROYECTO | I113: DESCRIPCION | J113: CATEGORÍA | K113: SUB CATEGORIA | L113: EQUILIBRAR
B114: Efectivo | C114: 45717 | E114: 4500 | F114: JOSE ALFREDO ACOSTA FARIAS | G114: NO APLICA | H114: NOMINA | J114: Sueldos y Salarios | L114: =IF(ISERROR(OFFSET(L114,-1,0,1,1)+D114-E114),D114-E114,OFFSET(L114,-1,0,1,1)+D114-E114) -> -4500
...

Sheet Estimado
B1: SEGUIMIENTO DE TESORERIA
C2: ENERO | D2: FEBRERO | E2: MARZO | F2: ABRIL | G2: MAYO | H2: JUNIO | I2: JULIO | J2: AGOSTO | K2: SEPTIEMBRE | L2: OCTUBRE | M2: NOVIEMBRE | N2: DICIEMBRE
B3: Saldo inicial [Saldo en cuenta] | C3: 0 | D3: =C7 -> 0 | E3: =D7 -> 0 | F3: =E7 -> 0 | G3: =F7 -> 0 | H3: =G7 -> 0 | I3: =H7 -> 0 | J3: =I7 -> 0 | K3: =J7 -> 0 | ... N3: =M7 -> 0
B4: Ingresos Estimados | C4: =C22 -> 0 | D4: =D22 -> 0 | E4: =E22 -> 0 | F4: =F22 -> 0 | G4: =G22 -> 0 | H4: =H22 -> 0 | I4: =I22 -> 0 | J4: =J22 -> 0 | ... N4: =N22 -> 0
B5: Egresos Estimados | C5: =C74 -> 0 | D5: =D74 -> 0 | E5: =E74 -> 0 | F5: =F74 -> 0 | G5: =G74 -> 0 | H5: =H74 -> 0 | I5: =I74 -> 0 | J5: =J74 -> 0 | ... N5: =N74 -> 0
B6: INGRESOS NETOS | C6: =C4-C5 -> 0 | D6: =D4-D5 -> 0 | E6: =E4-E5 -> 0 | F6: =F4-F5 -> 0 | G6: =G4-G5 -> 0 | H6: =H4-H5 -> 0 | I6: =I4-I5 -> 0 | J6: =J4-J5 -> 0 | ... N6: =N4-N5 -> 0
B7: Saldo final proyectado | C7: =C4-C5+C3 -> 0 | D7: =D4-D5+D3 -> 0 | E7: =E4-E5+E3 -> 0 | F7: =F4-F5+F3 -> 0 | G7: =G4-G5+G3 -> 0 | H7: =H4-H5+H3 -> 0 | I7: =I4-I5+I3 -> 0 | J7: =J4-J5+J3 -> 0 | ... N7: =N4-N5+N3 -> 0
B9: INGRESOS
B11: Venta de Alevines | C11: =SUMIF(EneEst2024[CATEGORÍA],$B11,EneEst2024[INGRESO]) -> 0 | D11: =SUMIF(FebEst2024[CATEGORÍA],$B11,FebEst2024[INGRESO]) -> 0 | E11: =SUMIF(MarEst2024[CATEGORÍA],$B11,MarEst2024[INGRESO]) -> 0 | F11: =SUMIF(AbrEst2024[CATEGORÍA],$B11,AbrEst2024[INGRESO]) -> 0 | G11: =SUMIF(MayEst_2024[CATEGORÍA],$B11,MayEst_2024[INGRESO]) -> 0 | H11: =SUMIF(JunEst_2024[CATEGORÍA],$B11,JunEst_2024[INGRESO]) -> 0 | I11: =SUMIF(JulEst_2024[CATEGORÍA],$B11,JulEst_2024[INGRESO]) -> 0 | J11: =SUMIF(AgoEst_2024[CATEGORÍA],$B11,AgoEst_2024[INGRESO]) -> 0 | K11: =SUMIF(SepEst_2024[CATEGORÍA],$B11,SepEst_2024[INGRESO]) -> 0 | L11: =SUMIF(OctEst_2024[CATEGORÍA],$B11,OctEst_2024[INGRESO]) -> 0 | M11: =SUMIF(NovEst_2024[CATEGORÍA],$B11,NovEst_2024[INGRESO]) -> 0 | N11: =SUMIF(DicEst_2024[CATEGORÍA],$B11,DicEst_2024[INGRESO]) -> 0 | O11: =SUM(D11:N11) -> 0
B12: Venta de Alimento | C12: =SUMIF(EneEst2024[CATEGORÍA],$B12,EneEst2024[INGRESO]) -> 0 | D12: =SUMIF(FebEst2024[CATEGORÍA],$B12,FebEst2024[INGRESO]) -> 0 | E12: =SUMIF(MarEst2024[CATEGORÍA],$B12,MarEst2024[INGRESO]) -> 0 | F12: =SUMIF(AbrEst2024[CATEGORÍA],$B12,AbrEst2024[INGRESO]) -> 0 | G12: =SUMIF(MayEst_2024[CATEGORÍA],$B12,MayEst_2024[INGRESO]) -> 0 | H12: =SUMIF(JunEst_2024[CATEGORÍA],$B12,JunEst_2024[INGRESO]) -> 0 | I12: =SUMIF(JulEst_2024[CATEGORÍA],$B12,JulEst_2024[INGRESO]) -> 0 | J12: =SUMIF(AgoEst_2024[CATEGORÍA],$B12,AgoEst_2024[INGRESO]) -> 0 | K12: =SUMIF(SepEst_2024[CATEGORÍA],$B12,SepEst_2024[INGRESO]) -> 0 | L12: =SUMIF(OctEst_2024[CATEGORÍA],$B12,OctEst_2024[INGRESO]) -> 0 | M12: =SUMIF(NovEst_2024[CATEGORÍA],$B12,NovEst_2024[INGRESO]) -> 0 | N12: =SUMIF(DicEst_2024[CATEGORÍA],$B12,DicEst_2024[INGRESO]) -> 0 | O12: =SUM(D12:N12) -> 0
B13: Venta Medicamentos/Vitaminas | C13: =SUMIF(EneEst2024[CATEGORÍA],$B13,EneEst2024[INGRESO]) -> 0 | D13: =SUMIF(FebEst2024[CATEGORÍA],$B13,FebEst2024[INGRESO]) -> 0 | E13: =SUMIF(MarEst2024[CATEGORÍA],$B13,MarEst2024[INGRESO]) -> 0 | F13: =SUMIF(AbrEst2024[CATEGORÍA],$B13,AbrEst2024[INGRESO]) -> 0 | G13: =SUMIF(MayEst_2024[CATEGORÍA],$B13,MayEst_2024[INGRESO]) -> 0 | H13: =SUMIF(JunEst_2024[CATEGORÍA],$B13,JunEst_2024[INGRESO]) -> 0 | I13: =SUMIF(JulEst_2024[CATEGORÍA],$B13,JulEst_2024[INGRESO]) -> 0 | J13: =SUMIF(AgoEst_2024[CATEGORÍA],$B13,AgoEst_2024[INGRESO]) -> 0 | K13: =SUMIF(SepEst_2024[CATEGORÍA],$B13,SepEst_2024[INGRESO]) -> 0 | L13: =SUMIF(OctEst_2024[CATEGORÍA],$B13,OctEst_2024[INGRESO]) -> 0 | M13: =SUMIF(NovEst_2024[CATEGORÍA],$B13,NovEst_2024[INGRESO]) -> 0 | N13: =SUMIF(DicEst_2024[CATEGORÍA],$B13,DicEst_2024[INGRESO]) -> 0 | O13: =SUM(D13:N13) -> 0
B14: Ingresos por intereses | C14: =SUMIF(EneEst2024[CATEGORÍA],$B14,EneEst2024[INGRESO]) -> 0 | D14: =SUMIF(FebEst2024[CATEGORÍA],$B14,FebEst2024[INGRESO]) -> 0 | E14: =SUMIF(MarEst2024[CATEGORÍA],$B14,MarEst2024[INGRESO]) -> 0 | F14: =SUMIF(AbrEst2024[CATEGORÍA],$B14,AbrEst2024[INGRESO]) -> 0 | G14: =SUMIF(MayEst_2024[CATEGORÍA],$B14,MayEst_2024[INGRESO]) -> 0 | H14: =SUMIF(JunEst_2024[CATEGORÍA],$B14,JunEst_2024[INGRESO]) -> 0 | I14: =SUMIF(JulEst_2024[CATEGORÍA],$B14,JulEst_2024[INGRESO]) -> 0 | J14: =SUMIF(AgoEst_2024[CATEGORÍA],$B14,AgoEst_2024[INGRESO]) -> 0 | K14: =SUMIF(SepEst_2024[CATEGORÍA],$B14,SepEst_2024[INGRESO]) -> 0 | L14: =SUMIF(OctEst_2024[CATEGORÍA],$B14,OctEst_2024[INGRESO]) -> 0 | M14: =SUMIF(NovEst_2024[CATEGORÍA],$B14,NovEst_2024[INGRESO]) -> 0 | N14: =SUMIF(DicEst_2024[CATEGORÍA],$B14,DicEst_2024[INGRESO]) -> 0 | O14: =SUM(D14:N14) -> 0
B15: Servicios de Gestion | C15: =SUMIF(EneEst2024[CATEGORÍA],$B15,EneEst2024[INGRESO]) -> 0 | D15: =SUMIF(FebEst2024[CATEGORÍA],$B15,FebEst2024[INGRESO]) -> 0 | E15: =SUMIF(MarEst2024[CATEGORÍA],$B15,MarEst2024[INGRESO]) -> 0 | F15: =SUMIF(AbrEst2024[CATEGORÍA],$B15,AbrEst2024[INGRESO]) -> 0 | G15: =SUMIF(MayEst_2024[CATEGORÍA],$B15,MayEst_2024[INGRESO]) -> 0 | H15: =SUMIF(JunEst_2024[CATEGORÍA],$B15,JunEst_2024[INGRESO]) -> 0 | I15: =SUMIF(JulEst_2024[CATEGORÍA],$B15,JulEst_2024[INGRESO]) -> 0 | J15: =SUMIF(AgoEst_2024[CATEGORÍA],$B15,AgoEst_2024[INGRESO]) -> 0 | K15: =SUMIF(SepEst_2024[CATEGORÍA],$B15,SepEst_2024[INGRESO]) -> 0 | L15: =SUMIF(OctEst_2024[CATEGORÍA],$B15,OctEst_2024[INGRESO]) -> 0 | M15: =SUMIF(NovEst_2024[CATEGORÍA],$B15,NovEst_2024[INGRESO]) -> 0 | N15: =SUMIF(DicEst_2024[CATEGORÍA],$B15,DicEst_2024[INGRESO]) -> 0 | O15: =SUM(D15:N15) -> 0
B16: GPS Over Track Cobro | C16: =SUMIF(EneEst2024[CATEGORÍA],$B16,EneEst2024[INGRESO]) -> 0 | D16: =SUMIF(FebEst2024[CATEGORÍA],$B16,FebEst2024[INGRESO]) -> 0 | E16: =SUMIF(MarEst2024[CATEGORÍA],$B16,MarEst2024[INGRESO]) -> 0 | F16: =SUMIF(AbrEst2024[CATEGORÍA],$B16,AbrEst2024[INGRESO]) -> 0 | G16: =SUMIF(MayEst_2024[CATEGORÍA],$B16,MayEst_2024[INGRESO]) -> 0 | H16: =SUMIF(JunEst_2024[CATEGORÍA],$B16,JunEst_2024[INGRESO]) -> 0 | I16: =SUMIF(JulEst_2024[CATEGORÍA],$B16,JulEst_2024[INGRESO]) -> 0 | J16: =SUMIF(AgoEst_2024[CATEGORÍA],$B16,AgoEst_2024[INGRESO]) -> 0 | K16: =SUMIF(SepEst_2024[CATEGORÍA],$B16,SepEst_2024[INGRESO]) -> 0 | L16: =SUMIF(OctEst_2024[CATEGORÍA],$B16,OctEst_2024[INGRESO]) -> 0 | M16: =SUMIF(NovEst_2024[CATEGORÍA],$B16,NovEst_2024[INGRESO]) -> 0 | N16: =SUMIF(DicEst_2024[CATEGORÍA],$B16,DicEst_2024[INGRESO]) -> 0 | O16: =SUM(D16:N16) -> 0
B17: Reembolsos | C17: =SUMIF(EneEst2024[CATEGORÍA],$B17,EneEst2024[INGRESO]) -> 0 | D17: =SUMIF(FebEst2024[CATEGORÍA],$B17,FebEst2024[INGRESO]) -> 0 | E17: =SUMIF(MarEst2024[CATEGORÍA],$B17,MarEst2024[INGRESO]) -> 0 | F17: =SUMIF(AbrEst2024[CATEGORÍA],$B17,AbrEst2024[INGRESO]) -> 0 | G17: =SUMIF(MayEst_2024[CATEGORÍA],$B17,MayEst_2024[INGRESO]) -> 0 | H17: =SUMIF(JunEst_2024[CATEGORÍA],$B17,JunEst_2024[INGRESO]) -> 0 | I17: =SUMIF(JulEst_2024[CATEGORÍA],$B17,JulEst_2024[INGRESO]) -> 0 | J17: =SUMIF(AgoEst_2024[CATEGORÍA],$B17,AgoEst_2024[INGRESO]) -> 0 | K17: =SUMIF(SepEst_2024[CATEGORÍA],$B17,SepEst_2024[INGRESO]) -> 0 | L17: =SUMIF(OctEst_2024[CATEGORÍA],$B17,OctEst_2024[INGRESO]) -> 0 | M17: =SUMIF(NovEst_2024[CATEGORÍA],$B17,NovEst_2024[INGRESO]) -> 0 | N17: =SUMIF(DicEst_2024[CATEGORÍA],$B17,DicEst_2024[INGRESO]) -> 0 | O17: =SUM(D17:N17) -> 0
B18: Comisiones | C18: =SUMIF(EneEst2024[CATEGORÍA],$B18,EneEst2024[INGRESO]) -> 0 | D18: =SUMIF(FebEst2024[CATEGORÍA],$B18,FebEst2024[INGRESO]) -> 0 | E18: =SUMIF(MarEst2024[CATEGORÍA],$B18,MarEst2024[INGRESO]) -> 0 | F18: =SUMIF(AbrEst2024[CATEGORÍA],$B18,AbrEst2024[INGRESO]) -> 0 | G18: =SUMIF(MayEst_2024[CATEGORÍA],$B18,MayEst_2024[INGRESO]) -> 0 | H18: =SUMIF(JunEst_2024[CATEGORÍA],$B18,JunEst_2024[INGRESO]) -> 0 | I18: =SUMIF(JulEst_2024[CATEGORÍA],$B18,JulEst_2024[INGRESO]) -> 0 | J18: =SUMIF(AgoEst_2024[CATEGORÍA],$B18,AgoEst_2024[INGRESO]) -> 0 | K18: =SUMIF(SepEst_2024[CATEGORÍA],$B18,SepEst_2024[INGRESO]) -> 0 | L18: =SUMIF(OctEst_2024[CATEGORÍA],$B18,OctEst_2024[INGRESO]) -> 0 | M18: =SUMIF(NovEst_2024[CATEGORÍA],$B18,NovEst_2024[INGRESO]) -> 0 | N18: =SUMIF(DicEst_2024[CATEGORÍA],$B18,DicEst_2024[INGRESO]) -> 0 | O18: =SUM(D18:N18) -> 0
B19: Fondeo Externo y Pasivos | C19: =SUMIF(EneEst2024[CATEGORÍA],$B19,EneEst2024[INGRESO]) -> 0 | D19: =SUMIF(FebEst2024[CATEGORÍA],$B19,FebEst2024[INGRESO]) -> 0 | E19: =SUMIF(MarEst2024[CATEGORÍA],$B19,MarEst2024[INGRESO]) -> 0 | F19: =SUMIF(AbrEst2024[CATEGORÍA],$B19,AbrEst2024[INGRESO]) -> 0 | G19: =SUMIF(MayEst_2024[CATEGORÍA],$B19,MayEst_2024[INGRESO]) -> 0 | H19: =SUMIF(JunEst_2024[CATEGORÍA],$B19,JunEst_2024[INGRESO]) -> 0 | I19: =SUMIF(JulEst_2024[CATEGORÍA],$B19,JulEst_2024[INGRESO]) -> 0 | J19: =SUMIF(AgoEst_2024[CATEGORÍA],$B19,AgoEst_2024[INGRESO]) -> 0 | K19: =SUMIF(SepEst_2024[CATEGORÍA],$B19,SepEst_2024[INGRESO]) -> 0 | L19: =SUMIF(OctEst_2024[CATEGORÍA],$B19,OctEst_2024[INGRESO]) -> 0 | M19: =SUMIF(NovEst_2024[CATEGORÍA],$B19,NovEst_2024[INGRESO]) -> 0 | N19: =SUMIF(DicEst_2024[CATEGORÍA],$B19,DicEst_2024[INGRESO]) -> 0 | O19: =SUM(D19:N19) -> 0
B20: Miscelaneo | C20: =SUMIF(EneEst2024[CATEGORÍA],$B20,EneEst2024[INGRESO]) -> 0 | D20: =SUMIF(FebEst2024[CATEGORÍA],$B20,FebEst2024[INGRESO]) -> 0 | E20: =SUMIF(MarEst2024[CATEGORÍA],$B20,MarEst2024[INGRESO]) -> 0 | F20: =SUMIF(AbrEst2024[CATEGORÍA],$B20,AbrEst2024[INGRESO]) -> 0 | G20: =SUMIF(MayEst_2024[CATEGORÍA],$B20,MayEst_2024[INGRESO]) -> 0 | H20: =SUMIF(JunEst_2024[CATEGORÍA],$B20,JunEst_2024[INGRESO]) -> 0 | I20: =SUMIF(JulEst_2024[CATEGORÍA],$B20,JulEst_2024[INGRESO]) -> 0 | J20: =SUMIF(AgoEst_2024[CATEGORÍA],$B20,AgoEst_2024[INGRESO]) -> 0 | K20: =SUMIF(SepEst_2024[CATEGORÍA],$B20,SepEst_2024[INGRESO]) -> 0 | L20: =SUMIF(OctEst_2024[CATEGORÍA],$B20,OctEst_2024[INGRESO]) -> 0 | M20: =SUMIF(NovEst_2024[CATEGORÍA],$B20,NovEst_2024[INGRESO]) -> 0 | N20: =SUMIF(DicEst_2024[CATEGORÍA],$B20,DicEst_2024[INGRESO]) -> 0 | O20: =SUM(D20:N20) -> 0
B22: TOTAL | C22: =SUM(C11:C20) -> 0 | D22: =SUM(D11:D20) -> 0 | E22: =SUM(E11:E20) -> 0 | F22: =SUM(F11:F20) -> 0 | G22: =SUM(G11:G20) -> 0 | H22: =SUM(H11:H20) -> 0 | I22: =SUM(I11:I20) -> 0 | J22: =SUM(J11:J20) -> 0 | ... O22: =SUM(O11:O20) -> 0
B24: CAPITAL
B26: Fondo Liquido | C26: =SUMIF(EneEst2024[CATEGORÍA],$B26,EneEst2024[INGRESO]) -> 0 | D26: =SUMIF(FebEst2024[CATEGORÍA],$B26,FebEst2024[INGRESO]) -> 0 | E26: =SUMIF(MarEst2024[CATEGORÍA],$B26,MarEst2024[INGRESO]) -> 0 | F26: =SUMIF(AbrEst2024[CATEGORÍA],$B26,AbrEst2024[INGRESO]) -> 0 | G26: =SUMIF(MayEst_2024[CATEGORÍA],$B26,MayEst_2024[INGRESO]) -> 0 | H26: =SUMIF(JunEst_2024[CATEGORÍA],$B26,JunEst_2024[INGRESO]) -> 0 | I26: =SUMIF(JulEst_2024[CATEGORÍA],$B26,JulEst_2024[INGRESO]) -> 0 | J26: =SUMIF(AgoEst_2024[CATEGORÍA],$B26,AgoEst_2024[INGRESO]) -> 0 | K26: =SUMIF(SepEst_2024[CATEGORÍA],$B26,SepEst_2024[INGRESO]) -> 0 | L26: =SUMIF(OctEst_2024[CATEGORÍA],$B26,OctEst_2024[INGRESO]) -> 0 | M26: =SUMIF(NovEst_2024[CATEGORÍA],$B26,NovEst_2024[INGRESO]) -> 0 | N26: =SUMIF(DicEst_2024[CATEGORÍA],$B26,DicEst_2024[INGRESO]) -> 0 | O26: =SUM(D26:N26) -> 0
B27: Capital en Inversion | C27: =C37 -> 0 | D27: =C27+D37 -> 0 | E27: =D27+E37 -> 0 | F27: =E27+F37 -> 0 | G27: =F27+G37 -> 0 | H27: =G27+H37 -> 0 | I27: =H27+I37 -> 0 | J27: =I27+J37 -> 0 | K27: =J27+K37 -> 0 | ... N27: =M27+N37 -> 0 | O27: =SUM(D27:N27) -> 0
B28: Cuentas por Cobrar | C28: =SUMIF(EneEst2024[CATEGORÍA],$B28,EneEst2024[INGRESO]) -> 0 | D28: =SUMIF(FebEst2024[CATEGORÍA],$B28,FebEst2024[INGRESO]) -> 0 | E28: =SUMIF(MarEst2024[CATEGORÍA],$B28,MarEst2024[INGRESO]) -> 0 | F28: =SUMIF(AbrEst2024[CATEGORÍA],$B28,AbrEst2024[INGRESO]) -> 0 | G28: =SUMIF(MayEst_2024[CATEGORÍA],$B28,MayEst_2024[INGRESO]) -> 0 | H28: =SUMIF(JunEst_2024[CATEGORÍA],$B28,JunEst_2024[INGRESO]) -> 0 | I28: =SUMIF(JulEst_2024[CATEGORÍA],$B28,JulEst_2024[INGRESO]) -> 0 | J28: =SUMIF(AgoEst_2024[CATEGORÍA],$B28,AgoEst_2024[INGRESO]) -> 0 | K28: =SUMIF(SepEst_2024[CATEGORÍA],$B28,SepEst_2024[INGRESO]) -> 0 | L28: =SUMIF(OctEst_2024[CATEGORÍA],$B28,OctEst_2024[INGRESO]) -> 0 | M28: =SUMIF(NovEst_2024[CATEGORÍA],$B28,NovEst_2024[INGRESO]) -> 0 | N28: =SUMIF(DicEst_2024[CATEGORÍA],$B28,DicEst_2024[INGRESO]) -> 0 | O28: =SUM(D28:N28) -> 0
B29: Otro | C29: =SUMIF(EneEst2024[CATEGORÍA],$B29,EneEst2024[INGRESO]) -> 0 | D29: =SUMIF(FebEst2024[CATEGORÍA],$B29,FebEst2024[INGRESO]) -> 0 | E29: =SUMIF(MarEst2024[CATEGORÍA],$B29,MarEst2024[INGRESO]) -> 0 | F29: =SUMIF(AbrEst2024[CATEGORÍA],$B29,AbrEst2024[INGRESO]) -> 0 | G29: =SUMIF(MayEst_2024[CATEGORÍA],$B29,MayEst_2024[INGRESO]) -> 0 | H29: =SUMIF(JunEst_2024[CATEGORÍA],$B29,JunEst_2024[INGRESO]) -> 0 | I29: =SUMIF(JulEst_2024[CATEGORÍA],$B29,JulEst_2024[INGRESO]) -> 0 | J29: =SUMIF(AgoEst_2024[CATEGORÍA],$B29,AgoEst_2024[INGRESO]) -> 0 | K29: =SUMIF(SepEst_2024[CATEGORÍA],$B29,SepEst_2024[INGRESO]) -> 0 | L29: =SUMIF(OctEst_2024[CATEGORÍA],$B29,OctEst_2024[INGRESO]) -> 0 | M29: =SUMIF(NovEst_2024[CATEGORÍA],$B29,NovEst_2024[INGRESO]) -> 0 | N29: =SUMIF(DicEst_2024[CATEGORÍA],$B29,DicEst_2024[INGRESO]) -> 0 | O29: =SUM(D29:N29) -> 0
B31: TOTAL | C31: =SUM(C26:C29) -> 0 | D31: =SUM(D26:D29) -> 0 | E31: =SUM(E26:E29) -> 0 | F31: =SUM(F26:F29) -> 0 | G31: =SUM(G26:G29) -> 0 | H31: =SUM(H26:H29) -> 0 | I31: =SUM(I26:I29) -> 0 | J31: =SUM(J26:J29) -> 0 | ... O31: =SUM(O26:O29) -> 0
B33: GASTOS OPERATIVOS
B34: RECURSOS HUMANOS
B35: Sueldos y Salarios | C35: =SUMIF(EneEst2024[CATEGORÍA],$B35,EneEst2024[EGRESO]) -> 0 | D35: =SUMIF(FebEst2024[CATEGORÍA],$B35,FebEst2024[EGRESO]) -> 0 | E35: =SUMIF(MarEst2024[CATEGORÍA],$B35,MarEst2024[EGRESO]) -> 0 | F35: =SUMIF(AbrEst2024[CATEGORÍA],$B35,AbrEst2024[EGRESO]) -> 0 | G35: =SUMIF(MayEst_2024[CATEGORÍA],$B35,MayEst_2024[EGRESO]) -> 0 | H35: =SUMIF(JunEst_2024[CATEGORÍA],$B35,JunEst_2024[EGRESO]) -> 0 | I35: =SUMIF(JulEst_2024[CATEGORÍA],$B35,JulEst_2024[EGRESO]) -> 0 | J35: =SUMIF(AgoEst_2024[CATEGORÍA],$B35,AgoEst_2024[EGRESO]) -> 0 | K35: =SUMIF(SepEst_2024[CATEGORÍA],$B35,SepEst_2024[EGRESO]) -> 0 | L35: =SUMIF(OctEst_2024[CATEGORÍA],$B35,OctEst_2024[EGRESO]) -> 0 | M35: =SUMIF(NovEst_2024[CATEGORÍA],$B35,NovEst_2024[EGRESO]) -> 0 | N35: =SUMIF(DicEst_2024[CATEGORÍA],$B35,DicEst_2024[EGRESO]) -> 0 | O35: =SUM(D35:N35) -> 0
B36: Prestamos de Nomina | C36: =SUMIF(EneEst2024[CATEGORÍA],$B36,EneEst2024[EGRESO]) -> 0 | D36: =SUMIF(FebEst2024[CATEGORÍA],$B36,FebEst2024[EGRESO]) -> 0 | E36: =SUMIF(MarEst2024[CATEGORÍA],$B36,MarEst2024[EGRESO]) -> 0 | F36: =SUMIF(AbrEst2024[CATEGORÍA],$B36,AbrEst2024[EGRESO]) -> 0 | G36: =SUMIF(MayEst_2024[CATEGORÍA],$B36,MayEst_2024[EGRESO]) -> 0 | H36: =SUMIF(JunEst_2024[CATEGORÍA],$B36,JunEst_2024[EGRESO]) -> 0 | I36: =SUMIF(JulEst_2024[CATEGORÍA],$B36,JulEst_2024[EGRESO]) -> 0 | J36: =SUMIF(AgoEst_2024[CATEGORÍA],$B36,AgoEst_2024[EGRESO]) -> 0 | K36: =SUMIF(SepEst_2024[CATEGORÍA],$B36,SepEst_2024[EGRESO]) -> 0 | L36: =SUMIF(OctEst_2024[CATEGORÍA],$B36,OctEst_2024[EGRESO]) -> 0 | M36: =SUMIF(NovEst_2024[CATEGORÍA],$B36,NovEst_2024[EGRESO]) -> 0 | N36: =SUMIF(DicEst_2024[CATEGORÍA],$B36,DicEst_2024[EGRESO]) -> 0 | O36: =SUM(D36:N36) -> 0
B37: Caja de Ahorro | C37: =SUMIF(EneEst2024[CATEGORÍA],$B37,EneEst2024[EGRESO]) -> 0 | D37: =SUMIF(FebEst2024[CATEGORÍA],$B37,FebEst2024[EGRESO]) -> 0 | E37: =SUMIF(MarEst2024[CATEGORÍA],$B37,MarEst2024[EGRESO]) -> 0 | F37: =SUMIF(AbrEst2024[CATEGORÍA],$B37,AbrEst2024[EGRESO]) -> 0 | G37: =SUMIF(MayEst_2024[CATEGORÍA],$B37,MayEst_2024[EGRESO]) -> 0 | H37: =SUMIF(JunEst_2024[CATEGORÍA],$B37,JunEst_2024[EGRESO]) -> 0 | I37: =SUMIF(JulEst_2024[CATEGORÍA],$B37,JulEst_2024[EGRESO]) -> 0 | J37: =SUMIF(AgoEst_2024[CATEGORÍA],$B37,AgoEst_2024[EGRESO]) -> 0 | K37: =SUMIF(SepEst_2024[CATEGORÍA],$B37,SepEst_2024[EGRESO]) -> 0 | L37: =SUMIF(OctEst_2024[CATEGORÍA],$B37,OctEst_2024[EGRESO]) -> 0 | M37: =SUMIF(NovEst_2024[CATEGORÍA],$B37,NovEst_2024[EGRESO]) -> 0 | N37: =SUMIF(DicEst_2024[CATEGORÍA],$B37,DicEst_2024[EGRESO]) -> 0 | O37: =SUM(D37:N37) -> 0
B38: Seguro Social | C38: =SUMIF(EneEst2024[CATEGORÍA],$B38,EneEst2024[EGRESO]) -> 0 | D38: =SUMIF(FebEst2024[CATEGORÍA],$B38,FebEst2024[EGRESO]) -> 0 | E38: =SUMIF(MarEst2024[CATEGORÍA],$B38,MarEst2024[EGRESO]) -> 0 | F38: =SUMIF(AbrEst2024[CATEGORÍA],$B38,AbrEst2024[EGRESO]) -> 0 | G38: =SUMIF(MayEst_2024[CATEGORÍA],$B38,MayEst_2024[EGRESO]) -> 0 | H38: =SUMIF(JunEst_2024[CATEGORÍA],$B38,JunEst_2024[EGRESO]) -> 0 | I38: =SUMIF(JulEst_2024[CATEGORÍA],$B38,JulEst_2024[EGRESO]) -> 0 | J38: =SUMIF(AgoEst_2024[CATEGORÍA],$B38,AgoEst_2024[EGRESO]) -> 0 | K38: =SUMIF(SepEst_2024[CATEGORÍA],$B38,SepEst_2024[EGRESO]) -> 0 | L38: =SUMIF(OctEst_2024[CATEGORÍA],$B38,OctEst_2024[EGRESO]) -> 0 | M38: =SUMIF(NovEst_2024[CATEGORÍA],$B38,NovEst_2024[EGRESO]) -> 0 | N38: =SUMIF(DicEst_2024[CATEGORÍA],$B38,DicEst_2024[EGRESO]) -> 0 | O38: =SUM(D38:N38) -> 0
B39: INFONAVIT | C39: =SUMIF(EneEst2024[CATEGORÍA],$B39,EneEst2024[EGRESO]) -> 0 | D39: =SUMIF(FebEst2024[CATEGORÍA],$B39,FebEst2024[EGRESO]) -> 0 | E39: =SUMIF(MarEst2024[CATEGORÍA],$B39,MarEst2024[EGRESO]) -> 0 | F39: =SUMIF(AbrEst2024[CATEGORÍA],$B39,AbrEst2024[EGRESO]) -> 0 | G39: =SUMIF(MayEst_2024[CATEGORÍA],$B39,MayEst_2024[EGRESO]) -> 0 | H39: =SUMIF(JunEst_2024[CATEGORÍA],$B39,JunEst_2024[EGRESO]) -> 0 | I39: =SUMIF(JulEst_2024[CATEGORÍA],$B39,JulEst_2024[EGRESO]) -> 0 | J39: =SUMIF(AgoEst_2024[CATEGORÍA],$B39,AgoEst_2024[EGRESO]) -> 0 | K39: =SUMIF(SepEst_2024[CATEGORÍA],$B39,SepEst_2024[EGRESO]) -> 0 | L39: =SUMIF(OctEst_2024[CATEGORÍA],$B39,OctEst_2024[EGRESO]) -> 0 | M39: =SUMIF(NovEst_2024[CATEGORÍA],$B39,NovEst_2024[EGRESO]) -> 0 | N39: =SUMIF(DicEst_2024[CATEGORÍA],$B39,DicEst_2024[EGRESO]) -> 0 | O39: =SUM(D39:N39) -> 0
B40: 2.5% Sobre Nomina | C40: =SUMIF(EneEst2024[CATEGORÍA],$B40,EneEst2024[EGRESO]) -> 0 | D40: =SUMIF(FebEst2024[CATEGORÍA],$B40,FebEst2024[EGRESO]) -> 0 | E40: =SUMIF(MarEst2024[CATEGORÍA],$B40,MarEst2024[EGRESO]) -> 0 | F40: =SUMIF(AbrEst2024[CATEGORÍA],$B40,AbrEst2024[EGRESO]) -> 0 | G40: =SUMIF(MayEst_2024[CATEGORÍA],$B40,MayEst_2024[EGRESO]) -> 0 | H40: =SUMIF(JunEst_2024[CATEGORÍA],$B40,JunEst_2024[EGRESO]) -> 0 | I40: =SUMIF(JulEst_2024[CATEGORÍA],$B40,JulEst_2024[EGRESO]) -> 0 | J40: =SUMIF(AgoEst_2024[CATEGORÍA],$B40,AgoEst_2024[EGRESO]) -> 0 | K40: =SUMIF(SepEst_2024[CATEGORÍA],$B40,SepEst_2024[EGRESO]) -> 0 | L40: =SUMIF(OctEst_2024[CATEGORÍA],$B40,OctEst_2024[EGRESO]) -> 0 | M40: =SUMIF(NovEst_2024[CATEGORÍA],$B40,NovEst_2024[EGRESO]) -> 0 | N40: =SUMIF(DicEst_2024[CATEGORÍA],$B40,DicEst_2024[EGRESO]) -> 0 | O40: =SUM(D40:N40) -> 0
B41: Capacitacion | C41: =SUMIF(EneEst2024[CATEGORÍA],$B41,EneEst2024[EGRESO]) -> 0 | D41: =SUMIF(FebEst2024[CATEGORÍA],$B41,FebEst2024[EGRESO]) -> 0 | E41: =SUMIF(MarEst2024[CATEGORÍA],$B41,MarEst2024[EGRESO]) -> 0 | F41: =SUMIF(AbrEst2024[CATEGORÍA],$B41,AbrEst2024[EGRESO]) -> 0 | G41: =SUMIF(MayEst_2024[CATEGORÍA],$B41,MayEst_2024[EGRESO]) -> 0 | H41: =SUMIF(JunEst_2024[CATEGORÍA],$B41,JunEst_2024[EGRESO]) -> 0 | I41: =SUMIF(JulEst_2024[CATEGORÍA],$B41,JulEst_2024[EGRESO]) -> 0 | J41: =SUMIF(AgoEst_2024[CATEGORÍA],$B41,AgoEst_2024[EGRESO]) -> 0 | K41: =SUMIF(SepEst_2024[CATEGORÍA],$B41,SepEst_2024[EGRESO]) -> 0 | L41: =SUMIF(OctEst_2024[CATEGORÍA],$B41,OctEst_2024[EGRESO]) -> 0 | M41: =SUMIF(NovEst_2024[CATEGORÍA],$B41,NovEst_2024[EGRESO]) -> 0 | N41: =SUMIF(DicEst_2024[CATEGORÍA],$B41,DicEst_2024[EGRESO]) -> 0 | O41: =SUM(D41:N41) -> 0
B42: Viaticos | C42: =SUMIF(EneEst2024[CATEGORÍA],$B42,EneEst2024[EGRESO]) -> 0 | D42: =SUMIF(FebEst2024[CATEGORÍA],$B42,FebEst2024[EGRESO]) -> 0 | E42: =SUMIF(MarEst2024[CATEGORÍA],$B42,MarEst2024[EGRESO]) -> 0 | F42: =SUMIF(AbrEst2024[CATEGORÍA],$B42,AbrEst2024[EGRESO]) -> 0 | G42: =SUMIF(MayEst_2024[CATEGORÍA],$B42,MayEst_2024[EGRESO]) -> 0 | H42: =SUMIF(JunEst_2024[CATEGORÍA],$B42,JunEst_2024[EGRESO]) -> 0 | I42: =SUMIF(JulEst_2024[CATEGORÍA],$B42,JulEst_2024[EGRESO]) -> 0 | J42: =SUMIF(AgoEst_2024[CATEGORÍA],$B42,AgoEst_2024[EGRESO]) -> 0 | K42: =SUMIF(SepEst_2024[CATEGORÍA],$B42,SepEst_2024[EGRESO]) -> 0 | L42: =SUMIF(OctEst_2024[CATEGORÍA],$B42,OctEst_2024[EGRESO]) -> 0 | M42: =SUMIF(NovEst_2024[CATEGORÍA],$B42,NovEst_2024[EGRESO]) -> 0 | N42: =SUMIF(DicEst_2024[CATEGORÍA],$B42,DicEst_2024[EGRESO]) -> 0 | O42: =SUM(D42:N42) -> 0
B43: Incentivos/Bonos | C43: =SUMIF(EneEst2024[CATEGORÍA],$B43,EneEst2024[EGRESO]) -> 0 | D43: =SUMIF(FebEst2024[CATEGORÍA],$B43,FebEst2024[EGRESO]) -> 0 | E43: =SUMIF(MarEst2024[CATEGORÍA],$B43,MarEst2024[EGRESO]) -> 0 | F43: =SUMIF(AbrEst2024[CATEGORÍA],$B43,AbrEst2024[EGRESO]) -> 0 | G43: =SUMIF(MayEst_2024[CATEGORÍA],$B43,MayEst_2024[EGRESO]) -> 0 | H43: =SUMIF(JunEst_2024[CATEGORÍA],$B43,JunEst_2024[EGRESO]) -> 0 | I43: =SUMIF(JulEst_2024[CATEGORÍA],$B43,JulEst_2024[EGRESO]) -> 0 | J43: =SUMIF(AgoEst_2024[CATEGORÍA],$B43,AgoEst_2024[EGRESO]) -> 0 | K43: =SUMIF(SepEst_2024[CATEGORÍA],$B43,SepEst_2024[EGRESO]) -> 0 | L43: =SUMIF(OctEst_2024[CATEGORÍA],$B43,OctEst_2024[EGRESO]) -> 0 | M43: =SUMIF(NovEst_2024[CATEGORÍA],$B43,NovEst_2024[EGRESO]) -> 0 | N43: =SUMIF(DicEst_2024[CATEGORÍA],$B43,DicEst_2024[EGRESO]) -> 0 | O43: =SUM(D43:N43) -> 0
B44: EPP/Uniformes | C44: =SUMIF(EneEst2024[CATEGORÍA],$B44,EneEst2024[EGRESO]) -> 0 | D44: =SUMIF(FebEst2024[CATEGORÍA],$B44,FebEst2024[EGRESO]) -> 0 | E44: =SUMIF(MarEst2024[CATEGORÍA],$B44,MarEst2024[EGRESO]) -> 0 | F44: =SUMIF(AbrEst2024[CATEGORÍA],$B44,AbrEst2024[EGRESO]) -> 0 | G44: =SUMIF(MayEst_2024[CATEGORÍA],$B44,MayEst_2024[EGRESO]) -> 0 | H44: =SUMIF(JunEst_2024[CATEGORÍA],$B44,JunEst_2024[EGRESO]) -> 0 | I44: =SUMIF(JulEst_2024[CATEGORÍA],$B44,JulEst_2024[EGRESO]) -> 0 | J44: =SUMIF(AgoEst_2024[CATEGORÍA],$B44,AgoEst_2024[EGRESO]) -> 0 | K44: =SUMIF(SepEst_2024[CATEGORÍA],$B44,SepEst_2024[EGRESO]) -> 0 | L44: =SUMIF(OctEst_2024[CATEGORÍA],$B44,OctEst_2024[EGRESO]) -> 0 | M44: =SUMIF(NovEst_2024[CATEGORÍA],$B44,NovEst_2024[EGRESO]) -> 0 | N44: =SUMIF(DicEst_2024[CATEGORÍA],$B44,DicEst_2024[EGRESO]) -> 0 | O44: =SUM(D44:N44) -> 0
B45: Liquidaciones | C45: =SUMIF(EneEst2024[CATEGORÍA],$B45,EneEst2024[EGRESO]) -> 0 | D45: =SUMIF(FebEst2024[CATEGORÍA],$B45,FebEst2024[EGRESO]) -> 0 | E45: =SUMIF(MarEst2024[CATEGORÍA],$B45,MarEst2024[EGRESO]) -> 0 | F45: =SUMIF(AbrEst2024[CATEGORÍA],$B45,AbrEst2024[EGRESO]) -> 0 | G45: =SUMIF(MayEst_2024[CATEGORÍA],$B45,MayEst_2024[EGRESO]) -> 0 | H45: =SUMIF(JunEst_2024[CATEGORÍA],$B45,JunEst_2024[EGRESO]) -> 0 | I45: =SUMIF(JulEst_2024[CATEGORÍA],$B45,JulEst_2024[EGRESO]) -> 0 | J45: =SUMIF(AgoEst_2024[CATEGORÍA],$B45,AgoEst_2024[EGRESO]) -> 0 | K45: =SUMIF(SepEst_2024[CATEGORÍA],$B45,SepEst_2024[EGRESO]) -> 0 | L45: =SUMIF(OctEst_2024[CATEGORÍA],$B45,OctEst_2024[EGRESO]) -> 0 | M45: =SUMIF(NovEst_2024[CATEGORÍA],$B45,NovEst_2024[EGRESO]) -> 0 | N45: =SUMIF(DicEst_2024[CATEGORÍA],$B45,DicEst_2024[EGRESO]) -> 0 | O45: =SUM(D45:N45) -> 0
B46: Otro RRHH | C46: =SUMIF(EneEst2024[CATEGORÍA],$B46,EneEst2024[EGRESO]) -> 0 | D46: =SUMIF(FebEst2024[CATEGORÍA],$B46,FebEst2024[EGRESO]) -> 0 | E46: =SUMIF(MarEst2024[CATEGORÍA],$B46,MarEst2024[EGRESO]) -> 0 | F46: =SUMIF(AbrEst2024[CATEGORÍA],$B46,AbrEst2024[EGRESO]) -> 0 | G46: =SUMIF(MayEst_2024[CATEGORÍA],$B46,MayEst_2024[EGRESO]) -> 0 | H46: =SUMIF(JunEst_2024[CATEGORÍA],$B46,JunEst_2024[EGRESO]) -> 0 | I46: =SUMIF(JulEst_2024[CATEGORÍA],$B46,JulEst_2024[EGRESO]) -> 0 | J46: =SUMIF(AgoEst_2024[CATEGORÍA],$B46,AgoEst_2024[EGRESO]) -> 0 | K46: =SUMIF(SepEst_2024[CATEGORÍA],$B46,SepEst_2024[EGRESO]) -> 0 | L46: =SUMIF(OctEst_2024[CATEGORÍA],$B46,OctEst_2024[EGRESO]) -> 0 | M46: =SUMIF(NovEst_2024[CATEGORÍA],$B46,NovEst_2024[EGRESO]) -> 0 | N46: =SUMIF(DicEst_2024[CATEGORÍA],$B46,DicEst_2024[EGRESO]) -> 0 | O46: =SUM(D46:N46) -> 0
C47: =SUM(C35:C46) -> 0 | D47: =SUM(D35:D46) -> 0 | E47: =SUM(E35:E46) -> 0 | F47: =SUM(F35:F46) -> 0 | G47: =SUM(G35:G46) -> 0 | H47: =SUM(H35:H46) -> 0 | I47: =SUM(I35:I46) -> 0 | J47: =SUM(J35:J46) -> 0 | ... O47: =SUM(O35:O46) -> 0
B48: LOGISTICA
B49: Pagos de automóviles | C49: =SUMIF(EneEst2024[CATEGORÍA],$B49,EneEst2024[EGRESO]) -> 0 | D49: =SUMIF(FebEst2024[CATEGORÍA],$B49,FebEst2024[EGRESO]) -> 0 | E49: =SUMIF(FebEst2024[CATEGORÍA],$B49,FebEst2024[EGRESO]) -> 0 | F49: =SUMIF(AbrEst2024[CATEGORÍA],$B49,AbrEst2024[EGRESO]) -> 0 | G49: =SUMIF(MayEst_2024[CATEGORÍA],$B49,MayEst_2024[EGRESO]) -> 0 | H49: =SUMIF(JunEst_2024[CATEGORÍA],$B49,JunEst_2024[EGRESO]) -> 0 | I49: =SUMIF(JulEst_2024[CATEGORÍA],$B49,JulEst_2024[EGRESO]) -> 0 | J49: =SUMIF(AgoEst_2024[CATEGORÍA],$B49,AgoEst_2024[EGRESO]) -> 0 | K49: =SUMIF(SepEst_2024[CATEGORÍA],$B49,SepEst_2024[EGRESO]) -> 0 | L49: =SUMIF(OctEst_2024[CATEGORÍA],$B49,OctEst_2024[EGRESO]) -> 0 | M49: =SUMIF(NovEst_2024[CATEGORÍA],$B49,NovEst_2024[EGRESO]) -> 0 | N49: =SUMIF(DicEst_2024[CATEGORÍA],$B49,DicEst_2024[EGRESO]) -> 0 | O49: =SUM(D49:N49) -> 0
B50: Seguro de Auto | C50: =SUMIF(EneEst2024[CATEGORÍA],$B50,EneEst2024[EGRESO]) -> 0 | D50: =SUMIF(FebEst2024[CATEGORÍA],$B50,FebEst2024[EGRESO]) -> 0 | E50: =SUMIF(FebEst2024[CATEGORÍA],$B50,FebEst2024[EGRESO]) -> 0 | F50: =SUMIF(AbrEst2024[CATEGORÍA],$B50,AbrEst2024[EGRESO]) -> 0 | G50: =SUMIF(MayEst_2024[CATEGORÍA],$B50,MayEst_2024[EGRESO]) -> 0 | H50: =SUMIF(JunEst_2024[CATEGORÍA],$B50,JunEst_2024[EGRESO]) -> 0 | I50: =SUMIF(JulEst_2024[CATEGORÍA],$B50,JulEst_2024[EGRESO]) -> 0 | J50: =SUMIF(AgoEst_2024[CATEGORÍA],$B50,AgoEst_2024[EGRESO]) -> 0 | K50: =SUMIF(SepEst_2024[CATEGORÍA],$B50,SepEst_2024[EGRESO]) -> 0 | L50: =SUMIF(OctEst_2024[CATEGORÍA],$B50,OctEst_2024[EGRESO]) -> 0 | M50: =SUMIF(NovEst_2024[CATEGORÍA],$B50,NovEst_2024[EGRESO]) -> 0 | N50: =SUMIF(DicEst_2024[CATEGORÍA],$B50,DicEst_2024[EGRESO]) -> 0 | O50: =SUM(D50:N50) -> 0
B51: Deducibles | C51: =SUMIF(EneEst2024[CATEGORÍA],$B51,EneEst2024[EGRESO]) -> 0 | D51: =SUMIF(FebEst2024[CATEGORÍA],$B51,FebEst2024[EGRESO]) -> 0 | E51: =SUMIF(FebEst2024[CATEGORÍA],$B51,FebEst2024[EGRESO]) -> 0 | F51: =SUMIF(AbrEst2024[CATEGORÍA],$B51,AbrEst2024[EGRESO]) -> 0 | G51: =SUMIF(MayEst_2024[CATEGORÍA],$B51,MayEst_2024[EGRESO]) -> 0 | H51: =SUMIF(JunEst_2024[CATEGORÍA],$B51,JunEst_2024[EGRESO]) -> 0 | I51: =SUMIF(JulEst_2024[CATEGORÍA],$B51,JulEst_2024[EGRESO]) -> 0 | J51: =SUMIF(AgoEst_2024[CATEGORÍA],$B51,AgoEst_2024[EGRESO]) -> 0 | K51: =SUMIF(SepEst_2024[CATEGORÍA],$B51,SepEst_2024[EGRESO]) -> 0 | L51: =SUMIF(OctEst_2024[CATEGORÍA],$B51,OctEst_2024[EGRESO]) -> 0 | M51: =SUMIF(NovEst_2024[CATEGORÍA],$B51,NovEst_2024[EGRESO]) -> 0 | N51: =SUMIF(DicEst_2024[CATEGORÍA],$B51,DicEst_2024[EGRESO]) -> 0 | O51: =SUM(D51:N51) -> 0
B52: Impuestos y Refrendos | C52: =SUMIF(EneEst2024[CATEGORÍA],$B52,EneEst2024[EGRESO]) -> 0 | D52: =SUMIF(FebEst2024[CATEGORÍA],$B52,FebEst2024[EGRESO]) -> 0 | E52: =SUMIF(FebEst2024[CATEGORÍA],$B52,FebEst2024[EGRESO]) -> 0 | F52: =SUMIF(AbrEst2024[CATEGORÍA],$B52,AbrEst2024[EGRESO]) -> 0 | G52: =SUMIF(MayEst_2024[CATEGORÍA],$B52,MayEst_2024[EGRESO]) -> 0 | H52: =SUMIF(JunEst_2024[CATEGORÍA],$B52,JunEst_2024[EGRESO]) -> 0 | I52: =SUMIF(JulEst_2024[CATEGORÍA],$B52,JulEst_2024[EGRESO]) -> 0 | J52: =SUMIF(AgoEst_2024[CATEGORÍA],$B52,AgoEst_2024[EGRESO]) -> 0 | K52: =SUMIF(SepEst_2024[CATEGORÍA],$B52,SepEst_2024[EGRESO]) -> 0 | L52: =SUMIF(OctEst_2024[CATEGORÍA],$B52,OctEst_2024[EGRESO]) -> 0 | M52: =SUMIF(NovEst_2024[CATEGORÍA],$B52,NovEst_2024[EGRESO]) -> 0 | N52: =SUMIF(DicEst_2024[CATEGORÍA],$B52,DicEst_2024[EGRESO]) -> 0 | O52: =SUM(D52:N52) -> 0
B53: Combustible | C53: =SUMIF(EneEst2024[CATEGORÍA],$B53,EneEst2024[EGRESO]) -> 0 | D53: =SUMIF(FebEst2024[CATEGORÍA],$B53,FebEst2024[EGRESO]) -> 0 | E53: =SUMIF(FebEst2024[CATEGORÍA],$B53,FebEst2024[EGRESO]) -> 0 | F53: =SUMIF(AbrEst2024[CATEGORÍA],$B53,AbrEst2024[EGRESO]) -> 0 | G53: =SUMIF(MayEst_2024[CATEGORÍA],$B53,MayEst_2024[EGRESO]) -> 0 | H53: =SUMIF(JunEst_2024[CATEGORÍA],$B53,JunEst_2024[EGRESO]) -> 0 | I53: =SUMIF(JulEst_2024[CATEGORÍA],$B53,JulEst_2024[EGRESO]) -> 0 | J53: =SUMIF(AgoEst_2024[CATEGORÍA],$B53,AgoEst_2024[EGRESO]) -> 0 | K53: =SUMIF(SepEst_2024[CATEGORÍA],$B53,SepEst_2024[EGRESO]) -> 0 | L53: =SUMIF(OctEst_2024[CATEGORÍA],$B53,OctEst_2024[EGRESO]) -> 0 | M53: =SUMIF(NovEst_2024[CATEGORÍA],$B53,NovEst_2024[EGRESO]) -> 0 | N53: =SUMIF(DicEst_2024[CATEGORÍA],$B53,DicEst_2024[EGRESO]) -> 0 | O53: =SUM(D53:N53) -> 0
B54: Transporte Público | C54: =SUMIF(EneEst2024[CATEGORÍA],$B54,EneEst2024[EGRESO]) -> 0 | D54: =SUMIF(FebEst2024[CATEGORÍA],$B54,FebEst2024[EGRESO]) -> 0 | E54: =SUMIF(FebEst2024[CATEGORÍA],$B54,FebEst2024[EGRESO]) -> 0 | F54: =SUMIF(AbrEst2024[CATEGORÍA],$B54,AbrEst2024[EGRESO]) -> 0 | G54: =SUMIF(MayEst_2024[CATEGORÍA],$B54,MayEst_2024[EGRESO]) -> 0 | H54: =SUMIF(JunEst_2024[CATEGORÍA],$B54,JunEst_2024[EGRESO]) -> 0 | I54: =SUMIF(JulEst_2024[CATEGORÍA],$B54,JulEst_2024[EGRESO]) -> 0 | J54: =SUMIF(AgoEst_2024[CATEGORÍA],$B54,AgoEst_2024[EGRESO]) -> 0 | K54: =SUMIF(SepEst_2024[CATEGORÍA],$B54,SepEst_2024[EGRESO]) -> 0 | L54: =SUMIF(OctEst_2024[CATEGORÍA],$B54,OctEst_2024[EGRESO]) -> 0 | M54: =SUMIF(NovEst_2024[CATEGORÍA],$B54,NovEst_2024[EGRESO]) -> 0 | N54: =SUMIF(DicEst_2024[CATEGORÍA],$B54,DicEst_2024[EGRESO]) -> 0 | O54: =SUM(D54:N54) -> 0
B55: Reparaciones y Mantenimientos | C55: =SUMIF(EneEst2024[CATEGORÍA],$B55,EneEst2024[EGRESO]) -> 0 | D55: =SUMIF(FebEst2024[CATEGORÍA],$B55,FebEst2024[EGRESO]) -> 0 | E55: =SUMIF(FebEst2024[CATEGORÍA],$B55,FebEst2024[EGRESO]) -> 0 | F55: =SUMIF(AbrEst2024[CATEGORÍA],$B55,AbrEst2024[EGRESO]) -> 0 | G55: =SUMIF(MayEst_2024[CATEGORÍA],$B55,MayEst_2024[EGRESO]) -> 0 | H55: =SUMIF(JunEst_2024[CATEGORÍA],$B55,JunEst_2024[EGRESO]) -> 0 | I55: =SUMIF(JulEst_2024[CATEGORÍA],$B55,JulEst_2024[EGRESO]) -> 0 | J55: =SUMIF(AgoEst_2024[CATEGORÍA],$B55,AgoEst_2024[EGRESO]) -> 0 | K55: =SUMIF(SepEst_2024[CATEGORÍA],$B55,SepEst_2024[EGRESO]) -> 0 | L55: =SUMIF(OctEst_2024[CATEGORÍA],$B55,OctEst_2024[EGRESO]) -> 0 | M55: =SUMIF(NovEst_2024[CATEGORÍA],$B55,NovEst_2024[EGRESO]) -> 0 | N55: =SUMIF(DicEst_2024[CATEGORÍA],$B55,DicEst_2024[EGRESO]) -> 0 | O55: =SUM(D55:N55) -> 0
B56: Registros y Licencias | C56: =SUMIF(EneEst2024[CATEGORÍA],$B56,EneEst2024[EGRESO]) -> 0 | D56: =SUMIF(FebEst2024[CATEGORÍA],$B56,FebEst2024[EGRESO]) -> 0 | E56: =SUMIF(FebEst2024[CATEGORÍA],$B56,FebEst2024[EGRESO]) -> 0 | F56: =SUMIF(AbrEst2024[CATEGORÍA],$B56,AbrEst2024[EGRESO]) -> 0 | G56: =SUMIF(MayEst_2024[CATEGORÍA],$B56,MayEst_2024[EGRESO]) -> 0 | H56: =SUMIF(JunEst_2024[CATEGORÍA],$B56,JunEst_2024[EGRESO]) -> 0 | I56: =SUMIF(JulEst_2024[CATEGORÍA],$B56,JulEst_2024[EGRESO]) -> 0 | J56: =SUMIF(AgoEst_2024[CATEGORÍA],$B56,AgoEst_2024[EGRESO]) -> 0 | K56: =SUMIF(SepEst_2024[CATEGORÍA],$B56,SepEst_2024[EGRESO]) -> 0 | L56: =SUMIF(OctEst_2024[CATEGORÍA],$B56,OctEst_2024[EGRESO]) -> 0 | M56: =SUMIF(NovEst_2024[CATEGORÍA],$B56,NovEst_2024[EGRESO]) -> 0 | N56: =SUMIF(DicEst_2024[CATEGORÍA],$B56,DicEst_2024[EGRESO]) -> 0 | O56: =SUM(D56:N56) -> 0
B57: Otro | C57: =SUMIF(EneEst2024[CATEGORÍA],$B57,EneEst2024[EGRESO]) -> 0 | D57: =SUMIF(FebEst2024[CATEGORÍA],$B57,FebEst2024[EGRESO]) -> 0 | E57: =SUMIF(FebEst2024[CATEGORÍA],$B57,FebEst2024[EGRESO]) -> 0 | F57: =SUMIF(AbrEst2024[CATEGORÍA],$B57,AbrEst2024[EGRESO]) -> 0 | G57: =SUMIF(MayEst_2024[CATEGORÍA],$B57,MayEst_2024[EGRESO]) -> 0 | H57: =SUMIF(JunEst_2024[CATEGORÍA],$B57,JunEst_2024[EGRESO]) -> 0 | I57: =SUMIF(JulEst_2024[CATEGORÍA],$B57,JulEst_2024[EGRESO]) -> 0 | J57: =SUMIF(AgoEst_2024[CATEGORÍA],$B57,AgoEst_2024[EGRESO]) -> 0 | K57: =SUMIF(SepEst_2024[CATEGORÍA],$B57,SepEst_2024[EGRESO]) -> 0 | L57: =SUMIF(OctEst_2024[CATEGORÍA],$B57,OctEst_2024[EGRESO]) -> 0 | M57: =SUMIF(NovEst_2024[CATEGORÍA],$B57,NovEst_2024[EGRESO]) -> 0 | N57: =SUMIF(DicEst_2024[CATEGORÍA],$B57,DicEst_2024[EGRESO]) -> 0 | O57: =SUM(D57:N57) -> 0
C58: =SUM(C49:C57) -> 0 | D58: =SUM(D49:D57) -> 0 | E58: =SUM(E49:E57) -> 0 | F58: =SUM(F49:F57) -> 0 | G58: =SUM(G49:G57) -> 0 | H58: =SUM(H49:H57) -> 0 | I58: =SUM(I49:I57) -> 0 | J58: =SUM(J49:J57) -> 0 | ... O58: =SUM(O49:O57) -> 0
B59: SERVICIOS
B60: Internet y Telefonico | C60: =SUMIF(EneEst2024[CATEGORÍA],$B60,EneEst2024[EGRESO]) -> 0 | D60: =SUMIF(FebEst2024[CATEGORÍA],$B60,FebEst2024[EGRESO]) -> 0 | E60: =SUMIF(FebEst2024[CATEGORÍA],$B60,FebEst2024[EGRESO]) -> 0 | F60: =SUMIF(AbrEst2024[CATEGORÍA],$B60,AbrEst2024[EGRESO]) -> 0 | G60: =SUMIF(MayEst_2024[CATEGORÍA],$B60,MayEst_2024[EGRESO]) -> 0 | H60: =SUMIF(JunEst_2024[CATEGORÍA],$B60,JunEst_2024[EGRESO]) -> 0 | I60: =SUMIF(JulEst_2024[CATEGORÍA],$B60,JulEst_2024[EGRESO]) -> 0 | J60: =SUMIF(AgoEst_2024[CATEGORÍA],$B60,AgoEst_2024[EGRESO]) -> 0 | K60: =SUMIF(SepEst_2024[CATEGORÍA],$B60,SepEst_2024[EGRESO]) -> 0 | L60: =SUMIF(OctEst_2024[CATEGORÍA],$B60,OctEst_2024[EGRESO]) -> 0 | M60: =SUMIF(NovEst_2024[CATEGORÍA],$B60,NovEst_2024[EGRESO]) -> 0 | N60: =SUMIF(DicEst_2024[CATEGORÍA],$B60,DicEst_2024[EGRESO]) -> 0 | O60: =SUM(D60:N60) -> 0
B61: Electricidad CFE | C61: =SUMIF(EneEst2024[CATEGORÍA],$B61,EneEst2024[EGRESO]) -> 0 | D61: =SUMIF(FebEst2024[CATEGORÍA],$B61,FebEst2024[EGRESO]) -> 0 | E61: =SUMIF(FebEst2024[CATEGORÍA],$B61,FebEst2024[EGRESO]) -> 0 | F61: =SUMIF(AbrEst2024[CATEGORÍA],$B61,AbrEst2024[EGRESO]) -> 0 | G61: =SUMIF(MayEst_2024[CATEGORÍA],$B61,MayEst_2024[EGRESO]) -> 0 | H61: =SUMIF(JunEst_2024[CATEGORÍA],$B61,JunEst_2024[EGRESO]) -> 0 | I61: =SUMIF(JulEst_2024[CATEGORÍA],$B61,JulEst_2024[EGRESO]) -> 0 | J61: =SUMIF(AgoEst_2024[CATEGORÍA],$B61,AgoEst_2024[EGRESO]) -> 0 | K61: =SUMIF(SepEst_2024[CATEGORÍA],$B61,SepEst_2024[EGRESO]) -> 0 | L61: =SUMIF(OctEst_2024[CATEGORÍA],$B61,OctEst_2024[EGRESO]) -> 0 | M61: =SUMIF(NovEst_2024[CATEGORÍA],$B61,NovEst_2024[EGRESO]) -> 0 | N61: =SUMIF(DicEst_2024[CATEGORÍA],$B61,DicEst_2024[EGRESO]) -> 0 | O61: =SUM(D61:N61) -> 0
B62: Limpieza | C62: =SUMIF(EneEst2024[CATEGORÍA],$B62,EneEst2024[EGRESO]) -> 0 | D62: =SUMIF(FebEst2024[CATEGORÍA],$B62,FebEst2024[EGRESO]) -> 0 | E62: =SUMIF(FebEst2024[CATEGORÍA],$B62,FebEst2024[EGRESO]) -> 0 | F62: =SUMIF(AbrEst2024[CATEGORÍA],$B62,AbrEst2024[EGRESO]) -> 0 | G62: =SUMIF(MayEst_2024[CATEGORÍA],$B62,MayEst_2024[EGRESO]) -> 0 | H62: =SUMIF(JunEst_2024[CATEGORÍA],$B62,JunEst_2024[EGRESO]) -> 0 | I62: =SUMIF(JulEst_2024[CATEGORÍA],$B62,JulEst_2024[EGRESO]) -> 0 | J62: =SUMIF(AgoEst_2024[CATEGORÍA],$B62,AgoEst_2024[EGRESO]) -> 0 | K62: =SUMIF(SepEst_2024[CATEGORÍA],$B62,SepEst_2024[EGRESO]) -> 0 | L62: =SUMIF(OctEst_2024[CATEGORÍA],$B62,OctEst_2024[EGRESO]) -> 0 | M62: =SUMIF(NovEst_2024[CATEGORÍA],$B62,NovEst_2024[EGRESO]) -> 0 | N62: =SUMIF(DicEst_2024[CATEGORÍA],$B62,DicEst_2024[EGRESO]) -> 0 | O62: =SUM(D62:N62) -> 0
B63: Comisiones Bancarias | C63: =SUMIF(EneEst2024[CATEGORÍA],$B63,EneEst2024[EGRESO]) -> 0 | D63: =SUMIF(FebEst2024[CATEGORÍA],$B63,FebEst2024[EGRESO]) -> 0 | E63: =SUMIF(FebEst2024[CATEGORÍA],$B63,FebEst2024[EGRESO]) -> 0 | F63: =SUMIF(AbrEst2024[CATEGORÍA],$B63,AbrEst2024[EGRESO]) -> 0 | G63: =SUMIF(MayEst_2024[CATEGORÍA],$B63,MayEst_2024[EGRESO]) -> 0 | H63: =SUMIF(JunEst_2024[CATEGORÍA],$B63,JunEst_2024[EGRESO]) -> 0 | I63: =SUMIF(JulEst_2024[CATEGORÍA],$B63,JulEst_2024[EGRESO]) -> 0 | J63: =SUMIF(AgoEst_2024[CATEGORÍA],$B63,AgoEst_2024[EGRESO]) -> 0 | K63: =SUMIF(SepEst_2024[CATEGORÍA],$B63,SepEst_2024[EGRESO]) -> 0 | L63: =SUMIF(OctEst_2024[CATEGORÍA],$B63,OctEst_2024[EGRESO]) -> 0 | M63: =SUMIF(NovEst_2024[CATEGORÍA],$B63,NovEst_2024[EGRESO]) -> 0 | N63: =SUMIF(DicEst_2024[CATEGORÍA],$B63,DicEst_2024[EGRESO]) -> 0 | O63: =SUM(D63:N63) -> 0
B64: Otros Servicios | C64: =SUMIF(EneEst2024[CATEGORÍA],$B64,EneEst2024[EGRESO]) -> 0 | D64: =SUMIF(FebEst2024[CATEGORÍA],$B64,FebEst2024[EGRESO]) -> 0 | E64: =SUMIF(FebEst2024[CATEGORÍA],$B64,FebEst2024[EGRESO]) -> 0 | F64: =SUMIF(AbrEst2024[CATEGORÍA],$B64,AbrEst2024[EGRESO]) -> 0 | G64: =SUMIF(MayEst_2024[CATEGORÍA],$B64,MayEst_2024[EGRESO]) -> 0 | H64: =SUMIF(JunEst_2024[CATEGORÍA],$B64,JunEst_2024[EGRESO]) -> 0 | I64: =SUMIF(JulEst_2024[CATEGORÍA],$B64,JulEst_2024[EGRESO]) -> 0 | J64: =SUMIF(AgoEst_2024[CATEGORÍA],$B64,AgoEst_2024[EGRESO]) -> 0 | K64: =SUMIF(SepEst_2024[CATEGORÍA],$B64,SepEst_2024[EGRESO]) -> 0 | L64: =SUMIF(OctEst_2024[CATEGORÍA],$B64,OctEst_2024[EGRESO]) -> 0 | M64: =SUMIF(NovEst_2024[CATEGORÍA],$B64,NovEst_2024[EGRESO]) -> 0 | N64: =SUMIF(DicEst_2024[CATEGORÍA],$B64,DicEst_2024[EGRESO]) -> 0 | O64: =SUM(D64:N64) -> 0
C65: =SUM(C60:C64) -> 0 | D65: =SUM(D60:D64) -> 0 | E65: =SUM(E60:E64) -> 0 | F65: =SUM(F60:F64) -> 0 | G65: =SUM(G60:G64) -> 0 | H65: =SUM(H60:H64) -> 0 | I65: =SUM(I60:I64) -> 0 | J65: =SUM(J60:J64) -> 0 | ... O65: =SUM(O60:O64) -> 0
B66: RECURSOS MATERIALES
B67: Material de Construccion | C67: =SUMIF(EneEst2024[CATEGORÍA],$B67,EneEst2024[EGRESO]) -> 0 | D67: =SUMIF(FebEst2024[CATEGORÍA],$B67,FebEst2024[EGRESO]) -> 0 | E67: =SUMIF(FebEst2024[CATEGORÍA],$B67,FebEst2024[EGRESO]) -> 0 | F67: =SUMIF(AbrEst2024[CATEGORÍA],$B67,AbrEst2024[EGRESO]) -> 0 | G67: =SUMIF(MayEst_2024[CATEGORÍA],$B67,MayEst_2024[EGRESO]) -> 0 | H67: =SUMIF(JunEst_2024[CATEGORÍA],$B67,JunEst_2024[EGRESO]) -> 0 | I67: =SUMIF(JulEst_2024[CATEGORÍA],$B67,JulEst_2024[EGRESO]) -> 0 | J67: =SUMIF(AgoEst_2024[CATEGORÍA],$B67,AgoEst_2024[EGRESO]) -> 0 | K67: =SUMIF(SepEst_2024[CATEGORÍA],$B67,SepEst_2024[EGRESO]) -> 0 | L67: =SUMIF(OctEst_2024[CATEGORÍA],$B67,OctEst_2024[EGRESO]) -> 0 | M67: =SUMIF(NovEst_2024[CATEGORÍA],$B67,NovEst_2024[EGRESO]) -> 0 | N67: =SUMIF(DicEst_2024[CATEGORÍA],$B67,DicEst_2024[EGRESO]) -> 0 | O67: =SUM(D67:N67) -> 0
B68: Pintura Barniz | C68: =SUMIF(EneEst2024[CATEGORÍA],$B68,EneEst2024[EGRESO]) -> 0 | D68: =SUMIF(FebEst2024[CATEGORÍA],$B68,FebEst2024[EGRESO]) -> 0 | E68: =SUMIF(FebEst2024[CATEGORÍA],$B68,FebEst2024[EGRESO]) -> 0 | F68: =SUMIF(AbrEst2024[CATEGORÍA],$B68,AbrEst2024[EGRESO]) -> 0 | G68: =SUMIF(MayEst_2024[CATEGORÍA],$B68,MayEst_2024[EGRESO]) -> 0 | H68: =SUMIF(JunEst_2024[CATEGORÍA],$B68,JunEst_2024[EGRESO]) -> 0 | I68: =SUMIF(JulEst_2024[CATEGORÍA],$B68,JulEst_2024[EGRESO]) -> 0 | J68: =SUMIF(AgoEst_2024[CATEGORÍA],$B68,AgoEst_2024[EGRESO]) -> 0 | K68: =SUMIF(SepEst_2024[CATEGORÍA],$B68,SepEst_2024[EGRESO]) -> 0 | L68: =SUMIF(OctEst_2024[CATEGORÍA],$B68,OctEst_2024[EGRESO]) -> 0 | M68: =SUMIF(NovEst_2024[CATEGORÍA],$B68,NovEst_2024[EGRESO]) -> 0 | N68: =SUMIF(DicEst_2024[CATEGORÍA],$B68,DicEst_2024[EGRESO]) -> 0 | O68: =SUM(D68:N68) -> 0
B69: Servicios Profesionales | C69: =SUMIF(EneEst2024[CATEGORÍA],$B69,EneEst2024[EGRESO]) -> 0 | D69: =SUMIF(FebEst2024[CATEGORÍA],$B69,FebEst2024[EGRESO]) -> 0 | E69: =SUMIF(FebEst2024[CATEGORÍA],$B69,FebEst2024[EGRESO]) -> 0 | F69: =SUMIF(AbrEst2024[CATEGORÍA],$B69,AbrEst2024[EGRESO]) -> 0 | G69: =SUMIF(MayEst_2024[CATEGORÍA],$B69,MayEst_2024[EGRESO]) -> 0 | H69: =SUMIF(JunEst_2024[CATEGORÍA],$B69,JunEst_2024[EGRESO]) -> 0 | I69: =SUMIF(JulEst_2024[CATEGORÍA],$B69,JulEst_2024[EGRESO]) -> 0 | J69: =SUMIF(AgoEst_2024[CATEGORÍA],$B69,AgoEst_2024[EGRESO]) -> 0 | K69: =SUMIF(SepEst_2024[CATEGORÍA],$B69,SepEst_2024[EGRESO]) -> 0 | L69: =SUMIF(OctEst_2024[CATEGORÍA],$B69,OctEst_2024[EGRESO]) -> 0 | M69: =SUMIF(NovEst_2024[CATEGORÍA],$B69,NovEst_2024[EGRESO]) -> 0 | N69: =SUMIF(DicEst_2024[CATEGORÍA],$B69,DicEst_2024[EGRESO]) -> 0 | O69: =SUM(D69:N69) -> 0
B70: GPS Over Track Pago | C70: =SUMIF(EneEst2024[CATEGORÍA],$B70,EneEst2024[EGRESO]) -> 0 | D70: =SUMIF(FebEst2024[CATEGORÍA],$B70,FebEst2024[EGRESO]) -> 0 | E70: =SUMIF(FebEst2024[CATEGORÍA],$B70,FebEst2024[EGRESO]) -> 0 | F70: =SUMIF(AbrEst2024[CATEGORÍA],$B70,AbrEst2024[EGRESO]) -> 0 | G70: =SUMIF(MayEst_2024[CATEGORÍA],$B70,MayEst_2024[EGRESO]) -> 0 | H70: =SUMIF(JunEst_2024[CATEGORÍA],$B70,JunEst_2024[EGRESO]) -> 0 | I70: =SUMIF(JulEst_2024[CATEGORÍA],$B70,JulEst_2024[EGRESO]) -> 0 | J70: =SUMIF(AgoEst_2024[CATEGORÍA],$B70,AgoEst_2024[EGRESO]) -> 0 | K70: =SUMIF(SepEst_2024[CATEGORÍA],$B70,SepEst_2024[EGRESO]) -> 0 | L70: =SUMIF(OctEst_2024[CATEGORÍA],$B70,OctEst_2024[EGRESO]) -> 0 | M70: =SUMIF(NovEst_2024[CATEGORÍA],$B70,NovEst_2024[EGRESO]) -> 0 | N70: =SUMIF(DicEst_2024[CATEGORÍA],$B70,DicEst_2024[EGRESO]) -> 0 | O70: =SUM(D70:N70) -> 0
B71: Mano de Obra | C71: =SUMIF(EneEst2024[CATEGORÍA],$B71,EneEst2024[EGRESO]) -> 0 | D71: =SUMIF(FebEst2024[CATEGORÍA],$B71,FebEst2024[EGRESO]) -> 0 | E71: =SUMIF(FebEst2024[CATEGORÍA],$B71,FebEst2024[EGRESO]) -> 0 | F71: =SUMIF(AbrEst2024[CATEGORÍA],$B71,AbrEst2024[EGRESO]) -> 0 | G71: =SUMIF(MayEst_2024[CATEGORÍA],$B71,MayEst_2024[EGRESO]) -> 0 | H71: =SUMIF(JunEst_2024[CATEGORÍA],$B71,JunEst_2024[EGRESO]) -> 0 | I71: =SUMIF(JulEst_2024[CATEGORÍA],$B71,JulEst_2024[EGRESO]) -> 0 | J71: =SUMIF(AgoEst_2024[CATEGORÍA],$B71,AgoEst_2024[EGRESO]) -> 0 | K71: =SUMIF(SepEst_2024[CATEGORÍA],$B71,SepEst_2024[EGRESO]) -> 0 | L71: =SUMIF(OctEst_2024[CATEGORÍA],$B71,OctEst_2024[EGRESO]) -> 0 | M71: =SUMIF(NovEst_2024[CATEGORÍA],$B71,NovEst_2024[EGRESO]) -> 0 | N71: =SUMIF(DicEst_2024[CATEGORÍA],$B71,DicEst_2024[EGRESO]) -> 0 | O71: =SUM(D71:N71) -> 0
C72: =SUM(C67:C71) -> 0 | D72: =SUM(D67:D71) -> 0 | E72: =SUM(E67:E71) -> 0 | F72: =SUM(F67:F71) -> 0 | G72: =SUM(G67:G71) -> 0 | H72: =SUM(H67:H71) -> 0 | I72: =SUM(I67:I71) -> 0 | J72: =SUM(J67:J71) -> 0 | ... O72: =SUM(O67:O71) -> 0
B74: TOTAL | C74: =C72+C65+C58+C47 -> 0 | D74: =D72+D65+D58+D47 -> 0 | E74: =E72+E65+E58+E47 -> 0 | F74: =F72+F65+F58+F47 -> 0 | G74: =G72+G65+G58+G47 -> 0 | H74: =H72+H65+H58+H47 -> 0 | I74: =I72+I65+I58+I47 -> 0 | J74: =J72+J65+J58+J47 -> 0 | ... O74: =O72+O65+O58+O47 -> 0
B76: ENERO 2025
B77: CUENTA | C77: FECHA | D77: INGRESO | E77: EGRESO | F77: BENEFICIARIO/PROVEEDOR | G77: NO. FACTURA | H77: NO. PROYECTO | I77: DESCRIPCION | J77: CATEGORÍA | K77: SUB CATEGORIA | L77: EQUILIBRAR
L78: =IF(ISERROR(OFFSET(L78,-1,0,1,1)+D78-E78),D78-E78,OFFSET(L78,-1,0,1,1)+D78-E78) -> 0
L79: =IF(ISERROR(OFFSET(L79,-1,0,1,1)+D79-E79),D79-E79,OFFSET(L79,-1,0,1,1)+D79-E79) -> 0
L80: =IF(ISERROR(OFFSET(L80,-1,0,1,1)+D80-E80),D80-E80,OFFSET(L80,-1,0,1,1)+D80-E80) -> 0
L81: =IF(ISERROR(OFFSET(L81,-1,0,1,1)+D81-E81),D81-E81,OFFSET(L81,-1,0,1,1)+D81-E81) -> 0
L82: =IF(ISERROR(OFFSET(L82,-1,0,1,1)+D82-E82),D82-E82,OFFSET(L82,-1,0,1,1)+D82-E82) -> 0
L83: =IF(ISERROR(OFFSET(L83,-1,0,1,1)+D83-E83),D83-E83,OFFSET(L83,-1,0,1,1)+D83-E83) -> 0
L84: =IF(ISERROR(OFFSET(L84,-1,0,1,1)+D84-E84),D84-E84,OFFSET(L84,-1,0,1,1)+D84-E84) -> 0
L85: =IF(ISERROR(OFFSET(L85,-1,0,1,1)+D85-E85),D85-E85,OFFSET(L85,-1,0,1,1)+D85-E85) -> 0
L86: =IF(ISERROR(OFFSET(L86,-1,0,1,1)+D86-E86),D86-E86,OFFSET(L86,-1,0,1,1)+D86-E86) -> 0
L87: =IF(ISERROR(OFFSET(L87,-1,0,1,1)+D87-E87),D87-E87,OFFSET(L87,-1,0,1,1)+D87-E87) -> 0
L88: =IF(ISERROR(OFFSET(L88,-1,0,1,1)+D88-E88),D88-E88,OFFSET(L88,-1,0,1,1)+D88-E88) -> 0
L89: =IF(ISERROR(OFFSET(L89,-1,0,1,1)+D89-E89),D89-E89,OFFSET(L89,-1,0,1,1)+D89-E89) -> 0
... L111: =IF(ISERROR(OFFSET(L111,-1,0,1,1)+D111-E111),D111-E111,OFFSET(L111,-1,0,1,1)+D111-E111) -> 0
D112: =SUBTOTAL(109,EneEst2024[INGRESO]) -> 0 | E112: =SUBTOTAL(109,EneEst2024[EGRESO]) -> 0
B114: FEBRERO 2025
B115: CUENTA | C115: FECHA | D115: INGRESO | E115: EGRESO | F115: BENEFICIARIO/PROVEEDOR | G115: NO. FACTURA | H115: NO. PROYECTO | I115: DESCRIPCION | J115: CATEGORÍA | K115: SUB CATEGORIA | L115: EQUILIBRAR
L116: =IF(ISERROR(OFFSET(L116,-1,0,1,1)+D116-E116),D116-E116,OFFSET(L116,-1,0,1,1)+D116-E116) -> 0
L117: =IF(ISERROR(OFFSET(L117,-1,0,1,1)+D117-E117),D117-E117,OFFSET(L117,-1,0,1,1)+D117-E117) -> 0
L118: =IF(ISERROR(OFFSET(L118,-1,0,1,1)+D118-E118),D118-E118,OFFSET(L118,-1,0,1,1)+D118-E118) -> 0
L119: =IF(ISERROR(OFFSET(L119,-1,0,1,1)+D119-E119),D119-E119,OFFSET(L119,-1,0,1,1)+D119-E119) -> 0
L120: =IF(ISERROR(OFFSET(L120,-1,0,1,1)+D120-E120),D120-E120,OFFSET(L120,-1,0,1,1)+D120-E120) -> 0
L121: =IF(ISERROR(OFFSET(L121,-1,0,1,1)+D121-E121),D121-E121,OFFSET(L121,-1,0,1,1)+D121-E121) -> 0
L122: =IF(ISERROR(OFFSET(L122,-1,0,1,1)+D122-E122),D122-E122,OFFSET(L122,-1,0,1,1)+D122-E122) -> 0
L123: =IF(ISERROR(OFFSET(L123,-1,0,1,1)+D123-E123),D123-E123,OFFSET(L123,-1,0,1,1)+D123-E123) -> 0
L124: =IF(ISERROR(OFFSET(L124,-1,0,1,1)+D124-E124),D124-E124,OFFSET(L124,-1,0,1,1)+D124-E124) -> 0
L125: =IF(ISERROR(OFFSET(L125,-1,0,1,1)+D125-E125),D125-E125,OFFSET(L125,-1,0,1,1)+D125-E125) -> 0
L126: =IF(ISERROR(OFFSET(L126,-1,0,1,1)+D126-E126),D126-E126,OFFSET(L126,-1,0,1,1)+D126-E126) -> 0
L127: =IF(ISERROR(OFFSET(L127,-1,0,1,1)+D127-E127),D127-E127,OFFSET(L127,-1,0,1,1)+D127-E127) -> 0
... L149: =IF(ISERROR(OFFSET(L149,-1,0,1,1)+D149-E149),D149-E149,OFFSET(L149,-1,0,1,1)+D149-E149) -> 0
D150: =SUBTOTAL(109,FebEst2024[INGRESO]) -> 0 | E150: =SUBTOTAL(109,FebEst2024[EGRESO]) -> 0
B152: MARZO 2025
B153: CUENTA | C153: FECHA | D153: INGRESO | E153: EGRESO | F153: BENEFICIARIO/PROVEEDOR | G153: NO. FACTURA | H153: NO. PROYECTO | I153: DESCRIPCION | J153: CATEGORÍA | K153: SUB CATEGORIA | L153: EQUILIBRAR
...
